Workbook
Name ActualNumberOfPayments: IFERROR(IF([0]!LoanIsGood,IF([0]!PaymentsPerYear=1,1,MATCH(0.01,Copy1!End_Bal,-1)+1)),"")
Name ActualNumberOfPayments: IFERROR(IF([0]!LoanIsGood,IF([0]!PaymentsPerYear=1,1,MATCH(0.01,FV_April25!End_Bal,-1)+1)),"")
Name ActualNumberOfPayments: IFERROR(IF([0]!LoanIsGood,IF([0]!PaymentsPerYear=1,1,MATCH(0.01,FV_August25!End_Bal,-1)+1)),"")
Name ActualNumberOfPayments: IFERROR(IF([0]!LoanIsGood,IF([0]!PaymentsPerYear=1,1,MATCH(0.01,FV_Dec25!End_Bal,-1)+1)),"")
Name ActualNumberOfPayments: IFERROR(IF([0]!LoanIsGood,IF([0]!PaymentsPerYear=1,1,MATCH(0.01,FV_Feb26!End_Bal,-1)+1)),"")
Name ActualNumberOfPayments: IFERROR(IF([0]!LoanIsGood,IF([0]!PaymentsPerYear=1,1,MATCH(0.01,FV_Jan26!End_Bal,-1)+1)),"")
Name ActualNumberOfPayments: IFERROR(IF([0]!LoanIsGood,IF([0]!PaymentsPerYear=1,1,MATCH(0.01,'FV_July25 '!End_Bal,-1)+1)),"")
Name ActualNumberOfPayments: IFERROR(IF([0]!LoanIsGood,IF([0]!PaymentsPerYear=1,1,MATCH(0.01,FV_July25TEST!End_Bal,-1)+1)),"")
Name ActualNumberOfPayments: IFERROR(IF([0]!LoanIsGood,IF([0]!PaymentsPerYear=1,1,MATCH(0.01,FV_June25!End_Bal,-1)+1)),"")
Name ActualNumberOfPayments: IFERROR(IF([0]!LoanIsGood,IF([0]!PaymentsPerYear=1,1,MATCH(0.01,FV_Mar26!End_Bal,-1)+1)),"")
Name ActualNumberOfPayments: IFERROR(IF([0]!LoanIsGood,IF([0]!PaymentsPerYear=1,1,MATCH(0.01,FV_May25!End_Bal,-1)+1)),"")
Name ActualNumberOfPayments: IFERROR(IF([0]!LoanIsGood,IF([0]!PaymentsPerYear=1,1,MATCH(0.01,FV_Nov25!End_Bal,-1)+1)),"")
Name ActualNumberOfPayments: IFERROR(IF([0]!LoanIsGood,IF([0]!PaymentsPerYear=1,1,MATCH(0.01,FV_October25!End_Bal,-1)+1)),"")
Name ActualNumberOfPayments: IFERROR(IF([0]!LoanIsGood,IF([0]!PaymentsPerYear=1,1,MATCH(0.01,FV_PLANNING!End_Bal,-1)+1)),"")
Name ActualNumberOfPayments: IFERROR(IF([0]!LoanIsGood,IF([0]!PaymentsPerYear=1,1,MATCH(0.01,FV_PLANNING2!End_Bal,-1)+1)),"")
Name ActualNumberOfPayments: IFERROR(IF([0]!LoanIsGood,IF([0]!PaymentsPerYear=1,1,MATCH(0.01,FV_Play!End_Bal,-1)+1)),"")
Name ActualNumberOfPayments: IFERROR(IF([0]!LoanIsGood,IF([0]!PaymentsPerYear=1,1,MATCH(0.01,FV_September25!End_Bal,-1)+1)),"")
Name ActualNumberOfPayments: IFERROR(IF([0]!LoanIsGood,IF([0]!PaymentsPerYear=1,1,MATCH(0.01,HouseView!End_Bal,-1)+1)),"")
Name ActualNumberOfPayments: IFERROR(IF(LoanIsGood,IF(PaymentsPerYear=1,1,MATCH(0.01,End_Bal,-1)+1)),"")
Name ActualNumberOfPayments: IFERROR(IF([0]!LoanIsGood,IF([0]!PaymentsPerYear=1,1,MATCH(0.01,Newhouse!End_Bal,-1)+1)),"")
Name ActualNumberOfPayments: IFERROR(IF([0]!LoanIsGood,IF([0]!PaymentsPerYear=1,1,MATCH(0.01,PayAsh!End_Bal,-1)+1)),"")
Name ActualNumberOfPayments: IFERROR(IF([0]!LoanIsGood,IF([0]!PaymentsPerYear=1,1,MATCH(0.01,[0]!End_Bal,-1)+1)),"")
Name ActualNumberOfPayments: IFERROR(IF([0]!LoanIsGood,IF([0]!PaymentsPerYear=1,1,MATCH(0.01,T!End_Bal,-1)+1)),"")
Name ActualNumberOfPayments: IFERROR(IF([0]!LoanIsGood,IF([0]!PaymentsPerYear=1,1,MATCH(0.01,'T2'!End_Bal,-1)+1)),"")
Name ActualNumberOfPayments: IFERROR(IF(LoanIsGood,IF(PaymentsPerYear=1,1,MATCH(0.01,End_Bal,-1)+1)),"")
Name ColumnTitle1: #REF!
Name ColumnTitle1: #REF!
Name ColumnTitle1: #REF!
Name ColumnTitle1: #REF!
Name ColumnTitle1: #REF!
Name ColumnTitle1: #REF!
Name ColumnTitle1: #REF!
Name ColumnTitle1: #REF!
Name ColumnTitle1: #REF!
Name ColumnTitle1: #REF!
Name ColumnTitle1: #REF!
Name ColumnTitle1: #REF!
Name ColumnTitle1: #REF!
Name ColumnTitle1: #REF!
Name ColumnTitle1: #REF!
Name ColumnTitle1: #REF!
Name ColumnTitle1: #REF!
Name ColumnTitle1: #REF!
Name ColumnTitle1: #REF!
Name ColumnTitle1: #REF!
Name ColumnTitle1: #REF!
Name ColumnTitle1: #REF!
Name ColumnTitle1: #REF!
Name End_Bal: #REF!
Name End_Bal: #REF!
Name End_Bal: #REF!
Name End_Bal: #REF!
Name End_Bal: #REF!
Name End_Bal: #REF!
Name End_Bal: #REF!
Name End_Bal: #REF!
Name End_Bal: #REF!
Name End_Bal: #REF!
Name End_Bal: #REF!
Name End_Bal: #REF!

Sheet Monthly Expenses Budget
B1: MONTHLY BUDGET TRACKER | P1: MONTHLY BUDGET TRACKER
C3: Monthly Target / Budget | E3: ACTUALS - 2024 | P3: ACTUALS - 2025
E4: 45292 | F4: 45323 | G4: 45352 | H4: 45383 | I4: 45413 | J4: 45444 | K4: 45474 | L4: 45505 | M4: 45536 | N4: 45566 | O4: 45597 | P4: 45627 | Q4: 45658 | R4: 45689 | S4: 45717 | T4: 45748 | U4: 45778 | V4: 45809 | W4: 45839 | X4: 45870 | Y4: 45901 | Z4: 45931 | AA4: 45962 | AB4: 45992
B5: Home and other Fixed Expenses | C5: =SUM(C6:C10) -> 0 | E5: =SUM(E6:E10) -> 0 | F5: =SUM(F6:F10) -> 0 | G5: =SUM(G6:G10) -> 0 | H5: =SUM(H6:H10) -> 0 | I5: =SUM(I6:I10) -> 0 | J5: =SUM(J6:J10) -> 0 | K5: =SUM(K6:K10) -> 0 | L5: =SUM(L6:L10) -> 0 | ... AB5: =SUM(AB6:AB10) -> 0
B6: Home Loan / Mortgage | E6: =$C$5 -> 0 | F6: =$C$5 -> 0 | G6: =$C$5 -> 0 | H6: =$C$5 -> 0 | I6: =$C$5 -> 0 | J6: =$C$5 -> 0 | K6: =$C$5 -> 0 | L6: =$C$5 -> 0 | ... AB6: =$C$5 -> 0
B7: Personal Loans
B8: Credit Card Repayments
B9: Car Lease
B10: Rent (cost per month)
B12: Essentials | C12: =SUM(C13:C20) -> 875.7325 | E12: =SUM(E13:E20) -> 957.21583 | F12: =SUM(F13:F20) -> 957.21583 | G12: =SUM(G13:G20) -> 937.80583 | H12: =SUM(H13:H20) -> 842.98917 | I12: =SUM(I13:I20) -> 943.55583 | J12: =SUM(J13:J20) -> 943.55583 | K12: =SUM(K13:K20) -> 1010.7658 | L12: =SUM(L13:L20) -> 893.19917 | ... AB12: =SUM(AB13:AB20) -> 875.7325
B13: Electricity | C13: 116.66667 | E13: 198.15 | F13: 198.15 | G13: 198.15 | H13: 116.66667 | I13: 217.23333 | J13: 217.23333 | K13: 217.23333 | L13: 99.666667 | M13: 99.666667 | N13: 99.666667 | O13: 274.33333 | P13: 274.33333 | Q13: 274.33333 | R13: 116.66667 | S13: 116.66667 | T13: 116.66667 | U13: 116.66667 | V13: 116.66667 | W13: 116.66667 | X13: 116.66667 | Y13: 116.66667 | Z13: 116.66667 | AA13: 116.66667 | AB13: 116.66667
B14: Gas | C14: 41.666667 | E14: 41.666667 | F14: 41.666667 | G14: 41.666667 | H14: 41.666667 | I14: 41.666667 | J14: 41.666667 | K14: 41.666667 | L14: 41.666667 | M14: 41.666667 | N14: 41.666667 | O14: 41.666667 | P14: 41.666667 | Q14: 41.666667 | R14: 41.666667 | S14: 41.666667 | T14: 41.666667 | U14: 41.666667 | V14: 41.666667 | W14: 41.666667 | X14: 41.666667 | Y14: 41.666667 | Z14: 41.666667 | AA14: 41.666667 | AB14: 41.666667
B15: Water | C15: 170 | E15: 170 | F15: 170 | G15: 150.59 | H15: 137.25667 | I15: 137.25667 | J15: 137.25667 | K15: 154.46667 | L15: 154.46667 | M15: 154.46667 | N15: 160 | O15: 160 | P15: 160 | Q15: 170 | R15: 170 | S15: 170 | T15: 170 | U15: 170 | V15: 170 | W15: 170 | X15: 170 | Y15: 170 | Z15: 170 | AA15: 170 | AB15: 170
B16: Council | C16: 172 | E16: 172 | F16: 172 | G16: 172 | H16: 172 | I16: 172 | J16: 172 | K16: 172 | L16: 172 | M16: 172 | N16: 172 | O16: 172 | P16: 172 | Q16: 172 | R16: 172 | S16: 172 | T16: 172 | U16: 172 | V16: 172 | W16: 172 | X16: 172 | Y16: 172 | Z16: 172 | AA16: 172 | AB16: 172
B17: Waterworks Insurance | C17: 375.39917 | E17: 375.39917 | F17: 375.39917 | G17: 375.39917 | H17: 375.39917 | I17: 375.39917 | J17: 375.39917 | K17: 375.39917 | L17: 375.39917 | M17: 375.39917 | N17: 375.39917 | O17: 375.39917 | P17: 375.39917 | Q17: 375.39917 | R17: 375.39917 | S17: 375.39917 | T17: 375.39917 | U17: 375.39917 | V17: 375.39917 | W17: 375.39917 | X17: 375.39917 | Y17: 375.39917 | Z17: 375.39917 | AA17: 375.39917 | AB17: 375.39917
B18: Mobile Phone TF | K18: 50 | L18: 50 | N18: 50 | O18: 65 | P18: 65 | Q18: 65 | R18: 65
B22: Groceries | C22: =SUM(C23:C29) -> 2120 | E22: =SUM(E23:E29) -> 1886.72 | F22: =SUM(F23:F29) -> 1534.94 | G22: =SUM(G23:G29) -> 2427.69 | H22: =SUM(H23:H29) -> 2999.92 | I22: =SUM(I23:I29) -> 1770.63 | J22: =SUM(J23:J29) -> 2257.22 | K22: =SUM(K23:K29) -> 2654.19 | L22: =SUM(L23:L29) -> 2156.84 | ... AB22: =SUM(AB23:AB29) -> 1400
B23: Groceries | C23: 2000 | E23: 1886.72 | F23: 1534.94 | G23: 2427.69 | H23: 2999.92 | I23: 1770.63 | J23: 1923.17 | K23: 2495.2 | L23: 2023.85 | M23: 2271.54 | N23: 2436.52 | O23: 2005.53 | P23: 2384.1 | Q23: 2991.56 | R23: 1400 | S23: 1400 | T23: 1400 | U23: 1400 | V23: 1400 | W23: 1400 | X23: 1400 | Y23: 1400 | Z23: 1400 | AA23: 1400 | AB23: 1400
B24: Nala Food | C24: 120 | J24: 334.05 | K24: 158.99 | L24: 132.99 | M24: 0 | N24: 139.99 | O24: 168.99 | P24: 43.36 | Q24: 129.6
B31: House Maintenance | C31: =SUM(C32:C37) -> 230 | E31: =SUM(E32:E37) -> 51.32 | F31: =SUM(F32:F37) -> 206.19 | G31: =SUM(G32:G37) -> 2419.71 | H31: =SUM(H32:H37) -> 4097.13 | I31: =SUM(I32:I37) -> 87.98 | J31: =SUM(J32:J37) -> 647.35 | K31: =SUM(K32:K37) -> 618.09 | L31: =SUM(L32:L37) -> 367.98 | ... AB31: =SUM(AB32:AB37) -> 30
B32: External | C32: 30 | G32: 374 | H32: 264 | I32: 87.98 | Q32: 1045 | X32: 30 | Y32: 30 | Z32: 30 | AA32: 30 | AB32: 30
B33: Maintenance general | C33: 150 | E33: 51.32 | F33: 206.19 | G33: 2045.71 | H33: 3833.13 | J33: 647.35 | K33: 618.09 | L33: 367.98 | M33: 481.48 | N33: 486.45 | O33: 363.95 | P33: 531.27 | Q33: 515.34
B34: Pool Service / Chemicals | C34: 50
B39: Health | C39: =SUM(C40:C47) -> 1514.7033 | E39: =SUM(E40:E47) -> 2527.1233 | F39: =SUM(F40:F47) -> 1030.8533 | G39: =SUM(G40:G47) -> 894.53333 | H39: =SUM(H40:H47) -> 1075.2533 | I39: =SUM(I40:I47) -> 905.12333 | J39: =SUM(J40:J47) -> 2110.2633 | K39: =SUM(K40:K47) -> 1265.8833 | L39: =SUM(L40:L47) -> 1206.9433 | ... AB39: =SUM(AB40:AB47) -> 440.83333
B40: HCF | C40: 402.75 | E40: 402.75 | F40: 402.75 | G40: 402.75 | H40: 414.12 | I40: 414.12 | J40: 414.12 | K40: 414.12 | L40: 414.12 | M40: 414.12 | N40: 414.12 | O40: 414.12 | P40: 414.12 | Q40: 414.12 | R40: 414.12
B41: Pet Insurance | C41: 183.12 | E41: 183.12 | F41: END | K41: 84.71 | L41: 56.44 | M41: 56.44 | N41: 56.44 | O41: 56.44 | P41: 56.44 | Q41: 56.44 | R41: 56.44
B42: Vet Bills/Medicine | C42: 238 | E42: 1353.69 | F42: END | J42: 263.8 | K42: 284.25 | L42: 48.2 | M42: -46.8 | N42: 112 | O42: 0 | P42: 0 | Q42: 0
B43: Medical | C43: 250 | E43: 146.73 | F43: 187.27 | G43: 50.95 | H43: 123.9 | I43: 50.17 | J43: 261.31 | K43: 41.97 | L43: 247.35 | M43: 585.33 | N43: 854.78 | O43: 580 | P43: 304.81 | Q43: 379
B44: Doctor | H44: 96.4 | J44: 730.2 | K44: 0 | L44: 0 | M44: 0 | N44: 250 | O44: 0 | P44: 0 | Q44: 0
B45: Orthodontist | C45: 440.83333 | E45: 440.83333 | F45: 440.83333 | G45: 440.83333 | H45: 440.83333 | I45: 440.83333 | J45: 440.83333 | K45: 440.83333 | L45: 440.83333 | M45: 440.83333 | N45: 440.83333 | O45: 440.83333 | P45: 440.83333 | Q45: 440.83333 | R45: 440.83333 | S45: 440.83333 | T45: 440.83333 | U45: 440.83333 | V45: 440.83333 | W45: 440.83333 | X45: 440.83333 | Y45: 440.83333 | Z45: 440.83333 | AA45: 440.83333 | AB45: 440.83333
B49: Discretionary | C49: =SUM(C50:C56) -> 1100 | E49: =SUM(E50:E56) -> 1625.98 | F49: =SUM(F50:F56) -> 2777.57 | G49: =SUM(G50:G56) -> 1438.42 | H49: =SUM(H50:H56) -> 1147.58 | I49: =SUM(I50:I56) -> 543.06 | J49: =SUM(J50:J56) -> 723.14 | K49: =SUM(K50:K56) -> 1622.83 | L49: =SUM(L50:L56) -> 808.17 | ... AB49: =SUM(AB50:AB56) -> 500
B50: Presents etc | C50: 100 | E50: 942.56 | F50: 155.93 | G50: 730.8 | H50: 435.1 | J50: 0 | K50: 506.67 | L50: 125.62 | M50: 121.96 | N50: 627.41 | O50: 1687.73 | P50: 993.87 | Q50: 24.85 | Z50: 0 | AA50: 0 | AB50: 0
B51: Entertainment | C51: 200 | E51: 99 | F51: 61.51 | G51: 95.7 | H51: 232 | I51: 79 | J51: 0 | K51: 0 | L51: 138 | M51: 0 | N51: 0 | O51: 0 | P51: 119.95 | Q51: 98 | Z51: 300 | AA51: 300 | AB51: 300
B52: Misc /Travel | C52: 200 | E52: 62.12 | F52: 129.1 | G52: 79.9 | I52: 8.85 | J52: 289.21 | K52: 573.09 | L52: 26.5 | M52: 67.27 | N52: 79.72 | O52: 1215.93 | P52: 725.48 | Q52: 221.41
B53: Eating Out | C53: 200 | E53: 264.08 | F53: 299.06 | G53: 121.8 | H53: 385.28 | I53: 371.71 | J53: 327.93 | K53: 283.31 | L53: 354.96 | M53: 740.33 | N53: 538.35 | O53: 716.76 | P53: 343.05 | Q53: 358.05
B54: Personal Care | C54: 200 | E54: 168.22 | F54: 302.81 | G54: 410.22 | H54: 95.2 | I54: 83.5 | J54: 106 | K54: 259.76 | L54: 163.09 | M54: 124 | N54: 231.34 | O54: 327.2 | P54: 207 | Q54: 303.95
B55: Wedding | C55: 200 | E55: 90 | F55: 1829.16 | Z55: 200 | AA55: 200 | AB55: 200
B58: Sports / Activities | C58: =SUM(C59:C62) -> 397.5 | E58: =SUM(E59:E62) -> 630.83333 | F58: =SUM(F59:F62) -> 630.83333 | G58: =SUM(G59:G62) -> 685.83333 | H58: =SUM(H59:H62) -> 713.31667 | I58: =SUM(I59:I62) -> 623.31667 | J58: =SUM(J59:J62) -> 600.31667 | K58: =SUM(K59:K62) -> 448.06333 | L58: =SUM(L59:L62) -> 454.73 | ... AB58: =SUM(AB59:AB62) -> 454.73
B59: Crossfit | C59: 0 | E59: 0 | F59: 0 | G59: 0 | H59: 0 | I59: 0 | J59: 0 | K59: 0 | L59: 0 | M59: 0 | N59: 0 | O59: 0 | P59: 0 | Q59: 0 | R59: 0 | S59: 0 | T59: 0 | U59: 0 | V59: 0 | W59: 0 | X59: 0
B60: Drama | C60: 147.5 | E60: 140.83333 | F60: 140.83333 | G60: 140.83333 | H60: 233.83333 | I60: 140.83333 | J60: 140.83333 | K60: 140.83333 | L60: 147.5 | M60: 147.5 | N60: 147.5 | O60: 147.5 | P60: 147.5 | Q60: 147.5 | R60: 147.5 | S60: 147.5 | T60: 147.5 | U60: 147.5 | V60: 147.5 | W60: 147.5 | X60: 147.5 | Y60: 147.5 | Z60: 147.5 | AA60: 147.5 | AB60: 147.5
B61: Netball | C61: 250 | E61: 250 | F61: 250 | G61: 250 | H61: 270 | I61: 273 | J61: 250 | K61: 250 | L61: 250 | M61: 250 | N61: 250 | O61: 250 | P61: 250 | Q61: 250 | R61: 250 | S61: 250 | T61: 250 | U61: 250 | V61: 250 | W61: 250 | X61: 250 | Y61: 250 | Z61: 250 | AA61: 250 | AB61: 250
B62: Basketball Team | E62: 240 | F62: 240 | G62: 295 | H62: 209.48333 | I62: 209.48333 | J62: 209.48333 | K62: 57.23 | L62: 57.23 | M62: 57.23 | N62: 57.23 | O62: 57.23 | P62: 57.23 | Q62: 57.23 | R62: 57.23 | S62: 57.23 | T62: 57.23 | U62: 57.23 | V62: 57.23 | W62: 57.23 | X62: 57.23 | Y62: 57.23 | Z62: 57.23 | AA62: 57.23 | AB62: 57.23
B64: Other | C64: =SUM(C65:C72) -> 1100 | E64: =SUM(E65:E72) -> 2487.8767 | F64: =SUM(F65:F72) -> 3683.8967 | G64: =SUM(G65:G72) -> 2235.8867 | H64: =SUM(H65:H72) -> 2821.9867 | I64: =SUM(I65:I72) -> 3604.8567 | J64: =SUM(J65:J72) -> 4153.72 | K64: =SUM(K65:K72) -> 1957.21 | L64: =SUM(L65:L72) -> 1531.41 | ... AB64: =SUM(AB65:AB72) -> 569.05
B65: Tonia | C65: 450 | E65: 450 | F65: 450 | G65: 450 | H65: 450 | I65: 450 | J65: 450 | K65: 450 | L65: 450 | M65: 450 | N65: 450 | O65: 450 | P65: 450 | Q65: 450 | R65: 450 | S65: 450 | T65: 450 | U65: 450 | V65: 450 | W65: 450 | X65: 450 | Y65: 450 | Z65: 450 | AA65: 450 | AB65: 450 | AC65: 450 | AD65: 450 | AE65: 450 | AF65: 450 | AG65: 450 | AH65: 450
B66: School fees/ other | C66: 320 | E66: 1165.74 | F66: 257.9 | G66: 525.85 | H66: 1314.9 | I66: 643.55 | J66: 86.6 | K66: 298.6 | L66: 364.84 | M66: 187.8 | N66: 442.68 | O66: 202.14 | P66: 71.99 | Q66: 679.86
B67: Nala | C67: 100 | I67: 886.34 | J67: 2834.05 | K67: 334.21 | L67: 195.16 | M67: 199.32 | N67: 0 | O67: 159.97 | P67: 403.79 | Q67: 97.96
B68: Clothing | C68: 150 | E68: 607.98 | F68: 2721.94 | G68: 975.63 | H68: 738.77 | I68: 1343.42 | J68: 572.07 | K68: 310.7 | L68: 402.36 | M68: 768.07 | N68: 487.48 | O68: 1598.347 | P68: 395.48 | Q68: 592.36
B69: Kids Pocket Money | C69: 80 | E69: 10.1 | G69: 30.35 | H69: 64.26 | I69: 27.49 | J69: 91.95 | K69: 444.65 | L69: 0 | M69: 0 | N69: 46.66 | O69: 201.07 | P69: 285.2 | Q69: 359
B70: KV Insurance | E70: 135.00667 | F70: 135.00667 | G70: 135.00667 | H70: 135.00667 | I70: 135.00667 | J70: END | K70: - | L70: - | M70: - | N70: - | O70: - | P70: - | Q70: - | R70: - | S70: - | T70: -
B71: FL Insurance | E71: 119.05 | F71: 119.05 | G71: 119.05 | H71: 119.05 | I71: 119.05 | J71: 119.05 | K71: 119.05 | L71: 119.05 | M71: 119.05 | N71: 119.05 | O71: 119.05 | P71: 119.05 | Q71: 119.05 | R71: 119.05 | S71: 119.05 | T71: 119.05 | U71: 119.05 | V71: 119.05 | W71: 119.05 | X71: 119.05 | Y71: 119.05 | Z71: 119.05 | AA71: 119.05 | AB71: 119.05 | AC71: 119.05 | AD71: 119.05 | AE71: 119.05 | AF71: 119.05 | AG71: 119.05 | AH71: 119.05
B74: Spending per month | C74: =SUM(C64+C58+C49+C39+C31+C22+C12+C5) -> 7337.9358 | E74: =SUM(E64+E58+E49+E39+E31+E22+E5+E12) -> 10167.069 | F74: =SUM(F64+F58+F49+F39+F31+F22+F5+F12) -> 10821.499 | G74: =SUM(G64+G58+G49+G39+G31+G22+G5+G12) -> 11039.879 | H74: =SUM(H64+H58+H49+H39+H31+H22+H5+H12) -> 13698.176 | I74: =SUM(I64+I58+I49+I39+I31+I22+I5+I12) -> 8478.5225 | J74: =SUM(J64+J58+J49+J39+J31+J22+J5+J12) -> 11435.566 | K74: =SUM(K64+K58+K49+K39+K31+K22+K5+K12) -> 9577.0325 | L74: =SUM(L64+L58+L49+L39+L31+L22+L5+L12) -> 7419.2725 | ... AB74: =SUM(AB64+AB58+AB49+AB39+AB31+AB22+AB5+AB12) -> 4270.3458
C77: Over or Under Budget | E77: =$C$74-E$74 -> -2829.1333 | F77: =$C$74-F$74 -> -3483.5633 | G77: =$C$74-G$74 -> -3701.9433 | H77: =$C$74-H$74 -> -6360.24 | I77: =$C$74-I$74 -> -1140.5867 | J77: =$C$74-J$74 -> -4097.63 | K77: =$C$74-K$74 -> -2239.0967 | L77: =$C$74-L$74 -> -81.336667 | ... AB77: =$C$74-AB$74 -> 3067.59
E80: Actual Spending (average) | G80: =AVERAGE(E74:H74) -> 11431.656
E84: Step 1 | F84: Update Grey Cells in Budget Column (Column C)
E85: Step 2 | F85: At the end of each month, update the corresponding month with actual figures achieved
E86: Step 3 | F86: Adjust budget figures as required

Sheet Property Expenses
B1: Investment Expenses
B4: Forest Lake | C4: Monthly | D4: Yearly | E4: Rental Income Per week
B5: Council Rates | C5: =D5/12 -> 166.66667 | D5: 2000 | E5: 620
B6: Water Rates | C6: =D6/12 -> 83.333333 | D6: 1000
B7: Property management | C7: =D7/12 -> 236.42667 | D7: =E5*52*0.088 -> 2837.12
B8: Building/Landlords Insurance | C8: =D8/12 -> 120.83333 | D8: 1450
B10: Total | C10: =SUM(C5:C9) -> 607.26 | D10: =SUM(D5:D9) -> 7287.12
B12: Strathpine | C12: Monthly | D12: Yearly | E12: Rental Income Per week
B13: Insurance | C13: =D13/12 -> 266.66667 | D13: 3200 | E13: =39156/52 -> 753 | F13: =E13*52/12 -> 3263
B14: Council Rates | C14: =D14/12 -> 345 | D14: 4140 | F14: =F13*12 -> 39156
B15: Property management | C15: =D15/12 -> 100 | D15: 1200 | F15: 39287
B16: Repairs | C16: =D16/12 -> 125 | D16: 1500 | F16: =F15/52 -> 755.51923
B18: Total | C18: =SUM(C13:C17) -> 836.66667 | D18: =SUM(D13:D17) -> 10040
B20: Mount Sheridan | C20: Monthly | D20: Yearly | E20: Rental Income Per week
B21: Council Rates | C21: =D21/12 -> 273.66667 | D21: 3284 | E21: 730
B22: Water Rates | C22: =D22/12 -> 150 | D22: 1800
B23: Property management | C23: =D23/12 -> 278.37333 | D23: =E21*52*0.088 -> 3340.48
B24: Building/Landlords Insurance | C24: =D24/12 -> 120.83333 | D24: 1450
B26: Total | C26: =SUM(C21:C25) -> 822.87333 | D26: =SUM(D21:D25) -> 9874.48
B28: Eimeo | C28: Monthly | D28: Yearly | E28: Rental Income Per week
B29: Council Rates | C29: =D29/12 -> 273.66667 | D29: 3284 | E29: 830
B30: Water Rates | C30: =D30/12 -> 150 | D30: 1800
B31: Property management | C31: =D31/12 -> 316.50667 | D31: =E29*52*0.088 -> 3798.08
B32: Building/Landlords Insurance | C32: =D32/12 -> 120.83333 | D32: 1450
B34: Total | C34: =SUM(C29:C33) -> 861.00667 | D34: =SUM(D29:D33) -> 10332.08

Sheet FV_April25
U1: Property Growth Rate (PY) | V1: 0.07
B2: INCOME STATEMENT | L2: INPUTS!!! Fill out the ORANGE cells ONLY | U2: Stock Growth Rate (PY) | V2: 0.1
U3: Stock contribution per month | V3: 5000 | AI3: NET GROWTH FORECAST
B4: INCOME | C4: PER YEAR | D4: PER MONTH | E4: PASSIVE PM | G4: PASSIVE | H4: PER MONTH | I4: PER YEAR | L4: INCOME | U4: Yearly Prop Purchase Value | V4: 1000000
G5: PASSIVE INCOME | H5: =SUM(E8:E15) -> 2359.6 | I5: =H5*12 -> 28315.2
B6: Salary 1 | C6: =D6*12 -> 240000 | D6: =M6 -> 20000 | L6: Salary 1 (ex tax per month) | M6: 20000 | P6: Date | Q6: Date | R6: Month | S6: Properties | T6: Add Prop | U6: Stocks | V6: Savings | W6: Liabilities | X6: Add Liab | Y6: Total Net Worth
B7: Salary 2 | C7: =D7*12 -> 0 | D7: =M7 -> 0 | L7: Salary 2 (ex tax per month) | P7: 1 | Q7: =TODAY() -> 46091 | R7: =TEXT($Q7,"MMMM")&TEXT($Q7," YYYY") -> March 2026 | S7: =SUM(E44:E46) -> 3550000 | U7: =SUM(E37:E39) -> 792000 | V7: =$E$34 -> 818000 | W7: =$I$50 -> 1488000 | X7: =T7 -> 0 | Y7: =SUM(S7:V7)-W7 -> 3672000
B8: Interest Earned (from savings) | D8: =M8 -> 10 | E8: =D8 -> 10 | L8: Interest from Savings (per month) | M8: 10 | P8: 2 | Q8: =Q7+30 -> 46121 | R8: =TEXT($Q8,"MMMM")&TEXT($Q8," YYYY") -> April 2026 | S8: =($V$1/12+1)*S7+T7 -> 3570708.3 | U8: =($V$2/12+1)*U7+$V$3 -> 803600 | V8: =V7+$I$56 -> 833021.66 | W8: =W7+X7 -> 1488000 | X8: =T8 -> 0 | Y8: =SUM(S8:V8)-W8 -> 3719330
B9: Dividends | D9: =M9 -> 830 | E9: =D9 -> 830 | L9: Income from Dividends (per month) | M9: 830 | P9: 3 | Q9: =Q8+30 -> 46151 | R9: =TEXT($Q9,"MMMM")&TEXT($Q9," YYYY") -> May 2026 | S9: =($V$1/12+1)*S8+T8 -> 3591537.5 | U9: =($V$2/12+1)*U8+$V$3 -> 815296.67 | V9: =V8+$I$56 -> 848043.33 | W9: =W8+X8 -> 1488000 | X9: =T9 -> 0 | Y9: =SUM(S9:V9)-W9 -> 3766877.5
B10: Other income | D10: =M10 -> 0 | L10: Any other income (per month) | M10: 0 | P10: 4 | Q10: =Q9+30 -> 46181 | R10: =TEXT($Q10,"MMMM")&TEXT($Q10," YYYY") -> June 2026 | S10: =($V$1/12+1)*S9+T9 -> 3612488.1 | U10: =($V$2/12+1)*U9+$V$3 -> 827090.81 | V10: =V9+$I$56 -> 863064.99 | W10: =W9+X9 -> 1488000 | X10: =T10 -> 0 | Y10: =SUM(S10:V10)-W10 -> 3814643.9
P11: 5 | Q11: =Q10+30 -> 46211 | R11: =TEXT($Q11,"MMMM")&TEXT($Q11," YYYY") -> July 2026 | S11: =($V$1/12+1)*S10+T10 -> 3633560.9 | U11: =($V$2/12+1)*U10+$V$3 -> 838983.23 | V11: =V10+$I$56 -> 878086.66 | W11: =W10+X10 -> 1488000 | X11: =T11 -> 0 | Y11: =SUM(S11:V11)-W11 -> 3862630.8
B12: Real Estate / Other income: | P12: 6 | Q12: =Q11+30 -> 46241 | R12: =TEXT($Q12,"MMMM")&TEXT($Q12," YYYY") -> August 2026 | S12: =($V$1/12+1)*S11+T11 -> 3654756.7 | U12: =($V$2/12+1)*U11+$V$3 -> 850974.76 | V12: =V11+$I$56 -> 893108.32 | W12: =W11+X11 -> 1488000 | X12: =T12 -> 0 | Y12: =SUM(S12:V12)-W12 -> 3910839.8
G13: Property Yield | H13: % | P13: 7 | Q13: =Q12+30 -> 46271 | R13: =TEXT($Q13,"MMMM")&TEXT($Q13," YYYY") -> September 2026 | S13: =($V$1/12+1)*S12+T12 -> 3676076.1 | U13: =($V$2/12+1)*U12+$V$3 -> 863066.21 | V13: =V12+$I$56 -> 908129.99 | W13: =W12+X12 -> 1488000 | X13: =T13 -> 0 | Y13: =SUM(S13:V13)-W13 -> 3959272.3
B14: =L14 -> Rental income 1 (per week) | C14: =D14*12 -> 32240 | D14: =M14*52/12 -> 2686.6667 | E14: =D14-D21 -> -18.4 | G14: Investment 1 (rental income) | H14: =C14/E45 -> 0.03224 | L14: Rental income 1 (per week) | M14: 620 | P14: 8 | Q14: =Q13+30 -> 46301 | R14: =TEXT($Q14,"MMMM")&TEXT($Q14," YYYY") -> October 2026 | S14: =($V$1/12+1)*S13+T13 -> 3697519.9 | U14: =($V$2/12+1)*U13+$V$3 -> 875258.43 | V14: =V13+$I$56 -> 923151.65 | W14: =W13+X13 -> 1488000 | X14: =T14 -> 0 | Y14: =SUM(S14:V14)-W14 -> 4007930
B15: =L15 -> Rental income 2 (per week) | C15: =D15*12 -> 28600 | D15: =M15*52/12 -> 2383.3333 | E15: =D15-D22 -> 1538 | G15: Investment 2 (rental income) | H15: =C15/E46 -> 0.044 | L15: Rental income 2 (per week) | M15: 550 | P15: 9 | Q15: =Q14+30 -> 46331 | R15: =TEXT($Q15,"MMMM")&TEXT($Q15," YYYY") -> November 2026 | S15: =($V$1/12+1)*S14+T14 -> 3719088.8 | U15: =($V$2/12+1)*U14+$V$3 -> 887552.25 | V15: =V14+$I$56 -> 938173.31 | W15: =W14+X14 -> 1488000 | X15: =T15 -> 0 | Y15: =SUM(S15:V15)-W15 -> 4056814.3
P16: 10 | Q16: =Q15+30 -> 46361 | R16: =TEXT($Q16,"MMMM")&TEXT($Q16," YYYY") -> December 2026 | S16: =($V$1/12+1)*S15+T15 -> 3740783.5 | U16: =($V$2/12+1)*U15+$V$3 -> 899948.52 | V16: =V15+$I$56 -> 953194.98 | W16: =W15+X15 -> 1488000 | X16: =T16 -> 0 | Y16: =SUM(S16:V16)-W16 -> 4105927
G17: TOTAL INCOME | H17: (per month) | I17: =SUM(D6:D15) -> 25910 | P17: 11 | Q17: =Q16+30 -> 46391 | R17: =TEXT($Q17,"MMMM")&TEXT($Q17," YYYY") -> January 2027 | S17: =($V$1/12+1)*S16+T16 -> 3762604.7 | T17: =$V$4 -> 1000000 | U17: =($V$2/12+1)*U16+$V$3 -> 912448.09 | V17: =V16+$I$56 -> 968216.64 | W17: =W16+X16 -> 1488000 | X17: =T17 -> 1000000 | Y17: =SUM(S17:V17)-W17 -> 5155269.4
B18: EXPENSES | C18: PER YEAR | D18: PER MONTH | L18: EXPENSES | P18: 12 | Q18: =Q17+30 -> 46421 | R18: =TEXT($Q18,"MMMM")&TEXT($Q18," YYYY") -> February 2027 | S18: =($V$1/12+1)*S17+T17 -> 4784553.2 | U18: =($V$2/12+1)*U17+$V$3 -> 925051.82 | V18: =V17+$I$56 -> 983238.31 | W18: =W17+X17 -> 2488000 | X18: =T18 -> 0 | Y18: =SUM(S18:V18)-W18 -> 4204843.4
P19: 13 | Q19: =Q18+30 -> 46451 | R19: =TEXT($Q19,"MMMM")&TEXT($Q19," YYYY") -> March 2027 | S19: =($V$1/12+1)*S18+T18 -> 4812463.1 | U19: =($V$2/12+1)*U18+$V$3 -> 937760.59 | V19: =V18+$I$56 -> 998259.97 | W19: =W18+X18 -> 2488000 | X19: =T19 -> 0 | Y19: =SUM(S19:V19)-W19 -> 4260483.7
B20: Mortgage - Home per month | C20: =D20*12 -> 0 | D20: =M20 -> 0 | L20: HOME Mortgage (P+I) - per month | M20: 0 | P20: 14 | Q20: =Q19+30 -> 46481 | R20: =TEXT($Q20,"MMMM")&TEXT($Q20," YYYY") -> April 2027 | S20: =($V$1/12+1)*S19+T19 -> 4840535.8 | U20: =($V$2/12+1)*U19+$V$3 -> 950575.26 | V20: =V19+$I$56 -> 1013281.6 | W20: =W19+X19 -> 2488000 | X20: =T20 -> 0 | Y20: =SUM(S20:V20)-W20 -> 4316392.7
B21: =L21 -> Interest Forest Lake | C21: =D21*12 -> 32460.8 | D21: =M21*I45/12 -> 2705.0667 | L21: Interest Forest Lake | M21: 0.0634 | P21: 15 | Q21: =Q20+30 -> 46511 | R21: =TEXT($Q21,"MMMM")&TEXT($Q21," YYYY") -> May 2027 | S21: =($V$1/12+1)*S20+T20 -> 4868772.3 | U21: =($V$2/12+1)*U20+$V$3 -> 963496.72 | V21: =V20+$I$56 -> 1028303.3 | W21: =W20+X20 -> 2488000 | X21: =T21 -> 0 | Y21: =SUM(S21:V21)-W21 -> 4372572.3
B22: =L22 -> Interest Strathpine | C22: =D22*12 -> 10144 | D22: =M22*I46/12 -> 845.33333 | G22: CASH FLOW (monthly) | H22: =I17-I28 -> 15021.664 | L22: Interest Strathpine | M22: 0.0634 | P22: 16 | Q22: =Q21+30 -> 46541 | R22: =TEXT($Q22,"MMMM")&TEXT($Q22," YYYY") -> June 2027 | S22: =($V$1/12+1)*S21+T21 -> 4897173.5 | U22: =($V$2/12+1)*U21+$V$3 -> 976525.86 | V22: =V21+$I$56 -> 1043325 | W22: =W21+X21 -> 2488000 | X22: =T22 -> 0 | Y22: =SUM(S22:V22)-W22 -> 4429024.3
B23: LOC | C23: =D23*12 -> 0 | D23: =M23*I47/12 -> 0 | G23: Total Income - Total Expenses | L23: Investment 3, interest rate on debt | M23: 0 | P23: 17 | Q23: =Q22+30 -> 46571 | R23: =TEXT($Q23,"MMMM")&TEXT($Q23," YYYY") -> July 2027 | S23: =($V$1/12+1)*S22+T22 -> 4925740.3 | U23: =($V$2/12+1)*U22+$V$3 -> 989663.58 | V23: =V22+$I$56 -> 1058346.6 | W23: =W22+X22 -> 2488000 | X23: =T23 -> 0 | Y23: =SUM(S23:V23)-W23 -> 4485750.5
P24: 18 | Q24: =Q23+30 -> 46601 | R24: =TEXT($Q24,"MMMM")&TEXT($Q24," YYYY") -> August 2027 | S24: =($V$1/12+1)*S23+T23 -> 4954473.8 | U24: =($V$2/12+1)*U23+$V$3 -> 1002910.8 | V24: =V23+$I$56 -> 1073368.3 | W24: =W23+X23 -> 2488000 | X24: =T24 -> 0 | Y24: =SUM(S24:V24)-W24 -> 4542752.8
B25: Monthly Personal Expenses / Spending | C25: =D25*12 -> 88055.23 | D25: =SUM(M30:M36) -> 7337.9358 | P25: 19 | Q25: =Q24+30 -> 46631 | R25: =TEXT($Q25,"MMMM")&TEXT($Q25," YYYY") -> September 2027 | S25: =($V$1/12+1)*S24+T24 -> 4983374.9 | U25: =($V$2/12+1)*U24+$V$3 -> 1016268.4 | V25: =V24+$I$56 -> 1088390 | W25: =W24+X24 -> 2488000 | X25: =T25 -> 0 | Y25: =SUM(S25:V25)-W25 -> 4600033.2
B26: Rental Payment | C26: =D26*12 -> 0 | D26: ='Monthly Expenses Budget'!C10 -> 0 | L26: Other (Insert any other not covered) | P26: 20 | Q26: =Q25+30 -> 46661 | R26: =TEXT($Q26,"MMMM")&TEXT($Q26," YYYY") -> October 2027 | S26: =($V$1/12+1)*S25+T25 -> 5012444.6 | U26: =($V$2/12+1)*U25+$V$3 -> 1029737.3 | V26: =V25+$I$56 -> 1103411.6 | W26: =W25+X25 -> 2488000 | X26: =T26 -> 0 | Y26: =SUM(S26:V26)-W26 -> 4657593.5
B27: Other | D27: =M26 -> 0 | P27: 21 | Q27: =Q26+30 -> 46691 | R27: =TEXT($Q27,"MMMM")&TEXT($Q27," YYYY") -> October 2027 | S27: =($V$1/12+1)*S26+T26 -> 5041683.8 | U27: =($V$2/12+1)*U26+$V$3 -> 1043318.4 | V27: =V26+$I$56 -> 1118433.3 | W27: =W26+X26 -> 2488000 | X27: =T27 -> 0 | Y27: =SUM(S27:V27)-W27 -> 4715435.5
G28: TOTAL EXPENSES | H28: (per month) | I28: =SUM(D20:D27) -> 10888.336 | L28: From Budget Spreadsheet - DO NOT UPDATE THIS | M28: =SUM(M29:M36) -> 7337.9358 | P28: 22 | Q28: =Q27+30 -> 46721 | R28: =TEXT($Q28,"MMMM")&TEXT($Q28," YYYY") -> November 2027 | S28: =($V$1/12+1)*S27+T27 -> 5071093.6 | T28: =$V$4 -> 1000000 | U28: =($V$2/12+1)*U27+$V$3 -> 1057012.7 | V28: =V27+$I$56 -> 1133454.9 | W28: =W27+X27 -> 2488000 | X28: =T28 -> 1000000 | Y28: =SUM(S28:V28)-W28 -> 5773561.3
L29: ='Monthly Expenses Budget'!B5 -> Home and other Fixed Expenses | M29: ='Monthly Expenses Budget'!C5 -> 0 | P29: 23 | Q29: =Q28+30 -> 46751 | R29: =TEXT($Q29,"MMMM")&TEXT($Q29," YYYY") -> December 2027 | S29: =($V$1/12+1)*S28+T28 -> 6100675 | U29: =($V$2/12+1)*U28+$V$3 -> 1070821.2 | V29: =V28+$I$56 -> 1148476.6 | W29: =W28+X28 -> 3488000 | X29: =T29 -> 0 | Y29: =SUM(S29:V29)-W29 -> 4831972.8
B30: BALANCE SHEET | L30: ='Monthly Expenses Budget'!B12 -> Essentials | M30: ='Monthly Expenses Budget'!C12 -> 875.7325 | P30: 24 | Q30: =Q29+30 -> 46781 | R30: =TEXT($Q30,"MMMM")&TEXT($Q30," YYYY") -> January 2028 | S30: =($V$1/12+1)*S29+T29 -> 6136262.3 | U30: =($V$2/12+1)*U29+$V$3 -> 1084744.7 | V30: =V29+$I$56 -> 1163498.3 | W30: =W29+X29 -> 3488000 | X30: =T30 -> 0 | Y30: =SUM(S30:V30)-W30 -> 4896505.3
L31: ='Monthly Expenses Budget'!B22 -> Groceries | M31: ='Monthly Expenses Budget'!C22 -> 2120 | P31: 25 | Q31: =Q30+30 -> 46811 | R31: =TEXT($Q31,"MMMM")&TEXT($Q31," YYYY") -> February 2028 | S31: =($V$1/12+1)*S30+T30 -> 6172057.2 | U31: =($V$2/12+1)*U30+$V$3 -> 1098784.2 | V31: =V30+$I$56 -> 1178519.9 | W31: =W30+X30 -> 3488000 | X31: =T31 -> 0 | Y31: =SUM(S31:V31)-W31 -> 4961361.3
B32: ASSETS | E32: ASSET VALUE | G32: LIABILITIES (DEBT) | L32: ='Monthly Expenses Budget'!B31 -> House Maintenance | M32: ='Monthly Expenses Budget'!C31 -> 230 | P32: 26 | Q32: =Q31+30 -> 46841 | R32: =TEXT($Q32,"MMMM")&TEXT($Q32," YYYY") -> March 2028 | S32: =($V$1/12+1)*S31+T31 -> 6208060.8 | U32: =($V$2/12+1)*U31+$V$3 -> 1112940.8 | V32: =V31+$I$56 -> 1193541.6 | W32: =W31+X31 -> 3488000 | X32: =T32 -> 0 | Y32: =SUM(S32:V32)-W32 -> 5026543.2
L33: ='Monthly Expenses Budget'!B39 -> Health | M33: ='Monthly Expenses Budget'!C39 -> 1514.7033 | P33: 27 | Q33: =Q32+30 -> 46871 | R33: =TEXT($Q33,"MMMM")&TEXT($Q33," YYYY") -> April 2028 | S33: =($V$1/12+1)*S32+T32 -> 6244274.5 | U33: =($V$2/12+1)*U32+$V$3 -> 1127215.3 | V33: =V32+$I$56 -> 1208563.3 | W33: =W32+X32 -> 3488000 | X33: =T33 -> 0 | Y33: =SUM(S33:V33)-W33 -> 5092053
B34: Savings Account 1 | E34: =M40 -> 818000 | G34: Credit Card 1 (total limit) | I34: 10000 | L34: ='Monthly Expenses Budget'!B49 -> Discretionary | M34: ='Monthly Expenses Budget'!C49 -> 1100 | P34: 28 | Q34: =Q33+30 -> 46901 | R34: =TEXT($Q34,"MMMM")&TEXT($Q34," YYYY") -> May 2028 | S34: =($V$1/12+1)*S33+T33 -> 6280699.5 | U34: =($V$2/12+1)*U33+$V$3 -> 1141608.7 | V34: =V33+$I$56 -> 1223584.9 | W34: =W33+X33 -> 3488000 | X34: =T34 -> 0 | Y34: =SUM(S34:V34)-W34 -> 5157893.1
B35: Savings Account 2 | E35: =M41 -> 0 | G35: Credit Card 2 (total limit) | I35: 2000 | L35: ='Monthly Expenses Budget'!B58 -> Sports / Activities | M35: ='Monthly Expenses Budget'!C58 -> 397.5 | P35: 29 | Q35: =Q34+30 -> 46931 | R35: =TEXT($Q35,"MMMM")&TEXT($Q35," YYYY") -> June 2028 | S35: =($V$1/12+1)*S34+T34 -> 6317336.9 | U35: =($V$2/12+1)*U34+$V$3 -> 1156122.1 | V35: =V34+$I$56 -> 1238606.6 | W35: =W34+X34 -> 3488000 | X35: =T35 -> 0 | Y35: =SUM(S35:V35)-W35 -> 5224065.6
G36: Personal Loans | L36: ='Monthly Expenses Budget'!B64 -> Other | M36: ='Monthly Expenses Budget'!C64 -> 1100 | P36: 30 | Q36: =Q35+30 -> 46961 | R36: =TEXT($Q36,"MMMM")&TEXT($Q36," YYYY") -> July 2028 | S36: =($V$1/12+1)*S35+T35 -> 6354188 | U36: =($V$2/12+1)*U35+$V$3 -> 1170756.5 | V36: =V35+$I$56 -> 1253628.3 | W36: =W35+X35 -> 3488000 | X36: =T36 -> 0 | Y36: =SUM(S36:V36)-W36 -> 5290572.7
B37: Stocks (local) | E37: =M43 -> 183000 | G37: Other Loans | P37: 31 | Q37: =Q36+30 -> 46991 | R37: =TEXT($Q37,"MMMM")&TEXT($Q37," YYYY") -> August 2028 | S37: =($V$1/12+1)*S36+T36 -> 6391254.1 | U37: =($V$2/12+1)*U36+$V$3 -> 1185512.8 | V37: =V36+$I$56 -> 1268649.9 | W37: =W36+X36 -> 3488000 | X37: =T37 -> 0 | Y37: =SUM(S37:V37)-W37 -> 5357416.8
B38: Stocks (offshore) | E38: =M44 -> 194000 | P38: 32 | Q38: =Q37+30 -> 47021 | R38: =TEXT($Q38,"MMMM")&TEXT($Q38," YYYY") -> September 2028 | S38: =($V$1/12+1)*S37+T37 -> 6428536.4 | U38: =($V$2/12+1)*U37+$V$3 -> 1200392.1 | V38: =V37+$I$56 -> 1283671.6 | W38: =W37+X37 -> 3488000 | X38: =T38 -> 0 | Y38: =SUM(S38:V38)-W38 -> 5424600.1
B39: Other stocks | E39: =M45 -> 415000 | L39: ASSETS | P39: 33 | Q39: =Q38+30 -> 47051 | R39: =TEXT($Q39,"MMMM")&TEXT($Q39," YYYY") -> October 2028 | S39: =($V$1/12+1)*S38+T38 -> 6466036.2 | U39: =($V$2/12+1)*U38+$V$3 -> 1215395.3 | V39: =V38+$I$56 -> 1298693.3 | W39: =W38+X38 -> 3488000 | X39: =T39 -> 0 | Y39: =SUM(S39:V39)-W39 -> 5492124.8
L40: Savings (account 1) | M40: 818000 | P40: 34 | Q40: =Q39+30 -> 47081 | R40: =TEXT($Q40,"MMMM")&TEXT($Q40," YYYY") -> November 2028 | S40: =($V$1/12+1)*S39+T39 -> 6503754.8 | T40: =$V$4 -> 1000000 | U40: =($V$2/12+1)*U39+$V$3 -> 1230523.6 | V40: =V39+$I$56 -> 1313714.9 | W40: =W39+X39 -> 3488000 | X40: =T40 -> 1000000 | Y40: =SUM(S40:V40)-W40 -> 6559993.3
B41: Super 1 | E41: =M47 -> 220000 | L41: Savings (account 2) | P41: 35 | Q41: =Q40+30 -> 47111 | R41: =TEXT($Q41,"MMMM")&TEXT($Q41," YYYY") -> December 2028 | S41: =($V$1/12+1)*S40+T40 -> 7541693.3 | U41: =($V$2/12+1)*U40+$V$3 -> 1245778 | V41: =V40+$I$56 -> 1328736.6 | W41: =W40+X40 -> 4488000 | X41: =T41 -> 0 | Y41: =SUM(S41:V41)-W41 -> 5628207.9
B42: Super 2 | E42: =M48 -> 200000 | P42: 36 | Q42: =Q41+30 -> 47141 | R42: =TEXT($Q42,"MMMM")&TEXT($Q42," YYYY") -> January 2029 | S42: =($V$1/12+1)*S41+T41 -> 7585686.5 | U42: =($V$2/12+1)*U41+$V$3 -> 1261159.5 | V42: =V41+$I$56 -> 1343758.2 | W42: =W41+X41 -> 4488000 | X42: =T42 -> 0 | Y42: =SUM(S42:V42)-W42 -> 5702604.2
D43: EQUITY | L43: Stocks / Shares (ASX) | M43: 183000 | P43: 37 | Q43: =Q42+30 -> 47171 | R43: =TEXT($Q43,"MMMM")&TEXT($Q43," YYYY") -> February 2029 | S43: =($V$1/12+1)*S42+T42 -> 7629936.4 | U43: =($V$2/12+1)*U42+$V$3 -> 1276669.1 | V43: =V42+$I$56 -> 1358779.9 | W43: =W42+X42 -> 4488000 | X43: =T43 -> 0 | Y43: =SUM(S43:V43)-W43 -> 5777385.4
B44: Home | D44: =E44-I44 -> 1086000 | E44: =M50 -> 1900000 | G44: Mortgage - Home | I44: =M62 -> 814000 | L44: Stocks / Shares (NASDAQ Other) | M44: 194000 | P44: 38 | Q44: =Q43+30 -> 47201 | R44: =TEXT($Q44,"MMMM")&TEXT($Q44," YYYY") -> March 2029 | S44: =($V$1/12+1)*S43+T43 -> 7674444.3 | U44: =($V$2/12+1)*U43+$V$3 -> 1292308 | V44: =V43+$I$56 -> 1373801.6 | W44: =W43+X43 -> 4488000 | X44: =T44 -> 0 | Y44: =SUM(S44:V44)-W44 -> 5852553.9
B45: =L51 -> Investment 1 - Forest Lake value | D45: =E45-I45 -> 488000 | E45: =M51 -> 1000000 | G45: Investment 1 | I45: =M64 -> 512000 | L45: Other stocks (Crypto etc) | M45: 415000 | P45: 39 | Q45: =Q44+30 -> 47231 | R45: =TEXT($Q45,"MMMM")&TEXT($Q45," YYYY") -> April 2029 | S45: =($V$1/12+1)*S44+T44 -> 7719211.9 | U45: =($V$2/12+1)*U44+$V$3 -> 1308077.3 | V45: =V44+$I$56 -> 1388823.2 | W45: =W44+X44 -> 4488000 | X45: =T45 -> 0 | Y45: =SUM(S45:V45)-W45 -> 5928112.4
B46: =L52 -> Investment 2 - Strathpine value | D46: =E46-I46 -> 490000 | E46: =M52 -> 650000 | G46: Investment 2 | I46: =M65 -> 160000 | P46: 40 | Q46: =Q45+30 -> 47261 | R46: =TEXT($Q46,"MMMM")&TEXT($Q46," YYYY") -> May 2029 | S46: =($V$1/12+1)*S45+T45 -> 7764240.7 | U46: =($V$2/12+1)*U45+$V$3 -> 1323977.9 | V46: =V45+$I$56 -> 1403844.9 | W46: =W45+X45 -> 4488000 | X46: =T46 -> 0 | Y46: =SUM(S46:V46)-W46 -> 6004063.5
B47: LOC | D47: =E47-I47 -> 0 | E47: =M53 -> 0 | G47: LOC | I47: =M66 -> 0 | L47: Super 1 | M47: 220000 | P47: 41 | Q47: =Q46+30 -> 47291 | R47: =TEXT($Q47,"MMMM")&TEXT($Q47," YYYY") -> June 2029 | S47: =($V$1/12+1)*S46+T46 -> 7809532.1 | U47: =($V$2/12+1)*U46+$V$3 -> 1340011.1 | V47: =V46+$I$56 -> 1418866.6 | W47: =W46+X46 -> 4488000 | X47: =T47 -> 0 | Y47: =SUM(S47:V47)-W47 -> 6080409.7
L48: Super 2 | M48: 200000 | P48: 42 | Q48: =Q47+30 -> 47321 | R48: =TEXT($Q48,"MMMM")&TEXT($Q48," YYYY") -> July 2029 | S48: =($V$1/12+1)*S47+T47 -> 7855087.7 | U48: =($V$2/12+1)*U47+$V$3 -> 1356177.8 | V48: =V47+$I$56 -> 1433888.2 | W48: =W47+X47 -> 4488000 | X48: =T48 -> 0 | Y48: =SUM(S48:V48)-W48 -> 6157153.7
B49: TOTAL ASSETS (including Super) | E49: =SUM(E34:E48) -> 5580000 | P49: 43 | Q49: =Q48+30 -> 47351 | R49: =TEXT($Q49,"MMMM")&TEXT($Q49," YYYY") -> August 2029 | S49: =($V$1/12+1)*S48+T48 -> 7900909 | U49: =($V$2/12+1)*U48+$V$3 -> 1372479.3 | V49: =V48+$I$56 -> 1448909.9 | W49: =W48+X48 -> 4488000 | X49: =T49 -> 0 | Y49: =SUM(S49:V49)-W49 -> 6234298.2
B50: TOTAL ASSETS | E50: =SUM(E49-E42-E41) -> 5160000 | G50: TOTAL LIABILITY | I50: =SUM(I35:I49) -> 1488000 | L50: Home Value (estimate) | M50: 1900000 | P50: 44 | Q50: =Q49+30 -> 47381 | R50: =TEXT($Q50,"MMMM")&TEXT($Q50," YYYY") -> September 2029 | S50: =($V$1/12+1)*S49+T49 -> 7946997.6 | U50: =($V$2/12+1)*U49+$V$3 -> 1388916.6 | V50: =V49+$I$56 -> 1463931.6 | W50: =W49+X49 -> 4488000 | X50: =T50 -> 0 | Y50: =SUM(S50:V50)-W50 -> 6311845.8
L51: Investment 1 - Forest Lake value | M51: 1000000 | P51: 45 | Q51: =Q50+30 -> 47411 | R51: =TEXT($Q51,"MMMM")&TEXT($Q51," YYYY") -> October 2029 | S51: =($V$1/12+1)*S50+T50 -> 7993355.1 | U51: =($V$2/12+1)*U50+$V$3 -> 1405490.9 | V51: =V50+$I$56 -> 1478953.2 | W51: =W50+X50 -> 4488000 | X51: =T51 -> 0 | Y51: =SUM(S51:V51)-W51 -> 6389799.3
B52: SUMMARY METRICS | L52: Investment 2 - Strathpine value | M52: 650000 | P52: 46 | Q52: =Q51+30 -> 47441 | R52: =TEXT($Q52,"MMMM")&TEXT($Q52," YYYY") -> November 2029 | S52: =($V$1/12+1)*S51+T51 -> 8039983 | T52: =$V$4 -> 1000000 | U52: =($V$2/12+1)*U51+$V$3 -> 1422203.4 | V52: =V51+$I$56 -> 1493974.9 | W52: =W51+X51 -> 4488000 | X52: =T52 -> 1000000 | Y52: =SUM(S52:V52)-W52 -> 7468161.3
L53: LOC | P53: 47 | Q53: =Q52+30 -> 47471 | R53: =TEXT($Q53,"MMMM")&TEXT($Q53," YYYY") -> December 2029 | S53: =($V$1/12+1)*S52+T52 -> 9086882.9 | U53: =($V$2/12+1)*U52+$V$3 -> 1439055.1 | V53: =V52+$I$56 -> 1508996.6 | W53: =W52+X52 -> 5488000 | X53: =T53 -> 0 | Y53: =SUM(S53:V53)-W53 -> 6546934.5
B54: Overall Net worth | G54: Cashflow | P54: 48 | Q54: =Q53+30 -> 47501 | R54: =TEXT($Q54,"MMMM")&TEXT($Q54," YYYY") -> January 2030 | S54: =($V$1/12+1)*S53+T53 -> 9139889.8 | U54: =($V$2/12+1)*U53+$V$3 -> 1456047.2 | V54: =V53+$I$56 -> 1524018.2 | W54: =W53+X53 -> 5488000 | X54: =T54 -> 0 | Y54: =SUM(S54:V54)-W54 -> 6631955.2
P55: 49 | Q55: =Q54+30 -> 47531 | R55: =TEXT($Q55,"MMMM")&TEXT($Q55," YYYY") -> February 2030 | S55: =($V$1/12+1)*S54+T54 -> 9193205.8 | U55: =($V$2/12+1)*U54+$V$3 -> 1473180.9 | V55: =V54+$I$56 -> 1539039.9 | W55: =W54+X54 -> 5488000 | X55: =T55 -> 0 | Y55: =SUM(S55:V55)-W55 -> 6717426.6
B56: Total Net Worth (ex Super) | D56: =E50-I50 -> 3672000 | G56: CASHFLOW | H56: monthly | I56: =I17-I28 -> 15021.664 | L56: LIABILITIES | P56: 50 | Q56: =Q55+30 -> 47561 | R56: =TEXT($Q56,"MMMM")&TEXT($Q56," YYYY") -> March 2030 | S56: =($V$1/12+1)*S55+T55 -> 9246832.8 | U56: =($V$2/12+1)*U55+$V$3 -> 1490457.4 | V56: =V55+$I$56 -> 1554061.5 | W56: =W55+X55 -> 5488000 | X56: =T56 -> 0 | Y56: =SUM(S56:V56)-W56 -> 6803351.8
L57: Credit Card 1 (total limit) | M57: 2000 | P57: 51 | Q57: =Q56+30 -> 47591 | R57: =TEXT($Q57,"MMMM")&TEXT($Q57," YYYY") -> April 2030 | S57: =($V$1/12+1)*S56+T56 -> 9300772.7 | U57: =($V$2/12+1)*U56+$V$3 -> 1507877.9 | V57: =V56+$I$56 -> 1569083.2 | W57: =W56+X56 -> 5488000 | X57: =T57 -> 0 | Y57: =SUM(S57:V57)-W57 -> 6889733.8
B58: Total Net Worth (incl Super) | D58: =E49-I50 -> 4092000 | G58: Savings Potential | H58: yearly | I58: =I56*12 -> 180259.97 | L58: Credit Card 2 (total limit) | M58: 3000 | P58: 52 | Q58: =Q57+30 -> 47621 | R58: =TEXT($Q58,"MMMM")&TEXT($Q58," YYYY") -> May 2030 | S58: =($V$1/12+1)*S57+T57 -> 9355027.2 | U58: =($V$2/12+1)*U57+$V$3 -> 1525443.5 | V58: =V57+$I$56 -> 1584104.9 | W58: =W57+X57 -> 5488000 | X58: =T58 -> 0 | Y58: =SUM(S58:V58)-W58 -> 6976575.6
L59: Personal Loans | P59: 53 | Q59: =Q58+30 -> 47651 | R59: =TEXT($Q59,"MMMM")&TEXT($Q59," YYYY") -> June 2030 | S59: =($V$1/12+1)*S58+T58 -> 9409598.2 | U59: =($V$2/12+1)*U58+$V$3 -> 1543155.6 | V59: =V58+$I$56 -> 1599126.5 | W59: =W58+X58 -> 5488000 | X59: =T59 -> 0 | Y59: =SUM(S59:V59)-W59 -> 7063880.3
B60: Property Stats | G60: Passive Income | L60: Other Loans | P60: 54 | Q60: =Q59+30 -> 47681 | R60: =TEXT($Q60,"MMMM")&TEXT($Q60," YYYY") -> July 2030 | S60: =($V$1/12+1)*S59+T59 -> 9464487.5 | U60: =($V$2/12+1)*U59+$V$3 -> 1561015.2 | V60: =V59+$I$56 -> 1614148.2 | W60: =W59+X59 -> 5488000 | X60: =T60 -> 0 | Y60: =SUM(S60:V60)-W60 -> 7151650.9
P61: 55 | Q61: =Q60+30 -> 47711 | R61: =TEXT($Q61,"MMMM")&TEXT($Q61," YYYY") -> August 2030 | S61: =($V$1/12+1)*S60+T60 -> 9519697 | U61: =($V$2/12+1)*U60+$V$3 -> 1579023.7 | V61: =V60+$I$56 -> 1629169.9 | W61: =W60+X60 -> 5488000 | X61: =T61 -> 0 | Y61: =SUM(S61:V61)-W61 -> 7239890.5
B62: Total Property Debt | D62: =SUM(I44:I47) -> 1486000 | G62: Passive Income | H62: monthly | I62: =H5 -> 2359.6 | L62: Home - Mortgage | M62: 814000 | P62: 56 | Q62: =Q61+30 -> 47741 | R62: =TEXT($Q62,"MMMM")&TEXT($Q62," YYYY") -> September 2030 | S62: =($V$1/12+1)*S61+T61 -> 9575228.6 | U62: =($V$2/12+1)*U61+$V$3 -> 1597182.2 | V62: =V61+$I$56 -> 1644191.5 | W62: =W61+X61 -> 5488000 | X62: =T62 -> 0 | Y62: =SUM(S62:V62)-W62 -> 7328602.3
P63: 57 | Q63: =Q62+30 -> 47771 | R63: =TEXT($Q63,"MMMM")&TEXT($Q63," YYYY") -> October 2030 | S63: =($V$1/12+1)*S62+T62 -> 9631084.1 | U63: =($V$2/12+1)*U62+$V$3 -> 1615492 | V63: =V62+$I$56 -> 1659213.2 | W63: =W62+X62 -> 5488000 | X63: =T63 -> 0 | Y63: =SUM(S63:V63)-W63 -> 7417789.3
B64: Total Property Assets | D64: =SUM(E44:E47) -> 3550000 | G64: Amount for 100% Passive | H64: monthly | I64: =I28-H5 -> 8528.7358 | L64: Investment 1 - Mortgage | M64: 512000 | P64: 58 | Q64: =Q63+30 -> 47801 | R64: =TEXT($Q64,"MMMM")&TEXT($Q64," YYYY") -> November 2030 | S64: =($V$1/12+1)*S63+T63 -> 9687265.4 | T64: =$V$4 -> 1000000 | U64: =($V$2/12+1)*U63+$V$3 -> 1633954.5 | V64: =V63+$I$56 -> 1674234.9 | W64: =W63+X63 -> 5488000 | X64: =T64 -> 1000000 | Y64: =SUM(S64:V64)-W64 -> 8507454.7
L65: Investment 2 - Mortgage | M65: 160000 | P65: 59 | Q65: =Q64+30 -> 47831 | R65: =TEXT($Q65,"MMMM")&TEXT($Q65," YYYY") -> December 2030 | S65: =($V$1/12+1)*S64+T64 -> 10743774 | U65: =($V$2/12+1)*U64+$V$3 -> 1652570.8 | V65: =V64+$I$56 -> 1689256.5 | W65: =W64+X64 -> 6488000 | X65: =T65 -> 0 | Y65: =SUM(S65:V65)-W65 -> 7597601.7
B66: Total Equity Available | D66: =SUM(D44:D47) -> 2064000 | G66: Capital Required to Invest | I66: =I64*12/0.08 -> 1279310.4 | L66: LOC | P66: 60 | Q66: =Q65+30 -> 47861 | R66: =TEXT($Q66,"MMMM")&TEXT($Q66," YYYY") -> January 2031 | S66: =($V$1/12+1)*S65+T65 -> 10806446 | U66: =($V$2/12+1)*U65+$V$3 -> 1671342.2 | V66: =V65+$I$56 -> 1704278.2 | W66: =W65+X65 -> 6488000 | X66: =T66 -> 0 | Y66: =SUM(S66:V66)-W66 -> 7694066.8
G67: Estimated Capital required (at 8% income) to be financially independent
B68: Current LVR | D68: =D62/D64 -> 0.41859155
G69: Liquidity
B70: Equity available 80% | D70: =(80%-D68)*D64 -> 1354000
G71: Available Cash (including Line of Credit) | I71: =SUM(E34+E35+E47) -> 818000
G72: Stocks currently invested | I72: =SUM(E37:E39) -> 792000
B73: Borrowing Power | G73: Total Liquidity | I73: =SUM(I71:I72) -> 1610000
B75: Bank will lend you | D75: =D78-D62 -> 561204.88 | G75: Emergency Fund
B76: Assumed 3% above loan rate for Assessment Rate
G77: Without Salary - you'll last this many MONTHS | I77: =SUM(E34:E39)/(I28-H5) -> 188.77358
B78: Total Borrowing Capacity | D78: =PV(8%/12,30*12,H22,0)*-1 -> 2047204.9 | G78: Without Salary - you'll last this many YEARS | I78: =SUM(E34:E39)/(I28-H5)/12 -> 15.731132
B79: Assuming no additional income to offset | G79: Every WORKING month buys you this many MONTHS | I79: =H22/(I28-H5) -> 1.7613002

Sheet FV_May25
U1: Property Growth Rate (PY) | V1: 0.07
B2: INCOME STATEMENT | L2: INPUTS!!! Fill out the ORANGE cells ONLY | U2: Stock Growth Rate (PY) | V2: 0.1
U3: Stock contribution per month | V3: 5000 | AI3: NET GROWTH FORECAST
B4: INCOME | C4: PER YEAR | D4: PER MONTH | E4: PASSIVE PM | G4: PASSIVE | H4: PER MONTH | I4: PER YEAR | L4: INCOME | U4: Yearly Prop Purchase Value | V4: 1000000
G5: PASSIVE INCOME | H5: =SUM(E8:E15) -> 2494 | I5: =H5*12 -> 29928
B6: Salary 1 | C6: =D6*12 -> 276000 | D6: =M6 -> 23000 | L6: Salary 1 (ex tax per month) | M6: 23000 | P6: Date | Q6: Date | R6: Month | S6: Properties | T6: Add Prop | U6: Stocks | V6: Savings | W6: Liabilities | X6: Add Liab | Y6: Total Net Worth
B7: Salary 2 | C7: =D7*12 -> 0 | D7: =M7 -> 0 | L7: Salary 2 (ex tax per month) | P7: 1 | Q7: =TODAY() -> 46091 | R7: =TEXT($Q7,"MMMM")&TEXT($Q7," YYYY") -> March 2026 | S7: =SUM(E44:E46) -> 3550000 | U7: =SUM(E37:E39) -> 915000 | V7: =$E$34 -> 818000 | W7: =$I$50 -> 1488000 | X7: =T7 -> 0 | Y7: =SUM(S7:V7)-W7 -> 3795000
B8: Interest Earned (from savings) | D8: =M8 -> 10 | E8: =D8 -> 10 | L8: Interest from Savings (per month) | M8: 10 | P8: 2 | Q8: =Q7+30 -> 46121 | R8: =TEXT($Q8,"MMMM")&TEXT($Q8," YYYY") -> April 2026 | S8: =($V$1/12+1)*S7+T7 -> 3570708.3 | U8: =($V$2/12+1)*U7+$V$3 -> 927625 | V8: =V7+$I$56 -> 836156.06 | W8: =W7+X7 -> 1488000 | X8: =T8 -> 0 | Y8: =SUM(S8:V8)-W8 -> 3846489.4
B9: Dividends | D9: =M9 -> 830 | E9: =D9 -> 830 | L9: Income from Dividends (per month) | M9: 830 | P9: 3 | Q9: =Q8+30 -> 46151 | R9: =TEXT($Q9,"MMMM")&TEXT($Q9," YYYY") -> May 2026 | S9: =($V$1/12+1)*S8+T8 -> 3591537.5 | U9: =($V$2/12+1)*U8+$V$3 -> 940355.21 | V9: =V8+$I$56 -> 854312.13 | W9: =W8+X8 -> 1488000 | X9: =T9 -> 0 | Y9: =SUM(S9:V9)-W9 -> 3898204.8
B10: Other income | D10: =M10 -> 0 | L10: Any other income (per month) | M10: 0 | P10: 4 | Q10: =Q9+30 -> 46181 | R10: =TEXT($Q10,"MMMM")&TEXT($Q10," YYYY") -> June 2026 | S10: =($V$1/12+1)*S9+T9 -> 3612488.1 | U10: =($V$2/12+1)*U9+$V$3 -> 953191.5 | V10: =V9+$I$56 -> 872468.19 | W10: =W9+X9 -> 1488000 | X10: =T10 -> 0 | Y10: =SUM(S10:V10)-W10 -> 3950147.8
P11: 5 | Q11: =Q10+30 -> 46211 | R11: =TEXT($Q11,"MMMM")&TEXT($Q11," YYYY") -> July 2026 | S11: =($V$1/12+1)*S10+T10 -> 3633560.9 | U11: =($V$2/12+1)*U10+$V$3 -> 966134.76 | V11: =V10+$I$56 -> 890624.26 | W11: =W10+X10 -> 1488000 | X11: =T11 -> 0 | Y11: =SUM(S11:V11)-W11 -> 4002320
B12: Real Estate / Other income: | P12: 6 | Q12: =Q11+30 -> 46241 | R12: =TEXT($Q12,"MMMM")&TEXT($Q12," YYYY") -> August 2026 | S12: =($V$1/12+1)*S11+T11 -> 3654756.7 | U12: =($V$2/12+1)*U11+$V$3 -> 979185.89 | V12: =V11+$I$56 -> 908780.32 | W12: =W11+X11 -> 1488000 | X12: =T12 -> 0 | Y12: =SUM(S12:V12)-W12 -> 4054722.9
G13: Property Yield | H13: % | P13: 7 | Q13: =Q12+30 -> 46271 | R13: =TEXT($Q13,"MMMM")&TEXT($Q13," YYYY") -> September 2026 | S13: =($V$1/12+1)*S12+T12 -> 3676076.1 | U13: =($V$2/12+1)*U12+$V$3 -> 992345.77 | V13: =V12+$I$56 -> 926936.39 | W13: =W12+X12 -> 1488000 | X13: =T13 -> 0 | Y13: =SUM(S13:V13)-W13 -> 4107358.3
B14: =L14 -> Rental income 1 (per week) | C14: =D14*12 -> 32240 | D14: =M14*52/12 -> 2686.6667 | E14: =D14-D21 -> 84 | G14: Investment 1 (rental income) | H14: =C14/E45 -> 0.03224 | L14: Rental income 1 (per week) | M14: 620 | P14: 8 | Q14: =Q13+30 -> 46301 | R14: =TEXT($Q14,"MMMM")&TEXT($Q14," YYYY") -> October 2026 | S14: =($V$1/12+1)*S13+T13 -> 3697519.9 | U14: =($V$2/12+1)*U13+$V$3 -> 1005615.3 | V14: =V13+$I$56 -> 945092.45 | W14: =W13+X13 -> 1488000 | X14: =T14 -> 0 | Y14: =SUM(S14:V14)-W14 -> 4160227.7
B15: =L15 -> Rental income 2 (per week) | C15: =D15*12 -> 28600 | D15: =M15*52/12 -> 2383.3333 | E15: =D15-D22 -> 1570 | G15: Investment 2 (rental income) | H15: =C15/E46 -> 0.044 | L15: Rental income 2 (per week) | M15: 550 | P15: 9 | Q15: =Q14+30 -> 46331 | R15: =TEXT($Q15,"MMMM")&TEXT($Q15," YYYY") -> November 2026 | S15: =($V$1/12+1)*S14+T14 -> 3719088.8 | U15: =($V$2/12+1)*U14+$V$3 -> 1018995.4 | V15: =V14+$I$56 -> 963248.51 | W15: =W14+X14 -> 1488000 | X15: =T15 -> 0 | Y15: =SUM(S15:V15)-W15 -> 4213332.7
P16: 10 | Q16: =Q15+30 -> 46361 | R16: =TEXT($Q16,"MMMM")&TEXT($Q16," YYYY") -> December 2026 | S16: =($V$1/12+1)*S15+T15 -> 3740783.5 | U16: =($V$2/12+1)*U15+$V$3 -> 1032487.1 | V16: =V15+$I$56 -> 981404.58 | W16: =W15+X15 -> 1488000 | X16: =T16 -> 0 | Y16: =SUM(S16:V16)-W16 -> 4266675.1
G17: TOTAL INCOME | H17: (per month) | I17: =SUM(D6:D15) -> 28910 | P17: 11 | Q17: =Q16+30 -> 46391 | R17: =TEXT($Q17,"MMMM")&TEXT($Q17," YYYY") -> January 2027 | S17: =($V$1/12+1)*S16+T16 -> 3762604.7 | T17: =$V$4 -> 1000000 | U17: =($V$2/12+1)*U16+$V$3 -> 1046091.1 | V17: =V16+$I$56 -> 999560.64 | W17: =W16+X16 -> 1488000 | X17: =T17 -> 1000000 | Y17: =SUM(S17:V17)-W17 -> 5320256.5
B18: EXPENSES | C18: PER YEAR | D18: PER MONTH | L18: EXPENSES | P18: 12 | Q18: =Q17+30 -> 46421 | R18: =TEXT($Q18,"MMMM")&TEXT($Q18," YYYY") -> February 2027 | S18: =($V$1/12+1)*S17+T17 -> 4784553.2 | U18: =($V$2/12+1)*U17+$V$3 -> 1059808.6 | V18: =V17+$I$56 -> 1017716.7 | W18: =W17+X17 -> 2488000 | X18: =T18 -> 0 | Y18: =SUM(S18:V18)-W18 -> 4374078.5
P19: 13 | Q19: =Q18+30 -> 46451 | R19: =TEXT($Q19,"MMMM")&TEXT($Q19," YYYY") -> March 2027 | S19: =($V$1/12+1)*S18+T18 -> 4812463.1 | U19: =($V$2/12+1)*U18+$V$3 -> 1073640.3 | V19: =V18+$I$56 -> 1035872.8 | W19: =W18+X18 -> 2488000 | X19: =T19 -> 0 | Y19: =SUM(S19:V19)-W19 -> 4433976.2
B20: Mortgage - Home per month | C20: =D20*12 -> 0 | D20: =M20 -> 0 | L20: HOME Mortgage (P+I) - per month | M20: 0 | P20: 14 | Q20: =Q19+30 -> 46481 | R20: =TEXT($Q20,"MMMM")&TEXT($Q20," YYYY") -> April 2027 | S20: =($V$1/12+1)*S19+T19 -> 4840535.8 | U20: =($V$2/12+1)*U19+$V$3 -> 1087587.3 | V20: =V19+$I$56 -> 1054028.8 | W20: =W19+X19 -> 2488000 | X20: =T20 -> 0 | Y20: =SUM(S20:V20)-W20 -> 4494152
B21: =L21 -> Interest Forest Lake | C21: =D21*12 -> 31232 | D21: =M21*I45/12 -> 2602.6667 | L21: Interest Forest Lake | M21: 0.061 | P21: 15 | Q21: =Q20+30 -> 46511 | R21: =TEXT($Q21,"MMMM")&TEXT($Q21," YYYY") -> May 2027 | S21: =($V$1/12+1)*S20+T20 -> 4868772.3 | U21: =($V$2/12+1)*U20+$V$3 -> 1101650.5 | V21: =V20+$I$56 -> 1072184.9 | W21: =W20+X20 -> 2488000 | X21: =T21 -> 0 | Y21: =SUM(S21:V21)-W21 -> 4554607.7
B22: =L22 -> Interest Strathpine | C22: =D22*12 -> 9760 | D22: =M22*I46/12 -> 813.33333 | G22: CASH FLOW (monthly) | H22: =I17-I28 -> 18156.064 | L22: Interest Strathpine | M22: 0.061 | P22: 16 | Q22: =Q21+30 -> 46541 | R22: =TEXT($Q22,"MMMM")&TEXT($Q22," YYYY") -> June 2027 | S22: =($V$1/12+1)*S21+T21 -> 4897173.5 | U22: =($V$2/12+1)*U21+$V$3 -> 1115830.9 | V22: =V21+$I$56 -> 1090341 | W22: =W21+X21 -> 2488000 | X22: =T22 -> 0 | Y22: =SUM(S22:V22)-W22 -> 4615345.4
B23: LOC | C23: =D23*12 -> 0 | D23: =M23*I47/12 -> 0 | G23: Total Income - Total Expenses | L23: Investment 3, interest rate on debt | M23: 0 | P23: 17 | Q23: =Q22+30 -> 46571 | R23: =TEXT($Q23,"MMMM")&TEXT($Q23," YYYY") -> July 2027 | S23: =($V$1/12+1)*S22+T22 -> 4925740.3 | U23: =($V$2/12+1)*U22+$V$3 -> 1130129.5 | V23: =V22+$I$56 -> 1108497 | W23: =W22+X22 -> 2488000 | X23: =T23 -> 0 | Y23: =SUM(S23:V23)-W23 -> 4676366.9
P24: 18 | Q24: =Q23+30 -> 46601 | R24: =TEXT($Q24,"MMMM")&TEXT($Q24," YYYY") -> August 2027 | S24: =($V$1/12+1)*S23+T23 -> 4954473.8 | U24: =($V$2/12+1)*U23+$V$3 -> 1144547.3 | V24: =V23+$I$56 -> 1126653.1 | W24: =W23+X23 -> 2488000 | X24: =T24 -> 0 | Y24: =SUM(S24:V24)-W24 -> 4737674.2
B25: Monthly Personal Expenses / Spending | C25: =D25*12 -> 88055.23 | D25: =SUM(M30:M36) -> 7337.9358 | P25: 19 | Q25: =Q24+30 -> 46631 | R25: =TEXT($Q25,"MMMM")&TEXT($Q25," YYYY") -> September 2027 | S25: =($V$1/12+1)*S24+T24 -> 4983374.9 | U25: =($V$2/12+1)*U24+$V$3 -> 1159085.2 | V25: =V24+$I$56 -> 1144809.2 | W25: =W24+X24 -> 2488000 | X25: =T25 -> 0 | Y25: =SUM(S25:V25)-W25 -> 4799269.2
B26: Rental Payment | C26: =D26*12 -> 0 | D26: ='Monthly Expenses Budget'!C10 -> 0 | L26: Other (Insert any other not covered) | P26: 20 | Q26: =Q25+30 -> 46661 | R26: =TEXT($Q26,"MMMM")&TEXT($Q26," YYYY") -> October 2027 | S26: =($V$1/12+1)*S25+T25 -> 5012444.6 | U26: =($V$2/12+1)*U25+$V$3 -> 1173744.2 | V26: =V25+$I$56 -> 1162965.2 | W26: =W25+X25 -> 2488000 | X26: =T26 -> 0 | Y26: =SUM(S26:V26)-W26 -> 4861154
B27: Other | D27: =M26 -> 0 | P27: 21 | Q27: =Q26+30 -> 46691 | R27: =TEXT($Q27,"MMMM")&TEXT($Q27," YYYY") -> October 2027 | S27: =($V$1/12+1)*S26+T26 -> 5041683.8 | U27: =($V$2/12+1)*U26+$V$3 -> 1188525.4 | V27: =V26+$I$56 -> 1181121.3 | W27: =W26+X26 -> 2488000 | X27: =T27 -> 0 | Y27: =SUM(S27:V27)-W27 -> 4923330.5
G28: TOTAL EXPENSES | H28: (per month) | I28: =SUM(D20:D27) -> 10753.936 | L28: From Budget Spreadsheet - DO NOT UPDATE THIS | M28: =SUM(M29:M36) -> 7337.9358 | P28: 22 | Q28: =Q27+30 -> 46721 | R28: =TEXT($Q28,"MMMM")&TEXT($Q28," YYYY") -> November 2027 | S28: =($V$1/12+1)*S27+T27 -> 5071093.6 | T28: =$V$4 -> 1000000 | U28: =($V$2/12+1)*U27+$V$3 -> 1203429.8 | V28: =V27+$I$56 -> 1199277.3 | W28: =W27+X27 -> 2488000 | X28: =T28 -> 1000000 | Y28: =SUM(S28:V28)-W28 -> 5985800.8
L29: ='Monthly Expenses Budget'!B5 -> Home and other Fixed Expenses | M29: ='Monthly Expenses Budget'!C5 -> 0 | P29: 23 | Q29: =Q28+30 -> 46751 | R29: =TEXT($Q29,"MMMM")&TEXT($Q29," YYYY") -> December 2027 | S29: =($V$1/12+1)*S28+T28 -> 6100675 | U29: =($V$2/12+1)*U28+$V$3 -> 1218458.4 | V29: =V28+$I$56 -> 1217433.4 | W29: =W28+X28 -> 3488000 | X29: =T29 -> 0 | Y29: =SUM(S29:V29)-W29 -> 5048566.8
B30: BALANCE SHEET | L30: ='Monthly Expenses Budget'!B12 -> Essentials | M30: ='Monthly Expenses Budget'!C12 -> 875.7325 | P30: 24 | Q30: =Q29+30 -> 46781 | R30: =TEXT($Q30,"MMMM")&TEXT($Q30," YYYY") -> January 2028 | S30: =($V$1/12+1)*S29+T29 -> 6136262.3 | U30: =($V$2/12+1)*U29+$V$3 -> 1233612.2 | V30: =V29+$I$56 -> 1235589.5 | W30: =W29+X29 -> 3488000 | X30: =T30 -> 0 | Y30: =SUM(S30:V30)-W30 -> 5117464
L31: ='Monthly Expenses Budget'!B22 -> Groceries | M31: ='Monthly Expenses Budget'!C22 -> 2120 | P31: 25 | Q31: =Q30+30 -> 46811 | R31: =TEXT($Q31,"MMMM")&TEXT($Q31," YYYY") -> February 2028 | S31: =($V$1/12+1)*S30+T30 -> 6172057.2 | U31: =($V$2/12+1)*U30+$V$3 -> 1248892.3 | V31: =V30+$I$56 -> 1253745.5 | W31: =W30+X30 -> 3488000 | X31: =T31 -> 0 | Y31: =SUM(S31:V31)-W31 -> 5186695
B32: ASSETS | E32: ASSET VALUE | G32: LIABILITIES (DEBT) | L32: ='Monthly Expenses Budget'!B31 -> House Maintenance | M32: ='Monthly Expenses Budget'!C31 -> 230 | P32: 26 | Q32: =Q31+30 -> 46841 | R32: =TEXT($Q32,"MMMM")&TEXT($Q32," YYYY") -> March 2028 | S32: =($V$1/12+1)*S31+T31 -> 6208060.8 | U32: =($V$2/12+1)*U31+$V$3 -> 1264299.7 | V32: =V31+$I$56 -> 1271901.6 | W32: =W31+X31 -> 3488000 | X32: =T32 -> 0 | Y32: =SUM(S32:V32)-W32 -> 5256262.2
L33: ='Monthly Expenses Budget'!B39 -> Health | M33: ='Monthly Expenses Budget'!C39 -> 1514.7033 | P33: 27 | Q33: =Q32+30 -> 46871 | R33: =TEXT($Q33,"MMMM")&TEXT($Q33," YYYY") -> April 2028 | S33: =($V$1/12+1)*S32+T32 -> 6244274.5 | U33: =($V$2/12+1)*U32+$V$3 -> 1279835.6 | V33: =V32+$I$56 -> 1290057.7 | W33: =W32+X32 -> 3488000 | X33: =T33 -> 0 | Y33: =SUM(S33:V33)-W33 -> 5326167.8
B34: Savings Account 1 | E34: =M40 -> 818000 | G34: Credit Card 1 (total limit) | I34: 10000 | L34: ='Monthly Expenses Budget'!B49 -> Discretionary | M34: ='Monthly Expenses Budget'!C49 -> 1100 | P34: 28 | Q34: =Q33+30 -> 46901 | R34: =TEXT($Q34,"MMMM")&TEXT($Q34," YYYY") -> May 2028 | S34: =($V$1/12+1)*S33+T33 -> 6280699.5 | U34: =($V$2/12+1)*U33+$V$3 -> 1295500.9 | V34: =V33+$I$56 -> 1308213.7 | W34: =W33+X33 -> 3488000 | X34: =T34 -> 0 | Y34: =SUM(S34:V34)-W34 -> 5396414.1
B35: Savings Account 2 | E35: =M41 -> 0 | G35: Credit Card 2 (total limit) | I35: 2000 | L35: ='Monthly Expenses Budget'!B58 -> Sports / Activities | M35: ='Monthly Expenses Budget'!C58 -> 397.5 | P35: 29 | Q35: =Q34+30 -> 46931 | R35: =TEXT($Q35,"MMMM")&TEXT($Q35," YYYY") -> June 2028 | S35: =($V$1/12+1)*S34+T34 -> 6317336.9 | U35: =($V$2/12+1)*U34+$V$3 -> 1311296.7 | V35: =V34+$I$56 -> 1326369.8 | W35: =W34+X34 -> 3488000 | X35: =T35 -> 0 | Y35: =SUM(S35:V35)-W35 -> 5467003.4
G36: Personal Loans | L36: ='Monthly Expenses Budget'!B64 -> Other | M36: ='Monthly Expenses Budget'!C64 -> 1100 | P36: 30 | Q36: =Q35+30 -> 46961 | R36: =TEXT($Q36,"MMMM")&TEXT($Q36," YYYY") -> July 2028 | S36: =($V$1/12+1)*S35+T35 -> 6354188 | U36: =($V$2/12+1)*U35+$V$3 -> 1327224.2 | V36: =V35+$I$56 -> 1344525.9 | W36: =W35+X35 -> 3488000 | X36: =T36 -> 0 | Y36: =SUM(S36:V36)-W36 -> 5537938
B37: Stocks (local) | E37: =M43 -> 183000 | G37: Other Loans | P37: 31 | Q37: =Q36+30 -> 46991 | R37: =TEXT($Q37,"MMMM")&TEXT($Q37," YYYY") -> August 2028 | S37: =($V$1/12+1)*S36+T36 -> 6391254.1 | U37: =($V$2/12+1)*U36+$V$3 -> 1343284.4 | V37: =V36+$I$56 -> 1362681.9 | W37: =W36+X36 -> 3488000 | X37: =T37 -> 0 | Y37: =SUM(S37:V37)-W37 -> 5609220.4
B38: Stocks (offshore) | E38: =M44 -> 202000 | P38: 32 | Q38: =Q37+30 -> 47021 | R38: =TEXT($Q38,"MMMM")&TEXT($Q38," YYYY") -> September 2028 | S38: =($V$1/12+1)*S37+T37 -> 6428536.4 | U38: =($V$2/12+1)*U37+$V$3 -> 1359478.4 | V38: =V37+$I$56 -> 1380838 | W38: =W37+X37 -> 3488000 | X38: =T38 -> 0 | Y38: =SUM(S38:V38)-W38 -> 5680852.8
B39: Other stocks | E39: =M45 -> 530000 | L39: ASSETS | P39: 33 | Q39: =Q38+30 -> 47051 | R39: =TEXT($Q39,"MMMM")&TEXT($Q39," YYYY") -> October 2028 | S39: =($V$1/12+1)*S38+T38 -> 6466036.2 | U39: =($V$2/12+1)*U38+$V$3 -> 1375807.4 | V39: =V38+$I$56 -> 1398994.1 | W39: =W38+X38 -> 3488000 | X39: =T39 -> 0 | Y39: =SUM(S39:V39)-W39 -> 5752837.7
L40: Savings (account 1) | M40: 818000 | P40: 34 | Q40: =Q39+30 -> 47081 | R40: =TEXT($Q40,"MMMM")&TEXT($Q40," YYYY") -> November 2028 | S40: =($V$1/12+1)*S39+T39 -> 6503754.8 | T40: =$V$4 -> 1000000 | U40: =($V$2/12+1)*U39+$V$3 -> 1392272.5 | V40: =V39+$I$56 -> 1417150.1 | W40: =W39+X39 -> 3488000 | X40: =T40 -> 1000000 | Y40: =SUM(S40:V40)-W40 -> 6825177.3
B41: Super 1 | E41: =M47 -> 220000 | L41: Savings (account 2) | P41: 35 | Q41: =Q40+30 -> 47111 | R41: =TEXT($Q41,"MMMM")&TEXT($Q41," YYYY") -> December 2028 | S41: =($V$1/12+1)*S40+T40 -> 7541693.3 | U41: =($V$2/12+1)*U40+$V$3 -> 1408874.7 | V41: =V40+$I$56 -> 1435306.2 | W41: =W40+X40 -> 4488000 | X41: =T41 -> 0 | Y41: =SUM(S41:V41)-W41 -> 5897874.2
B42: Super 2 | E42: =M48 -> 200000 | P42: 36 | Q42: =Q41+30 -> 47141 | R42: =TEXT($Q42,"MMMM")&TEXT($Q42," YYYY") -> January 2029 | S42: =($V$1/12+1)*S41+T41 -> 7585686.5 | U42: =($V$2/12+1)*U41+$V$3 -> 1425615.4 | V42: =V41+$I$56 -> 1453462.2 | W42: =W41+X41 -> 4488000 | X42: =T42 -> 0 | Y42: =SUM(S42:V42)-W42 -> 5976764.1
D43: EQUITY | L43: Stocks / Shares (ASX) | M43: 183000 | P43: 37 | Q43: =Q42+30 -> 47171 | R43: =TEXT($Q43,"MMMM")&TEXT($Q43," YYYY") -> February 2029 | S43: =($V$1/12+1)*S42+T42 -> 7629936.4 | U43: =($V$2/12+1)*U42+$V$3 -> 1442495.5 | V43: =V42+$I$56 -> 1471618.3 | W43: =W42+X42 -> 4488000 | X43: =T43 -> 0 | Y43: =SUM(S43:V43)-W43 -> 6056050.2
B44: Home | D44: =E44-I44 -> 1086000 | E44: =M50 -> 1900000 | G44: Mortgage - Home | I44: =M62 -> 814000 | L44: Stocks / Shares (NASDAQ Other) | M44: 202000 | P44: 38 | Q44: =Q43+30 -> 47201 | R44: =TEXT($Q44,"MMMM")&TEXT($Q44," YYYY") -> March 2029 | S44: =($V$1/12+1)*S43+T43 -> 7674444.3 | U44: =($V$2/12+1)*U43+$V$3 -> 1459516.3 | V44: =V43+$I$56 -> 1489774.4 | W44: =W43+X43 -> 4488000 | X44: =T44 -> 0 | Y44: =SUM(S44:V44)-W44 -> 6135735
B45: =L51 -> Investment 1 - Forest Lake value | D45: =E45-I45 -> 488000 | E45: =M51 -> 1000000 | G45: Investment 1 | I45: =M64 -> 512000 | L45: Other stocks (Crypto etc) | M45: 530000 | P45: 39 | Q45: =Q44+30 -> 47231 | R45: =TEXT($Q45,"MMMM")&TEXT($Q45," YYYY") -> April 2029 | S45: =($V$1/12+1)*S44+T44 -> 7719211.9 | U45: =($V$2/12+1)*U44+$V$3 -> 1476678.9 | V45: =V44+$I$56 -> 1507930.4 | W45: =W44+X44 -> 4488000 | X45: =T45 -> 0 | Y45: =SUM(S45:V45)-W45 -> 6215821.3
B46: =L52 -> Investment 2 - Strathpine value | D46: =E46-I46 -> 490000 | E46: =M52 -> 650000 | G46: Investment 2 | I46: =M65 -> 160000 | P46: 40 | Q46: =Q45+30 -> 47261 | R46: =TEXT($Q46,"MMMM")&TEXT($Q46," YYYY") -> May 2029 | S46: =($V$1/12+1)*S45+T45 -> 7764240.7 | U46: =($V$2/12+1)*U45+$V$3 -> 1493984.6 | V46: =V45+$I$56 -> 1526086.5 | W46: =W45+X45 -> 4488000 | X46: =T46 -> 0 | Y46: =SUM(S46:V46)-W46 -> 6296311.7
B47: LOC | D47: =E47-I47 -> 0 | E47: =M53 -> 0 | G47: LOC | I47: =M66 -> 0 | L47: Super 1 | M47: 220000 | P47: 41 | Q47: =Q46+30 -> 47291 | R47: =TEXT($Q47,"MMMM")&TEXT($Q47," YYYY") -> June 2029 | S47: =($V$1/12+1)*S46+T46 -> 7809532.1 | U47: =($V$2/12+1)*U46+$V$3 -> 1511434.5 | V47: =V46+$I$56 -> 1544242.6 | W47: =W46+X46 -> 4488000 | X47: =T47 -> 0 | Y47: =SUM(S47:V47)-W47 -> 6377209.1
L48: Super 2 | M48: 200000 | P48: 42 | Q48: =Q47+30 -> 47321 | R48: =TEXT($Q48,"MMMM")&TEXT($Q48," YYYY") -> July 2029 | S48: =($V$1/12+1)*S47+T47 -> 7855087.7 | U48: =($V$2/12+1)*U47+$V$3 -> 1529029.7 | V48: =V47+$I$56 -> 1562398.6 | W48: =W47+X47 -> 4488000 | X48: =T48 -> 0 | Y48: =SUM(S48:V48)-W48 -> 6458516
B49: TOTAL ASSETS (including Super) | E49: =SUM(E34:E48) -> 5703000 | P49: 43 | Q49: =Q48+30 -> 47351 | R49: =TEXT($Q49,"MMMM")&TEXT($Q49," YYYY") -> August 2029 | S49: =($V$1/12+1)*S48+T48 -> 7900909 | U49: =($V$2/12+1)*U48+$V$3 -> 1546771.7 | V49: =V48+$I$56 -> 1580554.7 | W49: =W48+X48 -> 4488000 | X49: =T49 -> 0 | Y49: =SUM(S49:V49)-W49 -> 6540235.4
B50: TOTAL ASSETS | E50: =SUM(E49-E42-E41) -> 5283000 | G50: TOTAL LIABILITY | I50: =SUM(I35:I49) -> 1488000 | L50: Home Value (estimate) | M50: 1900000 | P50: 44 | Q50: =Q49+30 -> 47381 | R50: =TEXT($Q50,"MMMM")&TEXT($Q50," YYYY") -> September 2029 | S50: =($V$1/12+1)*S49+T49 -> 7946997.6 | U50: =($V$2/12+1)*U49+$V$3 -> 1564661.4 | V50: =V49+$I$56 -> 1598710.8 | W50: =W49+X49 -> 4488000 | X50: =T50 -> 0 | Y50: =SUM(S50:V50)-W50 -> 6622369.8
L51: Investment 1 - Forest Lake value | M51: 1000000 | P51: 45 | Q51: =Q50+30 -> 47411 | R51: =TEXT($Q51,"MMMM")&TEXT($Q51," YYYY") -> October 2029 | S51: =($V$1/12+1)*S50+T50 -> 7993355.1 | U51: =($V$2/12+1)*U50+$V$3 -> 1582700.3 | V51: =V50+$I$56 -> 1616866.8 | W51: =W50+X50 -> 4488000 | X51: =T51 -> 0 | Y51: =SUM(S51:V51)-W51 -> 6704922.2
B52: SUMMARY METRICS | L52: Investment 2 - Strathpine value | M52: 650000 | P52: 46 | Q52: =Q51+30 -> 47441 | R52: =TEXT($Q52,"MMMM")&TEXT($Q52," YYYY") -> November 2029 | S52: =($V$1/12+1)*S51+T51 -> 8039983 | T52: =$V$4 -> 1000000 | U52: =($V$2/12+1)*U51+$V$3 -> 1600889.4 | V52: =V51+$I$56 -> 1635022.9 | W52: =W51+X51 -> 4488000 | X52: =T52 -> 1000000 | Y52: =SUM(S52:V52)-W52 -> 7787895.4
L53: LOC | P53: 47 | Q53: =Q52+30 -> 47471 | R53: =TEXT($Q53,"MMMM")&TEXT($Q53," YYYY") -> December 2029 | S53: =($V$1/12+1)*S52+T52 -> 9086882.9 | U53: =($V$2/12+1)*U52+$V$3 -> 1619230.2 | V53: =V52+$I$56 -> 1653179 | W53: =W52+X52 -> 5488000 | X53: =T53 -> 0 | Y53: =SUM(S53:V53)-W53 -> 6871292.1
B54: Overall Net worth | G54: Cashflow | P54: 48 | Q54: =Q53+30 -> 47501 | R54: =TEXT($Q54,"MMMM")&TEXT($Q54," YYYY") -> January 2030 | S54: =($V$1/12+1)*S53+T53 -> 9139889.8 | U54: =($V$2/12+1)*U53+$V$3 -> 1637723.8 | V54: =V53+$I$56 -> 1671335 | W54: =W53+X53 -> 5488000 | X54: =T54 -> 0 | Y54: =SUM(S54:V54)-W54 -> 6960948.5
P55: 49 | Q55: =Q54+30 -> 47531 | R55: =TEXT($Q55,"MMMM")&TEXT($Q55," YYYY") -> February 2030 | S55: =($V$1/12+1)*S54+T54 -> 9193205.8 | U55: =($V$2/12+1)*U54+$V$3 -> 1656371.5 | V55: =V54+$I$56 -> 1689491.1 | W55: =W54+X54 -> 5488000 | X55: =T55 -> 0 | Y55: =SUM(S55:V55)-W55 -> 7051068.3
B56: Total Net Worth (ex Super) | D56: =E50-I50 -> 3795000 | G56: CASHFLOW | H56: monthly | I56: =I17-I28 -> 18156.064 | L56: LIABILITIES | P56: 50 | Q56: =Q55+30 -> 47561 | R56: =TEXT($Q56,"MMMM")&TEXT($Q56," YYYY") -> March 2030 | S56: =($V$1/12+1)*S55+T55 -> 9246832.8 | U56: =($V$2/12+1)*U55+$V$3 -> 1675174.6 | V56: =V55+$I$56 -> 1707647.1 | W56: =W55+X55 -> 5488000 | X56: =T56 -> 0 | Y56: =SUM(S56:V56)-W56 -> 7141654.5
L57: Credit Card 1 (total limit) | M57: 2000 | P57: 51 | Q57: =Q56+30 -> 47591 | R57: =TEXT($Q57,"MMMM")&TEXT($Q57," YYYY") -> April 2030 | S57: =($V$1/12+1)*S56+T56 -> 9300772.7 | U57: =($V$2/12+1)*U56+$V$3 -> 1694134.3 | V57: =V56+$I$56 -> 1725803.2 | W57: =W56+X56 -> 5488000 | X57: =T57 -> 0 | Y57: =SUM(S57:V57)-W57 -> 7232710.2
B58: Total Net Worth (incl Super) | D58: =E49-I50 -> 4215000 | G58: Savings Potential | H58: yearly | I58: =I56*12 -> 217872.77 | L58: Credit Card 2 (total limit) | M58: 3000 | P58: 52 | Q58: =Q57+30 -> 47621 | R58: =TEXT($Q58,"MMMM")&TEXT($Q58," YYYY") -> May 2030 | S58: =($V$1/12+1)*S57+T57 -> 9355027.2 | U58: =($V$2/12+1)*U57+$V$3 -> 1713252.1 | V58: =V57+$I$56 -> 1743959.3 | W58: =W57+X57 -> 5488000 | X58: =T58 -> 0 | Y58: =SUM(S58:V58)-W58 -> 7324238.6
L59: Personal Loans | P59: 53 | Q59: =Q58+30 -> 47651 | R59: =TEXT($Q59,"MMMM")&TEXT($Q59," YYYY") -> June 2030 | S59: =($V$1/12+1)*S58+T58 -> 9409598.2 | U59: =($V$2/12+1)*U58+$V$3 -> 1732529.2 | V59: =V58+$I$56 -> 1762115.3 | W59: =W58+X58 -> 5488000 | X59: =T59 -> 0 | Y59: =SUM(S59:V59)-W59 -> 7416242.7
B60: Property Stats | G60: Passive Income | L60: Other Loans | P60: 54 | Q60: =Q59+30 -> 47681 | R60: =TEXT($Q60,"MMMM")&TEXT($Q60," YYYY") -> July 2030 | S60: =($V$1/12+1)*S59+T59 -> 9464487.5 | U60: =($V$2/12+1)*U59+$V$3 -> 1751967 | V60: =V59+$I$56 -> 1780271.4 | W60: =W59+X59 -> 5488000 | X60: =T60 -> 0 | Y60: =SUM(S60:V60)-W60 -> 7508725.9
P61: 55 | Q61: =Q60+30 -> 47711 | R61: =TEXT($Q61,"MMMM")&TEXT($Q61," YYYY") -> August 2030 | S61: =($V$1/12+1)*S60+T60 -> 9519697 | U61: =($V$2/12+1)*U60+$V$3 -> 1771566.7 | V61: =V60+$I$56 -> 1798427.5 | W61: =W60+X60 -> 5488000 | X61: =T61 -> 0 | Y61: =SUM(S61:V61)-W61 -> 7601691.2
B62: Total Property Debt | D62: =SUM(I44:I47) -> 1486000 | G62: Passive Income | H62: monthly | I62: =H5 -> 2494 | L62: Home - Mortgage | M62: 814000 | P62: 56 | Q62: =Q61+30 -> 47741 | R62: =TEXT($Q62,"MMMM")&TEXT($Q62," YYYY") -> September 2030 | S62: =($V$1/12+1)*S61+T61 -> 9575228.6 | U62: =($V$2/12+1)*U61+$V$3 -> 1791329.8 | V62: =V61+$I$56 -> 1816583.5 | W62: =W61+X61 -> 5488000 | X62: =T62 -> 0 | Y62: =SUM(S62:V62)-W62 -> 7695141.9
P63: 57 | Q63: =Q62+30 -> 47771 | R63: =TEXT($Q63,"MMMM")&TEXT($Q63," YYYY") -> October 2030 | S63: =($V$1/12+1)*S62+T62 -> 9631084.1 | U63: =($V$2/12+1)*U62+$V$3 -> 1811257.5 | V63: =V62+$I$56 -> 1834739.6 | W63: =W62+X62 -> 5488000 | X63: =T63 -> 0 | Y63: =SUM(S63:V63)-W63 -> 7789081.2
B64: Total Property Assets | D64: =SUM(E44:E47) -> 3550000 | G64: Amount for 100% Passive | H64: monthly | I64: =I28-H5 -> 8259.9358 | L64: Investment 1 - Mortgage | M64: 512000 | P64: 58 | Q64: =Q63+30 -> 47801 | R64: =TEXT($Q64,"MMMM")&TEXT($Q64," YYYY") -> November 2030 | S64: =($V$1/12+1)*S63+T63 -> 9687265.4 | T64: =$V$4 -> 1000000 | U64: =($V$2/12+1)*U63+$V$3 -> 1831351.3 | V64: =V63+$I$56 -> 1852895.7 | W64: =W63+X63 -> 5488000 | X64: =T64 -> 1000000 | Y64: =SUM(S64:V64)-W64 -> 8883512.4
L65: Investment 2 - Mortgage | M65: 160000 | P65: 59 | Q65: =Q64+30 -> 47831 | R65: =TEXT($Q65,"MMMM")&TEXT($Q65," YYYY") -> December 2030 | S65: =($V$1/12+1)*S64+T64 -> 10743774 | U65: =($V$2/12+1)*U64+$V$3 -> 1851612.6 | V65: =V64+$I$56 -> 1871051.7 | W65: =W64+X64 -> 6488000 | X65: =T65 -> 0 | Y65: =SUM(S65:V65)-W65 -> 7978438.7
B66: Total Equity Available | D66: =SUM(D44:D47) -> 2064000 | G66: Capital Required to Invest | I66: =I64*12/0.08 -> 1238990.4 | L66: LOC | P66: 60 | Q66: =Q65+30 -> 47861 | R66: =TEXT($Q66,"MMMM")&TEXT($Q66," YYYY") -> January 2031 | S66: =($V$1/12+1)*S65+T65 -> 10806446 | U66: =($V$2/12+1)*U65+$V$3 -> 1872042.7 | V66: =V65+$I$56 -> 1889207.8 | W66: =W65+X65 -> 6488000 | X66: =T66 -> 0 | Y66: =SUM(S66:V66)-W66 -> 8079696.9
G67: Estimated Capital required (at 8% income) to be financially independent
B68: Current LVR | D68: =D62/D64 -> 0.41859155
G69: Liquidity
B70: Equity available 80% | D70: =(80%-D68)*D64 -> 1354000
G71: Available Cash (including Line of Credit) | I71: =SUM(E34+E35+E47) -> 818000
G72: Stocks currently invested | I72: =SUM(E37:E39) -> 915000
B73: Borrowing Power | G73: Total Liquidity | I73: =SUM(I71:I72) -> 1733000
B75: Bank will lend you | D75: =D78-D62 -> 988371.86 | G75: Emergency Fund
B76: Assumed 3% above loan rate for Assessment Rate
G77: Without Salary - you'll last this many MONTHS | I77: =SUM(E34:E39)/(I28-H5) -> 209.80793
B78: Total Borrowing Capacity | D78: =PV(8%/12,30*12,H22,0)*-1 -> 2474371.9 | G78: Without Salary - you'll last this many YEARS | I78: =SUM(E34:E39)/(I28-H5)/12 -> 17.483994
B79: Assuming no additional income to offset | G79: Every WORKING month buys you this many MONTHS | I79: =H22/(I28-H5) -> 2.1980878

Sheet FV_June25
U1: Property Growth Rate (PY) | V1: 0.07
B2: INCOME STATEMENT | L2: INPUTS!!! Fill out the ORANGE cells ONLY | U2: Stock Growth Rate (PY) | V2: 0.1
U3: Stock contribution per month | V3: 10000 | AI3: NET GROWTH FORECAST
B4: INCOME | C4: PER YEAR | D4: PER MONTH | E4: PASSIVE PM | G4: PASSIVE | H4: PER MONTH | I4: PER YEAR | L4: INCOME | U4: Yearly Prop Purchase Value | V4: 3000000
G5: PASSIVE INCOME | H5: =SUM(E8:E16) -> 1996.0167 | I5: =H5*12 -> 23952.2
B6: Salary 1 | C6: =D6*12 -> 276000 | D6: =M6 -> 23000 | L6: Salary 1 (ex tax per month) | M6: 23000 | P6: Date | Q6: Date | R6: Month | S6: Properties | T6: Add Prop | U6: Stocks | V6: Savings | W6: Liabilities | X6: Add Liab | Y6: Total Net Worth
B7: Salary 2 | C7: =D7*12 -> 0 | D7: =M7 -> 0 | L7: Salary 2 (ex tax per month) | P7: 1 | Q7: =TODAY() -> 46091 | R7: =TEXT($Q7,"MMMM")&TEXT($Q7," YYYY") -> March 2026 | S7: =SUM(E44:E47) -> 4175000 | U7: =SUM(E37:E39) -> 924000 | V7: =$E$34 -> 106000 | W7: =$I$50 -> 1524000 | X7: =T7 -> 0 | Y7: =SUM(S7:V7)-W7 -> 3681000
B8: Interest Earned (from savings) | D8: =M8 -> 10 | E8: =D8 -> 10 | L8: Interest from Savings (per month) | M8: 10 | P8: 2 | Q8: =Q7+30 -> 46121 | R8: =TEXT($Q8,"MMMM")&TEXT($Q8," YYYY") -> April 2026 | S8: =($V$1/12+1)*S7+T7 -> 4199354.2 | U8: =($V$2/12+1)*U7+$V$3 -> 941700 | V8: =V7+$I$56 -> 123658.08 | W8: =W7+X7 -> 1524000 | X8: =T8 -> 0 | Y8: =SUM(S8:V8)-W8 -> 3740712.2
B9: Dividends | D9: =M9 -> 830 | E9: =D9 -> 830 | L9: Income from Dividends (per month) | M9: 830 | P9: 3 | Q9: =Q8+30 -> 46151 | R9: =TEXT($Q9,"MMMM")&TEXT($Q9," YYYY") -> May 2026 | S9: =($V$1/12+1)*S8+T8 -> 4223850.4 | U9: =($V$2/12+1)*U8+$V$3 -> 959547.5 | V9: =V8+$I$56 -> 141316.16 | W9: =W8+X8 -> 1524000 | X9: =T9 -> 0 | Y9: =SUM(S9:V9)-W9 -> 3800714.1
B10: Other income | D10: =M10 -> 0 | L10: Any other income (per month) | M10: 0 | P10: 4 | Q10: =Q9+30 -> 46181 | R10: =TEXT($Q10,"MMMM")&TEXT($Q10," YYYY") -> June 2026 | S10: =($V$1/12+1)*S9+T9 -> 4248489.5 | U10: =($V$2/12+1)*U9+$V$3 -> 977543.73 | V10: =V9+$I$56 -> 158974.24 | W10: =W9+X9 -> 1524000 | X10: =T10 -> 0 | Y10: =SUM(S10:V10)-W10 -> 3861007.5
P11: 5 | Q11: =Q10+30 -> 46211 | R11: =TEXT($Q11,"MMMM")&TEXT($Q11," YYYY") -> July 2026 | S11: =($V$1/12+1)*S10+T10 -> 4273272.4 | U11: =($V$2/12+1)*U10+$V$3 -> 995689.93 | V11: =V10+$I$56 -> 176632.32 | W11: =W10+X10 -> 1524000 | X11: =T11 -> 0 | Y11: =SUM(S11:V11)-W11 -> 3921594.6
B12: Real Estate / Other income: | G12: Property Yield | H12: % | P12: 6 | Q12: =Q11+30 -> 46241 | R12: =TEXT($Q12,"MMMM")&TEXT($Q12," YYYY") -> August 2026 | S12: =($V$1/12+1)*S11+T11 -> 4298199.8 | U12: =($V$2/12+1)*U11+$V$3 -> 1013987.3 | V12: =V11+$I$56 -> 194290.4 | W12: =W11+X11 -> 1524000 | X12: =T12 -> 0 | Y12: =SUM(S12:V12)-W12 -> 3982477.6
G13: Investment 1 (rental income) | H13: =C14/E45 -> 0.033936842 | P13: 7 | Q13: =Q12+30 -> 46271 | R13: =TEXT($Q13,"MMMM")&TEXT($Q13," YYYY") -> September 2026 | S13: =($V$1/12+1)*S12+T12 -> 4323272.6 | U13: =($V$2/12+1)*U12+$V$3 -> 1032437.2 | V13: =V12+$I$56 -> 211948.49 | W13: =W12+X12 -> 1524000 | X13: =T13 -> 0 | Y13: =SUM(S13:V13)-W13 -> 4043658.4
B14: =L14 -> Rental income Forest Lake (per week) | C14: =D14*12 -> 32240 | D14: =M14*52/12 -> 2686.6667 | E14: =D14-D21 -> 130.93333 | G14: Investment 2 (rental income) | H14: =C15/E46 -> 0.060666667 | L14: Rental income Forest Lake (per week) | M14: 620 | P14: 8 | Q14: =Q13+30 -> 46301 | R14: =TEXT($Q14,"MMMM")&TEXT($Q14," YYYY") -> October 2026 | S14: =($V$1/12+1)*S13+T13 -> 4348491.7 | U14: =($V$2/12+1)*U13+$V$3 -> 1051040.9 | V14: =V13+$I$56 -> 229606.57 | W14: =W13+X13 -> 1524000 | X14: =T14 -> 0 | Y14: =SUM(S14:V14)-W14 -> 4105139.2
B15: =L15 -> Rental income Strathpine (per week) | C15: =D15*12 -> 36400 | D15: =M15*52/12 -> 3033.3333 | E15: =D15-D22 -> 1885.25 | G15: Investment 3 (rental income) | H15: =C16/E47 -> 0.050206897 | L15: Rental income Strathpine (per week) | M15: 700 | P15: 9 | Q15: =Q14+30 -> 46331 | R15: =TEXT($Q15,"MMMM")&TEXT($Q15," YYYY") -> November 2026 | S15: =($V$1/12+1)*S14+T14 -> 4373857.9 | U15: =($V$2/12+1)*U14+$V$3 -> 1069799.6 | V15: =V14+$I$56 -> 247264.65 | W15: =W14+X14 -> 1524000 | X15: =T15 -> 0 | Y15: =SUM(S15:V15)-W15 -> 4166922.1
B16: =L16 -> Rental income Mt Sheridan (per week) | C16: =D16*12 -> 36400 | D16: =M16*52/12 -> 3033.3333 | E16: =D16-D23 -> -860.16667 | L16: Rental income Mt Sheridan (per week) | M16: 700 | P16: 10 | Q16: =Q15+30 -> 46361 | R16: =TEXT($Q16,"MMMM")&TEXT($Q16," YYYY") -> December 2026 | S16: =($V$1/12+1)*S15+T15 -> 4399372.1 | U16: =($V$2/12+1)*U15+$V$3 -> 1088714.6 | V16: =V15+$I$56 -> 264922.73 | W16: =W15+X15 -> 1524000 | X16: =T16 -> 0 | Y16: =SUM(S16:V16)-W16 -> 4229009.4
G17: TOTAL INCOME | H17: (per month) | I17: =SUM(D6:D16) -> 32593.333 | P17: 11 | Q17: =Q16+30 -> 46391 | R17: =TEXT($Q17,"MMMM")&TEXT($Q17," YYYY") -> January 2027 | S17: =($V$1/12+1)*S16+T16 -> 4425035.1 | T17: =$V$4 -> 3000000 | U17: =($V$2/12+1)*U16+$V$3 -> 1107787.2 | V17: =V16+$I$56 -> 282580.81 | W17: =W16+X16 -> 1524000 | X17: =T17 -> 3000000 | Y17: =SUM(S17:V17)-W17 -> 7291403.1
B18: EXPENSES | C18: PER YEAR | D18: PER MONTH | L18: EXPENSES | P18: 12 | Q18: =Q17+30 -> 46421 | R18: =TEXT($Q18,"MMMM")&TEXT($Q18," YYYY") -> February 2027 | S18: =($V$1/12+1)*S17+T17 -> 7450847.8 | U18: =($V$2/12+1)*U17+$V$3 -> 1127018.7 | V18: =V17+$I$56 -> 300238.89 | W18: =W17+X17 -> 4524000 | X18: =T18 -> 0 | Y18: =SUM(S18:V18)-W18 -> 4354105.4
P19: 13 | Q19: =Q18+30 -> 46451 | R19: =TEXT($Q19,"MMMM")&TEXT($Q19," YYYY") -> March 2027 | S19: =($V$1/12+1)*S18+T18 -> 7494311.1 | U19: =($V$2/12+1)*U18+$V$3 -> 1146410.6 | V19: =V18+$I$56 -> 317896.97 | W19: =W18+X18 -> 4524000 | X19: =T19 -> 0 | Y19: =SUM(S19:V19)-W19 -> 4434618.6
B20: Mortgage - Home per month | C20: =D20*12 -> 0 | D20: =M20 -> 0 | L20: HOME Mortgage (P+I) - per month | M20: 0 | P20: 14 | Q20: =Q19+30 -> 46481 | R20: =TEXT($Q20,"MMMM")&TEXT($Q20," YYYY") -> April 2027 | S20: =($V$1/12+1)*S19+T19 -> 7538027.9 | U20: =($V$2/12+1)*U19+$V$3 -> 1165964 | V20: =V19+$I$56 -> 335555.05 | W20: =W19+X19 -> 4524000 | X20: =T20 -> 0 | Y20: =SUM(S20:V20)-W20 -> 4515546.9
B21: =L21 -> Interest Forest Lake | C21: =D21*12 -> 30668.8 | D21: =M21*I45/12 -> 2555.7333 | L21: Interest Forest Lake | M21: 0.0599 | P21: 15 | Q21: =Q20+30 -> 46511 | R21: =TEXT($Q21,"MMMM")&TEXT($Q21," YYYY") -> May 2027 | S21: =($V$1/12+1)*S20+T20 -> 7581999.7 | U21: =($V$2/12+1)*U20+$V$3 -> 1185680.3 | V21: =V20+$I$56 -> 353213.13 | W21: =W20+X20 -> 4524000 | X21: =T21 -> 0 | Y21: =SUM(S21:V21)-W21 -> 4596893.2
B22: =L22 -> Interest Strathpine | C22: =D22*12 -> 13777 | D22: =M22*I46/12 -> 1148.0833 | G22: CASH FLOW (monthly) | H22: =I17-I28 -> 17658.081 | L22: Interest Strathpine | M22: 0.0599 | P22: 16 | Q22: =Q21+30 -> 46541 | R22: =TEXT($Q22,"MMMM")&TEXT($Q22," YYYY") -> June 2027 | S22: =($V$1/12+1)*S21+T21 -> 7626228.1 | U22: =($V$2/12+1)*U21+$V$3 -> 1205561 | V22: =V21+$I$56 -> 370871.21 | W22: =W21+X21 -> 4524000 | X22: =T22 -> 0 | Y22: =SUM(S22:V22)-W22 -> 4678660.3
B23: Interest Mt Sheridan | C23: =D23*12 -> 46722 | D23: =M23*I47/12 -> 3893.5 | G23: Total Income - Total Expenses | L23: Invest Mt Sheridan | M23: 0.0599 | P23: 17 | Q23: =Q22+30 -> 46571 | R23: =TEXT($Q23,"MMMM")&TEXT($Q23," YYYY") -> July 2027 | S23: =($V$1/12+1)*S22+T22 -> 7670714.4 | U23: =($V$2/12+1)*U22+$V$3 -> 1225607.4 | V23: =V22+$I$56 -> 388529.29 | W23: =W22+X22 -> 4524000 | X23: =T23 -> 0 | Y23: =SUM(S23:V23)-W23 -> 4760851
P24: 18 | Q24: =Q23+30 -> 46601 | R24: =TEXT($Q24,"MMMM")&TEXT($Q24," YYYY") -> August 2027 | S24: =($V$1/12+1)*S23+T23 -> 7715460.2 | U24: =($V$2/12+1)*U23+$V$3 -> 1245820.7 | V24: =V23+$I$56 -> 406187.37 | W24: =W23+X23 -> 4524000 | X24: =T24 -> 0 | Y24: =SUM(S24:V24)-W24 -> 4843468.4
B25: Monthly Personal Expenses / Spending | C25: =D25*12 -> 88055.23 | D25: =SUM(M30:M36) -> 7337.9358 | P25: 19 | Q25: =Q24+30 -> 46631 | R25: =TEXT($Q25,"MMMM")&TEXT($Q25," YYYY") -> September 2027 | S25: =($V$1/12+1)*S24+T24 -> 7760467.1 | U25: =($V$2/12+1)*U24+$V$3 -> 1266202.6 | V25: =V24+$I$56 -> 423845.45 | W25: =W24+X24 -> 4524000 | X25: =T25 -> 0 | Y25: =SUM(S25:V25)-W25 -> 4926515.1
B26: Rental Payment | C26: =D26*12 -> 0 | D26: ='Monthly Expenses Budget'!C10 -> 0 | L26: Other (Insert any other not covered) | P26: 20 | Q26: =Q25+30 -> 46661 | R26: =TEXT($Q26,"MMMM")&TEXT($Q26," YYYY") -> October 2027 | S26: =($V$1/12+1)*S25+T25 -> 7805736.5 | U26: =($V$2/12+1)*U25+$V$3 -> 1286754.3 | V26: =V25+$I$56 -> 441503.54 | W26: =W25+X25 -> 4524000 | X26: =T26 -> 0 | Y26: =SUM(S26:V26)-W26 -> 5009994.3
B27: Other | D27: =M26 -> 0 | P27: 21 | Q27: =Q26+30 -> 46691 | R27: =TEXT($Q27,"MMMM")&TEXT($Q27," YYYY") -> October 2027 | S27: =($V$1/12+1)*S26+T26 -> 7851269.9 | U27: =($V$2/12+1)*U26+$V$3 -> 1307477.2 | V27: =V26+$I$56 -> 459161.62 | W27: =W26+X26 -> 4524000 | X27: =T27 -> 0 | Y27: =SUM(S27:V27)-W27 -> 5093908.8
G28: TOTAL EXPENSES | H28: (per month) | I28: =SUM(D20:D27) -> 14935.252 | L28: From Budget Spreadsheet - DO NOT UPDATE THIS | M28: =SUM(M29:M36) -> 7337.9358 | P28: 22 | Q28: =Q27+30 -> 46721 | R28: =TEXT($Q28,"MMMM")&TEXT($Q28," YYYY") -> November 2027 | S28: =($V$1/12+1)*S27+T27 -> 7897069 | T28: =$V$4 -> 3000000 | U28: =($V$2/12+1)*U27+$V$3 -> 1328372.9 | V28: =V27+$I$56 -> 476819.7 | W28: =W27+X27 -> 4524000 | X28: =T28 -> 3000000 | Y28: =SUM(S28:V28)-W28 -> 8178261.6
L29: ='Monthly Expenses Budget'!B5 -> Home and other Fixed Expenses | M29: ='Monthly Expenses Budget'!C5 -> 0 | P29: 23 | Q29: =Q28+30 -> 46751 | R29: =TEXT($Q29,"MMMM")&TEXT($Q29," YYYY") -> December 2027 | S29: =($V$1/12+1)*S28+T28 -> 10943135 | U29: =($V$2/12+1)*U28+$V$3 -> 1349442.6 | V29: =V28+$I$56 -> 494477.78 | W29: =W28+X28 -> 7524000 | X29: =T29 -> 0 | Y29: =SUM(S29:V29)-W29 -> 5263055.7
B30: BALANCE SHEET | L30: ='Monthly Expenses Budget'!B12 -> Essentials | M30: ='Monthly Expenses Budget'!C12 -> 875.7325 | P30: 24 | Q30: =Q29+30 -> 46781 | R30: =TEXT($Q30,"MMMM")&TEXT($Q30," YYYY") -> January 2028 | S30: =($V$1/12+1)*S29+T29 -> 11006970 | U30: =($V$2/12+1)*U29+$V$3 -> 1370688 | V30: =V29+$I$56 -> 512135.86 | W30: =W29+X29 -> 7524000 | X30: =T30 -> 0 | Y30: =SUM(S30:V30)-W30 -> 5365794.1
L31: ='Monthly Expenses Budget'!B22 -> Groceries | M31: ='Monthly Expenses Budget'!C22 -> 2120 | P31: 25 | Q31: =Q30+30 -> 46811 | R31: =TEXT($Q31,"MMMM")&TEXT($Q31," YYYY") -> February 2028 | S31: =($V$1/12+1)*S30+T30 -> 11071178 | U31: =($V$2/12+1)*U30+$V$3 -> 1392110.4 | V31: =V30+$I$56 -> 529793.94 | W31: =W30+X30 -> 7524000 | X31: =T31 -> 0 | Y31: =SUM(S31:V31)-W31 -> 5469081.9
B32: ASSETS | E32: ASSET VALUE | G32: LIABILITIES (DEBT) | L32: ='Monthly Expenses Budget'!B31 -> House Maintenance | M32: ='Monthly Expenses Budget'!C31 -> 230 | P32: 26 | Q32: =Q31+30 -> 46841 | R32: =TEXT($Q32,"MMMM")&TEXT($Q32," YYYY") -> March 2028 | S32: =($V$1/12+1)*S31+T31 -> 11135759 | U32: =($V$2/12+1)*U31+$V$3 -> 1413711.3 | V32: =V31+$I$56 -> 547452.02 | W32: =W31+X31 -> 7524000 | X32: =T32 -> 0 | Y32: =SUM(S32:V32)-W32 -> 5572922.7
L33: ='Monthly Expenses Budget'!B39 -> Health | M33: ='Monthly Expenses Budget'!C39 -> 1514.7033 | P33: 27 | Q33: =Q32+30 -> 46871 | R33: =TEXT($Q33,"MMMM")&TEXT($Q33," YYYY") -> April 2028 | S33: =($V$1/12+1)*S32+T32 -> 11200718 | U33: =($V$2/12+1)*U32+$V$3 -> 1435492.2 | V33: =V32+$I$56 -> 565110.1 | W33: =W32+X32 -> 7524000 | X33: =T33 -> 0 | Y33: =SUM(S33:V33)-W33 -> 5677320.3
B34: Savings Account 1 | E34: =M40 -> 106000 | G34: Credit Card 1 (total limit) | I34: 10000 | L34: ='Monthly Expenses Budget'!B49 -> Discretionary | M34: ='Monthly Expenses Budget'!C49 -> 1100 | P34: 28 | Q34: =Q33+30 -> 46901 | R34: =TEXT($Q34,"MMMM")&TEXT($Q34," YYYY") -> May 2028 | S34: =($V$1/12+1)*S33+T33 -> 11266056 | U34: =($V$2/12+1)*U33+$V$3 -> 1457454.7 | V34: =V33+$I$56 -> 582768.18 | W34: =W33+X33 -> 7524000 | X34: =T34 -> 0 | Y34: =SUM(S34:V34)-W34 -> 5782278.4
B35: Savings Account 2 | E35: =M41 -> 0 | G35: Credit Card 2 (total limit) | I35: 2000 | L35: ='Monthly Expenses Budget'!B58 -> Sports / Activities | M35: ='Monthly Expenses Budget'!C58 -> 397.5 | P35: 29 | Q35: =Q34+30 -> 46931 | R35: =TEXT($Q35,"MMMM")&TEXT($Q35," YYYY") -> June 2028 | S35: =($V$1/12+1)*S34+T34 -> 11331774 | U35: =($V$2/12+1)*U34+$V$3 -> 1479600.1 | V35: =V34+$I$56 -> 600426.26 | W35: =W34+X34 -> 7524000 | X35: =T35 -> 0 | Y35: =SUM(S35:V35)-W35 -> 5887800.6
G36: Personal Loans | L36: ='Monthly Expenses Budget'!B64 -> Other | M36: ='Monthly Expenses Budget'!C64 -> 1100 | P36: 30 | Q36: =Q35+30 -> 46961 | R36: =TEXT($Q36,"MMMM")&TEXT($Q36," YYYY") -> July 2028 | S36: =($V$1/12+1)*S35+T35 -> 11397876 | U36: =($V$2/12+1)*U35+$V$3 -> 1501930.1 | V36: =V35+$I$56 -> 618084.34 | W36: =W35+X35 -> 7524000 | X36: =T36 -> 0 | Y36: =SUM(S36:V36)-W36 -> 5993890.7
B37: Stocks (local) | E37: =M43 -> 190000 | G37: Other Loans | P37: 31 | Q37: =Q36+30 -> 46991 | R37: =TEXT($Q37,"MMMM")&TEXT($Q37," YYYY") -> August 2028 | S37: =($V$1/12+1)*S36+T36 -> 11464364 | U37: =($V$2/12+1)*U36+$V$3 -> 1524446.2 | V37: =V36+$I$56 -> 635742.42 | W37: =W36+X36 -> 7524000 | X37: =T37 -> 0 | Y37: =SUM(S37:V37)-W37 -> 6100552.4
B38: Stocks (offshore) | E38: =M44 -> 218000 | P38: 32 | Q38: =Q37+30 -> 47021 | R38: =TEXT($Q38,"MMMM")&TEXT($Q38," YYYY") -> September 2028 | S38: =($V$1/12+1)*S37+T37 -> 11531239 | U38: =($V$2/12+1)*U37+$V$3 -> 1547149.9 | V38: =V37+$I$56 -> 653400.51 | W38: =W37+X37 -> 7524000 | X38: =T38 -> 0 | Y38: =SUM(S38:V38)-W38 -> 6207789.7
B39: Other stocks | E39: =M45 -> 516000 | L39: ASSETS | P39: 33 | Q39: =Q38+30 -> 47051 | R39: =TEXT($Q39,"MMMM")&TEXT($Q39," YYYY") -> October 2028 | S39: =($V$1/12+1)*S38+T38 -> 11598505 | U39: =($V$2/12+1)*U38+$V$3 -> 1570042.9 | V39: =V38+$I$56 -> 671058.59 | W39: =W38+X38 -> 7524000 | X39: =T39 -> 0 | Y39: =SUM(S39:V39)-W39 -> 6315606.3
L40: Savings (account 1) | M40: 106000 | P40: 34 | Q40: =Q39+30 -> 47081 | R40: =TEXT($Q40,"MMMM")&TEXT($Q40," YYYY") -> November 2028 | S40: =($V$1/12+1)*S39+T39 -> 11666163 | T40: =$V$4 -> 3000000 | U40: =($V$2/12+1)*U39+$V$3 -> 1593126.6 | V40: =V39+$I$56 -> 688716.67 | W40: =W39+X39 -> 7524000 | X40: =T40 -> 3000000 | Y40: =SUM(S40:V40)-W40 -> 9424006
B41: Super 1 | E41: =M47 -> 220000 | L41: Savings (account 2) | P41: 35 | Q41: =Q40+30 -> 47111 | R41: =TEXT($Q41,"MMMM")&TEXT($Q41," YYYY") -> December 2028 | S41: =($V$1/12+1)*S40+T40 -> 14734215 | U41: =($V$2/12+1)*U40+$V$3 -> 1616402.6 | V41: =V40+$I$56 -> 706374.75 | W41: =W40+X40 -> 10524000 | X41: =T41 -> 0 | Y41: =SUM(S41:V41)-W41 -> 6532992.7
B42: Super 2 | E42: =M48 -> 200000 | P42: 36 | Q42: =Q41+30 -> 47141 | R42: =TEXT($Q42,"MMMM")&TEXT($Q42," YYYY") -> January 2029 | S42: =($V$1/12+1)*S41+T41 -> 14820165 | U42: =($V$2/12+1)*U41+$V$3 -> 1639872.6 | V42: =V41+$I$56 -> 724032.83 | W42: =W41+X41 -> 10524000 | X42: =T42 -> 0 | Y42: =SUM(S42:V42)-W42 -> 6660070.4
D43: EQUITY | L43: Stocks / Shares (ASX) | M43: 190000 | P43: 37 | Q43: =Q42+30 -> 47171 | R43: =TEXT($Q43,"MMMM")&TEXT($Q43," YYYY") -> February 2029 | S43: =($V$1/12+1)*S42+T42 -> 14906616 | U43: =($V$2/12+1)*U42+$V$3 -> 1663538.2 | V43: =V42+$I$56 -> 741690.91 | W43: =W42+X42 -> 10524000 | X43: =T43 -> 0 | Y43: =SUM(S43:V43)-W43 -> 6787845.1
B44: Home | D44: =E44-I44 -> 1900000 | E44: =M50 -> 1900000 | G44: Mortgage - Home | I44: =M62 -> 0 | L44: Stocks / Shares (NASDAQ Other) | M44: 218000 | P44: 38 | Q44: =Q43+30 -> 47201 | R44: =TEXT($Q44,"MMMM")&TEXT($Q44," YYYY") -> March 2029 | S44: =($V$1/12+1)*S43+T43 -> 14993571 | U44: =($V$2/12+1)*U43+$V$3 -> 1687401.1 | V44: =V43+$I$56 -> 759348.99 | W44: =W43+X43 -> 10524000 | X44: =T44 -> 0 | Y44: =SUM(S44:V44)-W44 -> 6916321.2
B45: =L51 -> Investment 1 - Forest Lake value | D45: =E45-I45 -> 438000 | E45: =M51 -> 950000 | G45: Investment 1 | I45: =M64 -> 512000 | L45: Other stocks (Crypto etc) | M45: 516000 | P45: 39 | Q45: =Q44+30 -> 47231 | R45: =TEXT($Q45,"MMMM")&TEXT($Q45," YYYY") -> April 2029 | S45: =($V$1/12+1)*S44+T44 -> 15081034 | U45: =($V$2/12+1)*U44+$V$3 -> 1711462.7 | V45: =V44+$I$56 -> 777007.07 | W45: =W44+X44 -> 10524000 | X45: =T45 -> 0 | Y45: =SUM(S45:V45)-W45 -> 7045503.5
B46: =L52 -> Investment 2 - Strathpine value | D46: =E46-I46 -> 370000 | E46: =M52 -> 600000 | G46: Investment 2 | I46: =M65 -> 230000 | P46: 40 | Q46: =Q45+30 -> 47261 | R46: =TEXT($Q46,"MMMM")&TEXT($Q46," YYYY") -> May 2029 | S46: =($V$1/12+1)*S45+T45 -> 15169006 | U46: =($V$2/12+1)*U45+$V$3 -> 1735724.9 | V46: =V45+$I$56 -> 794665.15 | W46: =W45+X45 -> 10524000 | X46: =T46 -> 0 | Y46: =SUM(S46:V46)-W46 -> 7175396.5
B47: =L53 -> Investment 3 - Mt Sheridan value | D47: =E47-I47 -> -55000 | E47: =M53 -> 725000 | G47: Investment 3 | I47: =M66 -> 780000 | L47: Super 1 | M47: 220000 | P47: 41 | Q47: =Q46+30 -> 47291 | R47: =TEXT($Q47,"MMMM")&TEXT($Q47," YYYY") -> June 2029 | S47: =($V$1/12+1)*S46+T46 -> 15257492 | U47: =($V$2/12+1)*U46+$V$3 -> 1760189.3 | V47: =V46+$I$56 -> 812323.23 | W47: =W46+X46 -> 10524000 | X47: =T47 -> 0 | Y47: =SUM(S47:V47)-W47 -> 7306004.8
L48: Super 2 | M48: 200000 | P48: 42 | Q48: =Q47+30 -> 47321 | R48: =TEXT($Q48,"MMMM")&TEXT($Q48," YYYY") -> July 2029 | S48: =($V$1/12+1)*S47+T47 -> 15346494 | U48: =($V$2/12+1)*U47+$V$3 -> 1784857.5 | V48: =V47+$I$56 -> 829981.31 | W48: =W47+X47 -> 10524000 | X48: =T48 -> 0 | Y48: =SUM(S48:V48)-W48 -> 7437333.1
B49: TOTAL ASSETS (including Super) | E49: =SUM(E34:E48) -> 5625000 | P49: 43 | Q49: =Q48+30 -> 47351 | R49: =TEXT($Q49,"MMMM")&TEXT($Q49," YYYY") -> August 2029 | S49: =($V$1/12+1)*S48+T48 -> 15436016 | U49: =($V$2/12+1)*U48+$V$3 -> 1809731.3 | V49: =V48+$I$56 -> 847639.39 | W49: =W48+X48 -> 10524000 | X49: =T49 -> 0 | Y49: =SUM(S49:V49)-W49 -> 7569386.3
B50: TOTAL ASSETS | E50: =SUM(E49-E42-E41) -> 5205000 | G50: TOTAL LIABILITY | I50: =SUM(I35:I49) -> 1524000 | L50: Home Value (estimate) | M50: 1900000 | P50: 44 | Q50: =Q49+30 -> 47381 | R50: =TEXT($Q50,"MMMM")&TEXT($Q50," YYYY") -> September 2029 | S50: =($V$1/12+1)*S49+T49 -> 15526059 | U50: =($V$2/12+1)*U49+$V$3 -> 1834812.4 | V50: =V49+$I$56 -> 865297.48 | W50: =W49+X49 -> 10524000 | X50: =T50 -> 0 | Y50: =SUM(S50:V50)-W50 -> 7702168.8
L51: Investment 1 - Forest Lake value | M51: 950000 | P51: 45 | Q51: =Q50+30 -> 47411 | R51: =TEXT($Q51,"MMMM")&TEXT($Q51," YYYY") -> October 2029 | S51: =($V$1/12+1)*S50+T50 -> 15616628 | U51: =($V$2/12+1)*U50+$V$3 -> 1860102.5 | V51: =V50+$I$56 -> 882955.56 | W51: =W50+X50 -> 10524000 | X51: =T51 -> 0 | Y51: =SUM(S51:V51)-W51 -> 7835685.7
B52: SUMMARY METRICS | L52: Investment 2 - Strathpine value | M52: 600000 | P52: 46 | Q52: =Q51+30 -> 47441 | R52: =TEXT($Q52,"MMMM")&TEXT($Q52," YYYY") -> November 2029 | S52: =($V$1/12+1)*S51+T51 -> 15707725 | T52: =$V$4 -> 3000000 | U52: =($V$2/12+1)*U51+$V$3 -> 1885603.4 | V52: =V51+$I$56 -> 900613.64 | W52: =W51+X51 -> 10524000 | X52: =T52 -> 3000000 | Y52: =SUM(S52:V52)-W52 -> 10969942
L53: Investment 3 - Mt Sheridan value | M53: 725000 | P53: 47 | Q53: =Q52+30 -> 47471 | R53: =TEXT($Q53,"MMMM")&TEXT($Q53," YYYY") -> December 2029 | S53: =($V$1/12+1)*S52+T52 -> 18799353 | U53: =($V$2/12+1)*U52+$V$3 -> 1911316.8 | V53: =V52+$I$56 -> 918271.72 | W53: =W52+X52 -> 13524000 | X53: =T53 -> 0 | Y53: =SUM(S53:V53)-W53 -> 8104941.5
B54: Overall Net worth | G54: Cashflow | P54: 48 | Q54: =Q53+30 -> 47501 | R54: =TEXT($Q54,"MMMM")&TEXT($Q54," YYYY") -> January 2030 | S54: =($V$1/12+1)*S53+T53 -> 18909016 | U54: =($V$2/12+1)*U53+$V$3 -> 1937244.4 | V54: =V53+$I$56 -> 935929.8 | W54: =W53+X53 -> 13524000 | X54: =T54 -> 0 | Y54: =SUM(S54:V54)-W54 -> 8258190.1
P55: 49 | Q55: =Q54+30 -> 47531 | R55: =TEXT($Q55,"MMMM")&TEXT($Q55," YYYY") -> February 2030 | S55: =($V$1/12+1)*S54+T54 -> 19019318 | U55: =($V$2/12+1)*U54+$V$3 -> 1963388.1 | V55: =V54+$I$56 -> 953587.88 | W55: =W54+X54 -> 13524000 | X55: =T55 -> 0 | Y55: =SUM(S55:V55)-W55 -> 8412294.5
B56: Total Net Worth (ex Super) | D56: =E50-I50 -> 3681000 | G56: CASHFLOW | H56: monthly | I56: =I17-I28 -> 17658.081 | L56: LIABILITIES | P56: 50 | Q56: =Q55+30 -> 47561 | R56: =TEXT($Q56,"MMMM")&TEXT($Q56," YYYY") -> March 2030 | S56: =($V$1/12+1)*S55+T55 -> 19130265 | U56: =($V$2/12+1)*U55+$V$3 -> 1989749.7 | V56: =V55+$I$56 -> 971245.96 | W56: =W55+X55 -> 13524000 | X56: =T56 -> 0 | Y56: =SUM(S56:V56)-W56 -> 8567260.1
L57: Credit Card 1 (total limit) | M57: 2000 | P57: 51 | Q57: =Q56+30 -> 47591 | R57: =TEXT($Q57,"MMMM")&TEXT($Q57," YYYY") -> April 2030 | S57: =($V$1/12+1)*S56+T56 -> 19241858 | U57: =($V$2/12+1)*U56+$V$3 -> 2016330.9 | V57: =V56+$I$56 -> 988904.04 | W57: =W56+X56 -> 13524000 | X57: =T57 -> 0 | Y57: =SUM(S57:V57)-W57 -> 8723092.7
B58: Total Net Worth (incl Super) | D58: =E49-I50 -> 4101000 | G58: Savings Potential | H58: yearly | I58: =I56*12 -> 211896.97 | L58: Credit Card 2 (total limit) | M58: 3000 | P58: 52 | Q58: =Q57+30 -> 47621 | R58: =TEXT($Q58,"MMMM")&TEXT($Q58," YYYY") -> May 2030 | S58: =($V$1/12+1)*S57+T57 -> 19354102 | U58: =($V$2/12+1)*U57+$V$3 -> 2043133.7 | V58: =V57+$I$56 -> 1006562.1 | W58: =W57+X57 -> 13524000 | X58: =T58 -> 0 | Y58: =SUM(S58:V58)-W58 -> 8879797.7
B59: Total Net Asset Worth (excl Super) | D59: =D56-D44 -> 1781000 | L59: Personal Loans | P59: 53 | Q59: =Q58+30 -> 47651 | R59: =TEXT($Q59,"MMMM")&TEXT($Q59," YYYY") -> June 2030 | S59: =($V$1/12+1)*S58+T58 -> 19467001 | U59: =($V$2/12+1)*U58+$V$3 -> 2070159.8 | V59: =V58+$I$56 -> 1024220.2 | W59: =W58+X58 -> 13524000 | X59: =T59 -> 0 | Y59: =SUM(S59:V59)-W59 -> 9037380.8
L60: Other Loans | P60: 54 | Q60: =Q59+30 -> 47681 | R60: =TEXT($Q60,"MMMM")&TEXT($Q60," YYYY") -> July 2030 | S60: =($V$1/12+1)*S59+T59 -> 19580558 | U60: =($V$2/12+1)*U59+$V$3 -> 2097411.1 | V60: =V59+$I$56 -> 1041878.3 | W60: =W59+X59 -> 13524000 | X60: =T60 -> 0 | Y60: =SUM(S60:V60)-W60 -> 9195847.7
B61: Property Stats | G61: Passive Income | P61: 55 | Q61: =Q60+30 -> 47711 | R61: =TEXT($Q61,"MMMM")&TEXT($Q61," YYYY") -> August 2030 | S61: =($V$1/12+1)*S60+T60 -> 19694778 | U61: =($V$2/12+1)*U60+$V$3 -> 2124889.5 | V61: =V60+$I$56 -> 1059536.4 | W61: =W60+X60 -> 13524000 | X61: =T61 -> 0 | Y61: =SUM(S61:V61)-W61 -> 9355204.2
L62: Home - Mortgage | M62: 0 | P62: 56 | Q62: =Q61+30 -> 47741 | R62: =TEXT($Q62,"MMMM")&TEXT($Q62," YYYY") -> September 2030 | S62: =($V$1/12+1)*S61+T61 -> 19809664 | U62: =($V$2/12+1)*U61+$V$3 -> 2152597 | V62: =V61+$I$56 -> 1077194.4 | W62: =W61+X61 -> 13524000 | X62: =T62 -> 0 | Y62: =SUM(S62:V62)-W62 -> 9515455.9
B63: Total Property Debt | D63: =SUM(I44:I47) -> 1522000 | G63: Passive Income | H63: monthly | I63: =H5 -> 1996.0167 | P63: 57 | Q63: =Q62+30 -> 47771 | R63: =TEXT($Q63,"MMMM")&TEXT($Q63," YYYY") -> October 2030 | S63: =($V$1/12+1)*S62+T62 -> 19925221 | U63: =($V$2/12+1)*U62+$V$3 -> 2180535.3 | V63: =V62+$I$56 -> 1094852.5 | W63: =W62+X62 -> 13524000 | X63: =T63 -> 0 | Y63: =SUM(S63:V63)-W63 -> 9676608.6
L64: Investment 1 Forest Lake - Mortgage | M64: 512000 | P64: 58 | Q64: =Q63+30 -> 47801 | R64: =TEXT($Q64,"MMMM")&TEXT($Q64," YYYY") -> November 2030 | S64: =($V$1/12+1)*S63+T63 -> 20041451 | T64: =$V$4 -> 3000000 | U64: =($V$2/12+1)*U63+$V$3 -> 2208706.4 | V64: =V63+$I$56 -> 1112510.6 | W64: =W63+X63 -> 13524000 | X64: =T64 -> 3000000 | Y64: =SUM(S64:V64)-W64 -> 12838668
B65: Total Property Assets | D65: =SUM(E44:E47) -> 4175000 | G65: Amount for 100% Passive | H65: monthly | I65: =I28-H5 -> 12939.236 | L65: Investment 2 Strathpine - Mortgage | M65: 230000 | P65: 59 | Q65: =Q64+30 -> 47831 | R65: =TEXT($Q65,"MMMM")&TEXT($Q65," YYYY") -> December 2030 | S65: =($V$1/12+1)*S64+T64 -> 23158360 | U65: =($V$2/12+1)*U64+$V$3 -> 2237112.3 | V65: =V64+$I$56 -> 1130168.7 | W65: =W64+X64 -> 16524000 | X65: =T65 -> 0 | Y65: =SUM(S65:V65)-W65 -> 10001641
L66: Investment 3 Mt Sheridan - Mortgage | M66: 780000 | P66: 60 | Q66: =Q65+30 -> 47861 | R66: =TEXT($Q66,"MMMM")&TEXT($Q66," YYYY") -> January 2031 | S66: =($V$1/12+1)*S65+T65 -> 23293450 | U66: =($V$2/12+1)*U65+$V$3 -> 2265754.9 | V66: =V65+$I$56 -> 1147826.8 | W66: =W65+X65 -> 16524000 | X66: =T66 -> 0 | Y66: =SUM(S66:V66)-W66 -> 10183032
B67: Total Equity Available | D67: =SUM(D44:D47) -> 2653000 | G67: Capital Required to Invest | I67: =I65*12/0.08 -> 1940885.4
G68: Estimated Capital required (at 8% income) to be financially independent
B69: Current LVR | D69: =D63/D65 -> 0.3645509
G70: Liquidity
B71: Equity available 80% | D71: =(80%-D69)*D65 -> 1818000
G72: Available Cash (including Line of Credit) | I72: =SUM(E34:E35) -> 106000
G73: Stocks currently invested | I73: =SUM(E37:E39) -> 924000
B74: Borrowing Power | G74: Total Liquidity | I74: =SUM(I72:I73) -> 1030000
B76: Bank will lend you | D76: =D79-D63 -> 884504.96 | G76: Emergency Fund
B77: Assumed 3% above loan rate for Assessment Rate
G78: Without Salary - you'll last this many MONTHS | I78: =SUM(E34:E39)/(I28-H5) -> 79.602846
B79: Total Borrowing Capacity | D79: =PV(8%/12,30*12,H22,0)*-1 -> 2406505 | G79: Without Salary - you'll last this many YEARS | I79: =SUM(E34:E39)/(I28-H5)/12 -> 6.6335705
B80: Assuming no additional income to offset | G80: Every WORKING month buys you this many MONTHS | I80: =H22/(I28-H5) -> 1.3646927
B85: Dream 1 - Financial Security (Cover the Basics) | G85: Emergency Fund needed - 12 Months
B86: 1. Mortgage | D86: 0 | G86: =D113 -> 88055.23
B87: 2. Utilities / Essentials | D87: =M30 -> 875.7325
B88: 3. Food | D88: =M31 -> 2120 | G88: Current Capital
B89: 4. Transportation | D89: 500 | G89: Savings | H89: =SUM(M40:M41) -> 106000
B90: 5. Insurance Costs | D90: 500 | G90: Stocks | H90: =SUM(M43:M45) -> 924000
B91: 6. Health | D91: =M33 -> 1514.7033 | G91: Potential Equity | H91: =SUM(D45:D47) -> 753000 | I91: (excluding PPOR)
G93: Total Capital | H93: =SUM(H89:H92) -> 1783000
B94: Monthly | D94: =SUM(D86:D93) -> 5510.4358 | G94: (not including home)
B95: Yearly | D95: =D94*12 -> 66125.23
B96: Capital for Dream 1 @ 6% | D96: =D95/0.06 -> 1102087.2
B98: Dream 2 - Financial Vitality (half of extra expenses)
B99: 1. Other / Entertainment | D99: =M36/2 -> 550
B100: 2. Sports/Activities | D100: =M34/2 -> 550
B101: 3. Discretionary | D101: =M33/2 -> 757.35167
B102: 4. Financial Security | D102: =D94 -> 5510.4358
B105: Monthly | D105: =SUM(D99:D103) -> 7367.7875
B106: Yearly | D106: =D105*12 -> 88413.45
B107: Capital for Dream 2 @ 6% | D107: =D106/0.06 -> 1473557.5
B109: Dream 3 - Financial Independence (cover it all)
B110: Budget | D110: =M28 -> 7337.9358
...

Sheet FV_July25 
U1: Property Growth Rate (PY) | V1: 0.07
B2: INCOME STATEMENT | L2: INPUTS!!! Fill out the ORANGE cells ONLY | U2: Stock Growth Rate (PY) | V2: 0.1
U3: Stock contribution per month | V3: 10000 | AI3: NET GROWTH FORECAST
B4: INCOME | C4: PER YEAR | D4: PER MONTH | E4: CASHFLOW PM | G4: PASSIVE | H4: PER MONTH | I4: PER YEAR | L4: INCOME | U4: Yearly Prop Purchase Value | V4: 2000000
G5: PASSIVE INCOME | H5: =SUM(D8:D18) -> 9953 | I5: =H5*12 -> 119436
B6: Salary 1 | C6: =D6*12 -> 276000 | D6: =M6 -> 23000 | L6: Salary 1 (ex tax per month) | M6: 23000 | P6: Date | Q6: Date | R6: Month | S6: Properties | T6: Add Prop | U6: Stocks | V6: Savings | W6: Liabilities | X6: Add Liab | Y6: Total Net Worth
B7: Salary 2 | C7: =D7*12 -> 0 | D7: =M7 -> 0 | L7: Salary 2 (ex tax per month) | P7: 1 | Q7: =TODAY() -> 46091 | R7: =TEXT($Q7,"MMMM")&TEXT($Q7," YYYY") -> March 2026 | S7: =SUM(E48:E54) -> 4205000 | U7: =SUM(E41:E43) -> 1044000 | V7: =$E$38 -> 6000 | W7: =$I$57 -> 1480000 | X7: =T7 -> 0 | Y7: =SUM(S7:V7)-W7 -> 3775000
B8: Interest Earned (from savings) | D8: =M8 -> 10 | E8: =D8 -> 10 | L8: Interest from Savings (per month) | M8: 10 | P8: 2 | Q8: =Q7+30 -> 46121 | R8: =TEXT($Q8,"MMMM")&TEXT($Q8," YYYY") -> April 2026 | S8: =($V$1/12+1)*S7+T7 -> 4229529.2 | U8: =($V$2/12+1)*U7+$V$3 -> 1062700 | V8: =V7+$I$65 -> 22020.498 | W8: =W7+X7 -> 1480000 | X8: =T8 -> 0 | Y8: =SUM(S8:V8)-W8 -> 3834249.7
B9: Dividends | C9: =D9*12 -> 9960 | D9: =M9 -> 830 | E9: =D9 -> 830 | L9: Income from Dividends (per month) | M9: 830 | P9: 3 | Q9: =Q8+30 -> 46151 | R9: =TEXT($Q9,"MMMM")&TEXT($Q9," YYYY") -> May 2026 | S9: =($V$1/12+1)*S8+T8 -> 4254201.4 | U9: =($V$2/12+1)*U8+$V$3 -> 1081555.8 | V9: =V8+$I$65 -> 38040.995 | W9: =W8+X8 -> 1480000 | X9: =T9 -> 0 | Y9: =SUM(S9:V9)-W9 -> 3893798.2
B10: Other income | D10: =M10 -> 0 | L10: Any other income (per month) | M10: 0 | P10: 4 | Q10: =Q9+30 -> 46181 | R10: =TEXT($Q10,"MMMM")&TEXT($Q10," YYYY") -> June 2026 | S10: =($V$1/12+1)*S9+T9 -> 4279017.6 | U10: =($V$2/12+1)*U9+$V$3 -> 1100568.8 | V10: =V9+$I$65 -> 54061.493 | W10: =W9+X9 -> 1480000 | X10: =T10 -> 0 | Y10: =SUM(S10:V10)-W10 -> 3953647.9
P11: 5 | Q11: =Q10+30 -> 46211 | R11: =TEXT($Q11,"MMMM")&TEXT($Q11," YYYY") -> July 2026 | S11: =($V$1/12+1)*S10+T10 -> 4303978.5 | U11: =($V$2/12+1)*U10+$V$3 -> 1119740.2 | V11: =V10+$I$65 -> 70081.99 | W11: =W10+X10 -> 1480000 | X11: =T11 -> 0 | Y11: =SUM(S11:V11)-W11 -> 4013800.7
B12: Real Estate / Other income (gross): | G12: Property Yield | H12: % Gross | I12: % Net | P12: 6 | Q12: =Q11+30 -> 46241 | R12: =TEXT($Q12,"MMMM")&TEXT($Q12," YYYY") -> August 2026 | S12: =($V$1/12+1)*S11+T11 -> 4329085.1 | U12: =($V$2/12+1)*U11+$V$3 -> 1139071.4 | V12: =V11+$I$65 -> 86102.488 | W12: =W11+X11 -> 1480000 | X12: =T12 -> 0 | Y12: =SUM(S12:V12)-W12 -> 4074258.9
P13: 7 | Q13: =Q12+30 -> 46271 | R13: =TEXT($Q13,"MMMM")&TEXT($Q13," YYYY") -> September 2026 | S13: =($V$1/12+1)*S12+T12 -> 4354338.1 | U13: =($V$2/12+1)*U12+$V$3 -> 1158563.6 | V13: =V12+$I$65 -> 102122.99 | W13: =W12+X12 -> 1480000 | X13: =T13 -> 0 | Y13: =SUM(S13:V13)-W13 -> 4135024.7
B14: =L14 -> Rental income Forest Lake (per week) | C14: =D14*12 -> 32240 | D14: =M14*52/12 -> 2686.6667 | E14: =SUM(D14-D23) -> -476.32667 | G14: Investment 1 (rental income) | H14: =C14/E49 -> 0.03224 | I14: =(D14-M29)/E49*12 -> 0.02495288 | L14: Rental income Forest Lake (per week) | M14: 620 | P14: 8 | Q14: =Q13+30 -> 46301 | R14: =TEXT($Q14,"MMMM")&TEXT($Q14," YYYY") -> October 2026 | S14: =($V$1/12+1)*S13+T13 -> 4379738.4 | U14: =($V$2/12+1)*U13+$V$3 -> 1178218.3 | V14: =V13+$I$65 -> 118143.48 | W14: =W13+X13 -> 1480000 | X14: =T14 -> 0 | Y14: =SUM(S14:V14)-W14 -> 4196100.2
B15: =L15 -> Rental income Strathpine (per week) | C15: =D15*12 -> 39156 | D15: =M15*52/12 -> 3263 | E15: =SUM(D15-D24) -> 1428 | G15: Investment 2 (rental income) | H15: =C15/E50 -> 0.067510345 | I15: =(D15-M30)/E50*12 -> 0.0502 | L15: Rental income Strathpine (per week) | M15: 753 | P15: 9 | Q15: =Q14+30 -> 46331 | R15: =TEXT($Q15,"MMMM")&TEXT($Q15," YYYY") -> November 2026 | S15: =($V$1/12+1)*S14+T14 -> 4405286.8 | U15: =($V$2/12+1)*U14+$V$3 -> 1198036.8 | V15: =V14+$I$65 -> 134163.98 | W15: =W14+X14 -> 1480000 | X15: =T15 -> 0 | Y15: =SUM(S15:V15)-W15 -> 4257487.6
B16: =L16 -> Rental income Mt Sheridan (per week) | C16: =D16*12 -> 37960 | D16: =M16*52/12 -> 3163.3333 | E16: =SUM(D16-D25) -> -1433.24 | G16: Investment 3 (rental income) | H16: =C16/E51 -> 0.052358621 | I16: =(D16-M31)/E51*12 -> 0.038738648 | L16: Rental income Mt Sheridan (per week) | M16: 730 | P16: 10 | Q16: =Q15+30 -> 46361 | R16: =TEXT($Q16,"MMMM")&TEXT($Q16," YYYY") -> December 2026 | S16: =($V$1/12+1)*S15+T15 -> 4430984.4 | U16: =($V$2/12+1)*U15+$V$3 -> 1218020.5 | V16: =V15+$I$65 -> 150184.48 | W16: =W15+X15 -> 1480000 | X16: =T16 -> 0 | Y16: =SUM(S16:V16)-W16 -> 4319189.3
B17: =L17 -> Rental income - Eimeo (per week) | C17: =D17*12 -> 0 | D17: =M17*52/12 -> 0 | E17: =SUM(D17-D26) -> 0 | G17: Investment 4 (rental income) | H17: =C17/E52 -> #DIV/0! | I17: =(D17-M32)/E52*12 -> #DIV/0! | L17: Rental income - Eimeo (per week) | P17: 11 | Q17: =Q16+30 -> 46391 | R17: =TEXT($Q17,"MMMM")&TEXT($Q17," YYYY") -> January 2027 | S17: =($V$1/12+1)*S16+T16 -> 4456831.8 | T17: =$V$4 -> 2000000 | U17: =($V$2/12+1)*U16+$V$3 -> 1238170.6 | V17: =V16+$I$65 -> 166204.98 | W17: =W16+X16 -> 1480000 | X17: =T17 -> 2000000 | Y17: =SUM(S17:V17)-W17 -> 6381207.4
B18: =L18 -> Rental income - (per week) | C18: =D18*12 -> 0 | D18: =M18*52/12 -> 0 | E18: =IF(SUM(D18-D27)>=0, SUM(D18-D27), "") -> 0 | G18: Investment 5 (rental income) | H18: - | I18: - | L18: Rental income - (per week) | P18: 12 | Q18: =Q17+30 -> 46421 | R18: =TEXT($Q18,"MMMM")&TEXT($Q18," YYYY") -> February 2027 | S18: =($V$1/12+1)*S17+T17 -> 6482829.9 | U18: =($V$2/12+1)*U17+$V$3 -> 1258488.7 | V18: =V17+$I$65 -> 182225.47 | W18: =W17+X17 -> 3480000 | X18: =T18 -> 0 | Y18: =SUM(S18:V18)-W18 -> 4443544.1
B19: Negative Gearing Potential | C19: {=SUM(E16:E18+E14)*0.4*-12} -> 13738.656 | D19: =C19/12 -> 1144.888 | G19: TOTAL INCOME | H19: (per month) | I19: =SUM(D6:D18) -> 32953 | P19: 13 | Q19: =Q18+30 -> 46451 | R19: =TEXT($Q19,"MMMM")&TEXT($Q19," YYYY") -> March 2027 | S19: =($V$1/12+1)*S18+T18 -> 6520646.5 | U19: =($V$2/12+1)*U18+$V$3 -> 1278976.1 | V19: =V18+$I$65 -> 198245.97 | W19: =W18+X18 -> 3480000 | X19: =T19 -> 0 | Y19: =SUM(S19:V19)-W19 -> 4517868.6
B20: EXPENSES | C20: PER YEAR | D20: PER MONTH | L20: EXPENSES | P20: 14 | Q20: =Q19+30 -> 46481 | R20: =TEXT($Q20,"MMMM")&TEXT($Q20," YYYY") -> April 2027 | S20: =($V$1/12+1)*S19+T19 -> 6558683.6 | U20: =($V$2/12+1)*U19+$V$3 -> 1299634.3 | V20: =V19+$I$65 -> 214266.47 | W20: =W19+X19 -> 3480000 | X20: =T20 -> 0 | Y20: =SUM(S20:V20)-W20 -> 4592584.3
P21: 15 | Q21: =Q20+30 -> 46511 | R21: =TEXT($Q21,"MMMM")&TEXT($Q21," YYYY") -> May 2027 | S21: =($V$1/12+1)*S20+T20 -> 6596942.5 | U21: =($V$2/12+1)*U20+$V$3 -> 1320464.5 | V21: =V20+$I$65 -> 230286.96 | W21: =W20+X20 -> 3480000 | X21: =T21 -> 0 | Y21: =SUM(S21:V21)-W21 -> 4667694.1
B22: Mortgage - Home per month | C22: =D22*12 -> 0 | D22: =PMT(M22/12, 25*12, -M75) -> 0 | L22: HOME Mortgage (P+I) - per month | M22: 0.0599 | P22: 16 | Q22: =Q21+30 -> 46541 | R22: =TEXT($Q22,"MMMM")&TEXT($Q22," YYYY") -> June 2027 | S22: =($V$1/12+1)*S21+T21 -> 6635424.7 | U22: =($V$2/12+1)*U21+$V$3 -> 1341468.4 | V22: =V21+$I$65 -> 246307.46 | W22: =W21+X21 -> 3480000 | X22: =T22 -> 0 | Y22: =SUM(S22:V22)-W22 -> 4743200.6
B23: Interest / Expenses Forest Lake | C23: =D23*12 -> 37955.92 | D23: =M23*I49/12+(M29) -> 3162.9933 | L23: Interest Forest Lake | M23: 0.0599 | P23: 17 | Q23: =Q22+30 -> 46571 | R23: =TEXT($Q23,"MMMM")&TEXT($Q23," YYYY") -> July 2027 | S23: =($V$1/12+1)*S22+T22 -> 6674131.4 | U23: =($V$2/12+1)*U22+$V$3 -> 1362647.3 | V23: =V22+$I$65 -> 262327.96 | W23: =W22+X22 -> 3480000 | X23: =T23 -> 0 | Y23: =SUM(S23:V23)-W23 -> 4819106.6
B24: Interest / Expenses Strathpine | C24: =D24*12 -> 22020 | D24: =M24*I50/12+(M30) -> 1835 | G24: CASH FLOW (monthly) | H24: =I19-I32 -> 16020.498 | L24: Interest Strathpine | M24: =M23 -> 0.0599 | P24: 18 | Q24: =Q23+30 -> 46601 | R24: =TEXT($Q24,"MMMM")&TEXT($Q24," YYYY") -> August 2027 | S24: =($V$1/12+1)*S23+T23 -> 6713063.8 | U24: =($V$2/12+1)*U23+$V$3 -> 1384002.7 | V24: =V23+$I$65 -> 278348.46 | W24: =W23+X23 -> 3480000 | X24: =T24 -> 0 | Y24: =SUM(S24:V24)-W24 -> 4895415
B25: Interest / Expenses Mt Sheridan | C25: =D25*12 -> 55158.88 | D25: =M25*I51/12+(M31) -> 4596.5733 | G25: Total Income - Total Expenses | L25: Interest Mt Sheridan | M25: =M24 -> 0.0599 | P25: 19 | Q25: =Q24+30 -> 46631 | R25: =TEXT($Q25,"MMMM")&TEXT($Q25," YYYY") -> September 2027 | S25: =($V$1/12+1)*S24+T24 -> 6752223.3 | U25: =($V$2/12+1)*U24+$V$3 -> 1405536.1 | V25: =V24+$I$65 -> 294368.96 | W25: =W24+X24 -> 3480000 | X25: =T25 -> 0 | Y25: =SUM(S25:V25)-W25 -> 4972128.4
B26: Interest / Expenses Eimeo | C26: =D26*12 -> 0 | D26: =M26*I52/12+(M32) -> 0 | L26: Interest Eimeo | M26: =M25 -> 0.0599 | P26: 20 | Q26: =Q25+30 -> 46661 | R26: =TEXT($Q26,"MMMM")&TEXT($Q26," YYYY") -> October 2027 | S26: =($V$1/12+1)*S25+T25 -> 6791611.3 | U26: =($V$2/12+1)*U25+$V$3 -> 1427248.9 | V26: =V25+$I$65 -> 310389.45 | W26: =W25+X25 -> 3480000 | X26: =T26 -> 0 | Y26: =SUM(S26:V26)-W26 -> 5049249.6
B27: Interest / Expenses Investment 5 | C27: =D27*12 -> 0 | D27: =M27*I53/12 -> 0 | L27: Interest Investment 5 | M27: =M26 -> 0.0599 | P27: 21 | Q27: =Q26+30 -> 46691 | R27: =TEXT($Q27,"MMMM")&TEXT($Q27," YYYY") -> October 2027 | S27: =($V$1/12+1)*S26+T26 -> 6831229 | U27: =($V$2/12+1)*U26+$V$3 -> 1449142.6 | V27: =V26+$I$65 -> 326409.95 | W27: =W26+X26 -> 3480000 | X27: =T27 -> 0 | Y27: =SUM(S27:V27)-W27 -> 5126781.6
P28: 22 | Q28: =Q27+30 -> 46721 | R28: =TEXT($Q28,"MMMM")&TEXT($Q28," YYYY") -> November 2027 | S28: =($V$1/12+1)*S27+T27 -> 6871077.9 | T28: =$V$4 -> 2000000 | U28: =($V$2/12+1)*U27+$V$3 -> 1471218.8 | V28: =V27+$I$65 -> 342430.45 | W28: =W27+X27 -> 3480000 | X28: =T28 -> 2000000 | Y28: =SUM(S28:V28)-W28 -> 7204727.1
B29: Monthly Personal Expenses / Spending | C29: =D29*12 -> 88055.23 | D29: =SUM(M42:M48) -> 7337.9358 | L29: Other expenses Forest Lake | M29: ='Property Expenses'!C10 -> 607.26 | P29: 23 | Q29: =Q28+30 -> 46751 | R29: =TEXT($Q29,"MMMM")&TEXT($Q29," YYYY") -> December 2027 | S29: =($V$1/12+1)*S28+T28 -> 8911159.2 | U29: =($V$2/12+1)*U28+$V$3 -> 1493479 | V29: =V28+$I$65 -> 358450.95 | W29: =W28+X28 -> 5480000 | X29: =T29 -> 0 | Y29: =SUM(S29:V29)-W29 -> 5283089.1
B30: Rental Payment | C30: =D30*12 -> 0 | D30: ='Monthly Expenses Budget'!C10 -> 0 | L30: Other expenses Strathpine | M30: ='Property Expenses'!C18 -> 836.66667 | P30: 24 | Q30: =Q29+30 -> 46781 | R30: =TEXT($Q30,"MMMM")&TEXT($Q30," YYYY") -> January 2028 | S30: =($V$1/12+1)*S29+T29 -> 8963140.9 | U30: =($V$2/12+1)*U29+$V$3 -> 1515924.6 | V30: =V29+$I$65 -> 374471.44 | W30: =W29+X29 -> 5480000 | X30: =T30 -> 0 | Y30: =SUM(S30:V30)-W30 -> 5373537
B31: Other | D31: =M38 -> 0 | L31: Other expenses Mt Sheridan | M31: ='Property Expenses'!C26 -> 822.87333 | P31: 25 | Q31: =Q30+30 -> 46811 | R31: =TEXT($Q31,"MMMM")&TEXT($Q31," YYYY") -> February 2028 | S31: =($V$1/12+1)*S30+T30 -> 9015425.9 | U31: =($V$2/12+1)*U30+$V$3 -> 1538557.3 | V31: =V30+$I$65 -> 390491.94 | W31: =W30+X30 -> 5480000 | X31: =T31 -> 0 | Y31: =SUM(S31:V31)-W31 -> 5464475.2
G32: TOTAL EXPENSES | H32: (per month) | I32: =SUM(D22:D31) -> 16932.502 | L32: Other expenses Eimeo | P32: 26 | Q32: =Q31+30 -> 46841 | R32: =TEXT($Q32,"MMMM")&TEXT($Q32," YYYY") -> March 2028 | S32: =($V$1/12+1)*S31+T31 -> 9068015.9 | U32: =($V$2/12+1)*U31+$V$3 -> 1561378.6 | V32: =V31+$I$65 -> 406512.44 | W32: =W31+X31 -> 5480000 | X32: =T32 -> 0 | Y32: =SUM(S32:V32)-W32 -> 5555907
L33: Other expenses Investment 5 | P33: 27 | Q33: =Q32+30 -> 46871 | R33: =TEXT($Q33,"MMMM")&TEXT($Q33," YYYY") -> April 2028 | S33: =($V$1/12+1)*S32+T32 -> 9120912.6 | U33: =($V$2/12+1)*U32+$V$3 -> 1584390.1 | V33: =V32+$I$65 -> 422532.93 | W33: =W32+X32 -> 5480000 | X33: =T33 -> 0 | Y33: =SUM(S33:V33)-W33 -> 5647835.7
B34: BALANCE SHEET | P34: 28 | Q34: =Q33+30 -> 46901 | R34: =TEXT($Q34,"MMMM")&TEXT($Q34," YYYY") -> May 2028 | S34: =($V$1/12+1)*S33+T33 -> 9174118 | U34: =($V$2/12+1)*U33+$V$3 -> 1607593.4 | V34: =V33+$I$65 -> 438553.43 | W34: =W33+X33 -> 5480000 | X34: =T34 -> 0 | Y34: =SUM(S34:V34)-W34 -> 5740264.8
P35: 29 | Q35: =Q34+30 -> 46931 | R35: =TEXT($Q35,"MMMM")&TEXT($Q35," YYYY") -> June 2028 | S35: =($V$1/12+1)*S34+T34 -> 9227633.7 | U35: =($V$2/12+1)*U34+$V$3 -> 1630990 | V35: =V34+$I$65 -> 454573.93 | W35: =W34+X34 -> 5480000 | X35: =T35 -> 0 | Y35: =SUM(S35:V35)-W35 -> 5833197.6
B36: ASSETS | E36: ASSET VALUE | G36: LIABILITIES (DEBT) | P36: 30 | Q36: =Q35+30 -> 46961 | R36: =TEXT($Q36,"MMMM")&TEXT($Q36," YYYY") -> July 2028 | S36: =($V$1/12+1)*S35+T35 -> 9281461.5 | U36: =($V$2/12+1)*U35+$V$3 -> 1654581.6 | V36: =V35+$I$65 -> 470594.43 | W36: =W35+X35 -> 5480000 | X36: =T36 -> 0 | Y36: =SUM(S36:V36)-W36 -> 5926637.5
P37: 31 | Q37: =Q36+30 -> 46991 | R37: =TEXT($Q37,"MMMM")&TEXT($Q37," YYYY") -> August 2028 | S37: =($V$1/12+1)*S36+T36 -> 9335603.4 | U37: =($V$2/12+1)*U36+$V$3 -> 1678369.7 | V37: =V36+$I$65 -> 486614.92 | W37: =W36+X36 -> 5480000 | X37: =T37 -> 0 | Y37: =SUM(S37:V37)-W37 -> 6020588
B38: Savings Account 1 | E38: =M52 -> 6000 | G38: Credit Card 1 (total limit) | I38: 10000 | L38: Other (Insert any other not covered) | P38: 32 | Q38: =Q37+30 -> 47021 | R38: =TEXT($Q38,"MMMM")&TEXT($Q38," YYYY") -> September 2028 | S38: =($V$1/12+1)*S37+T37 -> 9390061.1 | U38: =($V$2/12+1)*U37+$V$3 -> 1702356.2 | V38: =V37+$I$65 -> 502635.42 | W38: =W37+X37 -> 5480000 | X38: =T38 -> 0 | Y38: =SUM(S38:V38)-W38 -> 6115052.6
B39: Savings Account 2 | E39: =M53 -> 0 | G39: Credit Card 2 (total limit) | I39: 2000 | P39: 33 | Q39: =Q38+30 -> 47051 | R39: =TEXT($Q39,"MMMM")&TEXT($Q39," YYYY") -> October 2028 | S39: =($V$1/12+1)*S38+T38 -> 9444836.4 | U39: =($V$2/12+1)*U38+$V$3 -> 1726542.5 | V39: =V38+$I$65 -> 518655.92 | W39: =W38+X38 -> 5480000 | X39: =T39 -> 0 | Y39: =SUM(S39:V39)-W39 -> 6210034.8
G40: Personal Loans | L40: From Budget Spreadsheet - DO NOT UPDATE THIS | M40: =SUM(M41:M48) -> 7337.9358 | P40: 34 | Q40: =Q39+30 -> 47081 | R40: =TEXT($Q40,"MMMM")&TEXT($Q40," YYYY") -> November 2028 | S40: =($V$1/12+1)*S39+T39 -> 9499931.3 | T40: =$V$4 -> 2000000 | U40: =($V$2/12+1)*U39+$V$3 -> 1750930.3 | V40: =V39+$I$65 -> 534676.42 | W40: =W39+X39 -> 5480000 | X40: =T40 -> 2000000 | Y40: =SUM(S40:V40)-W40 -> 8305538
B41: Stocks (local) | E41: =M55 -> 208000 | G41: Other Loans | L41: ='Monthly Expenses Budget'!B5 -> Home and other Fixed Expenses | M41: ='Monthly Expenses Budget'!C5 -> 0 | P41: 35 | Q41: =Q40+30 -> 47111 | R41: =TEXT($Q41,"MMMM")&TEXT($Q41," YYYY") -> December 2028 | S41: =($V$1/12+1)*S40+T40 -> 11555348 | U41: =($V$2/12+1)*U40+$V$3 -> 1775521.4 | V41: =V40+$I$65 -> 550696.92 | W41: =W40+X40 -> 7480000 | X41: =T41 -> 0 | Y41: =SUM(S41:V41)-W41 -> 6401565.9
B42: Stocks (offshore) | E42: =M56 -> 242000 | L42: ='Monthly Expenses Budget'!B12 -> Essentials | M42: ='Monthly Expenses Budget'!C12 -> 875.7325 | P42: 36 | Q42: =Q41+30 -> 47141 | R42: =TEXT($Q42,"MMMM")&TEXT($Q42," YYYY") -> January 2029 | S42: =($V$1/12+1)*S41+T41 -> 11622754 | U42: =($V$2/12+1)*U41+$V$3 -> 1800317.4 | V42: =V41+$I$65 -> 566717.41 | W42: =W41+X41 -> 7480000 | X42: =T42 -> 0 | Y42: =SUM(S42:V42)-W42 -> 6509788.6
B43: Other stocks | E43: =M57 -> 594000 | L43: ='Monthly Expenses Budget'!B22 -> Groceries | M43: ='Monthly Expenses Budget'!C22 -> 2120 | P43: 37 | Q43: =Q42+30 -> 47171 | R43: =TEXT($Q43,"MMMM")&TEXT($Q43," YYYY") -> February 2029 | S43: =($V$1/12+1)*S42+T42 -> 11690553 | U43: =($V$2/12+1)*U42+$V$3 -> 1825320.1 | V43: =V42+$I$65 -> 582737.91 | W43: =W42+X42 -> 7480000 | X43: =T43 -> 0 | Y43: =SUM(S43:V43)-W43 -> 6618611.1
L44: ='Monthly Expenses Budget'!B31 -> House Maintenance | M44: ='Monthly Expenses Budget'!C31 -> 230 | P44: 38 | Q44: =Q43+30 -> 47201 | R44: =TEXT($Q44,"MMMM")&TEXT($Q44," YYYY") -> March 2029 | S44: =($V$1/12+1)*S43+T43 -> 11758748 | U44: =($V$2/12+1)*U43+$V$3 -> 1850531.1 | V44: =V43+$I$65 -> 598758.41 | W44: =W43+X43 -> 7480000 | X44: =T44 -> 0 | Y44: =SUM(S44:V44)-W44 -> 6728037.5
B45: Super 1 | E45: =M59 -> 220000 | L45: ='Monthly Expenses Budget'!B39 -> Health | M45: ='Monthly Expenses Budget'!C39 -> 1514.7033 | P45: 39 | Q45: =Q44+30 -> 47231 | R45: =TEXT($Q45,"MMMM")&TEXT($Q45," YYYY") -> April 2029 | S45: =($V$1/12+1)*S44+T44 -> 11827341 | U45: =($V$2/12+1)*U44+$V$3 -> 1875952.1 | V45: =V44+$I$65 -> 614778.91 | W45: =W44+X44 -> 7480000 | X45: =T45 -> 0 | Y45: =SUM(S45:V45)-W45 -> 6838071.8
B46: Super 2 | E46: =M60 -> 200000 | L46: ='Monthly Expenses Budget'!B49 -> Discretionary | M46: ='Monthly Expenses Budget'!C49 -> 1100 | P46: 40 | Q46: =Q45+30 -> 47261 | R46: =TEXT($Q46,"MMMM")&TEXT($Q46," YYYY") -> May 2029 | S46: =($V$1/12+1)*S45+T45 -> 11896334 | U46: =($V$2/12+1)*U45+$V$3 -> 1901585.1 | V46: =V45+$I$65 -> 630799.4 | W46: =W45+X45 -> 7480000 | X46: =T46 -> 0 | Y46: =SUM(S46:V46)-W46 -> 6948718.1
D47: EQUITY | L47: ='Monthly Expenses Budget'!B58 -> Sports / Activities | M47: ='Monthly Expenses Budget'!C58 -> 397.5 | P47: 41 | Q47: =Q46+30 -> 47291 | R47: =TEXT($Q47,"MMMM")&TEXT($Q47," YYYY") -> June 2029 | S47: =($V$1/12+1)*S46+T46 -> 11965729 | U47: =($V$2/12+1)*U46+$V$3 -> 1927431.6 | V47: =V46+$I$65 -> 646819.9 | W47: =W46+X46 -> 7480000 | X47: =T47 -> 0 | Y47: =SUM(S47:V47)-W47 -> 7059980.4
B48: Home | D48: =E48-I48 -> 1900000 | E48: =M62 -> 1900000 | G48: Mortgage - Home | I48: =M75 -> 0 | L48: ='Monthly Expenses Budget'!B64 -> Other | M48: ='Monthly Expenses Budget'!C64 -> 1100 | P48: 42 | Q48: =Q47+30 -> 47321 | R48: =TEXT($Q48,"MMMM")&TEXT($Q48," YYYY") -> July 2029 | S48: =($V$1/12+1)*S47+T47 -> 12035529 | U48: =($V$2/12+1)*U47+$V$3 -> 1953493.6 | V48: =V47+$I$65 -> 662840.4 | W48: =W47+X47 -> 7480000 | X48: =T48 -> 0 | Y48: =SUM(S48:V48)-W48 -> 7171862.9
B49: Investment 1 - Forest Lake value | D49: =E49-I49 -> 488000 | E49: =M63 -> 1000000 | G49: Investment 1 Forest Lake - Mortgage | I49: =M77 -> 512000 | P49: 43 | Q49: =Q48+30 -> 47351 | R49: =TEXT($Q49,"MMMM")&TEXT($Q49," YYYY") -> August 2029 | S49: =($V$1/12+1)*S48+T48 -> 12105736 | U49: =($V$2/12+1)*U48+$V$3 -> 1979772.7 | V49: =V48+$I$65 -> 678860.9 | W49: =W48+X48 -> 7480000 | X49: =T49 -> 0 | Y49: =SUM(S49:V49)-W49 -> 7284369.8
B50: Investment 2 - Strathpine value | D50: =E50-I50 -> 380000 | E50: =M64 -> 580000 | G50: Investment 2 Strathpine - Mortgage | I50: =M78 -> 200000 | P50: 44 | Q50: =Q49+30 -> 47381 | R50: =TEXT($Q50,"MMMM")&TEXT($Q50," YYYY") -> September 2029 | S50: =($V$1/12+1)*S49+T49 -> 12176353 | U50: =($V$2/12+1)*U49+$V$3 -> 2006270.8 | V50: =V49+$I$65 -> 694881.39 | W50: =W49+X49 -> 7480000 | X50: =T50 -> 0 | Y50: =SUM(S50:V50)-W50 -> 7397505.1
B51: Investment 3 - Mt Sheridan value | D51: =E51-I51 -> -31000 | E51: =M65 -> 725000 | G51: Investment 3 Mt Sheridan - Mortgage | I51: =M79 -> 756000 | L51: ASSETS | P51: 45 | Q51: =Q50+30 -> 47411 | R51: =TEXT($Q51,"MMMM")&TEXT($Q51," YYYY") -> October 2029 | S51: =($V$1/12+1)*S50+T50 -> 12247382 | U51: =($V$2/12+1)*U50+$V$3 -> 2032989.7 | V51: =V50+$I$65 -> 710901.89 | W51: =W50+X50 -> 7480000 | X51: =T51 -> 0 | Y51: =SUM(S51:V51)-W51 -> 7511273.3
B52: Investment 4 - Eimeo value | D52: =E52-I52 -> 0 | E52: =M66 -> 0 | G52: Investment 4 Eimeo - Mortgage | I52: =M80 -> 0 | L52: Savings (account 1) | M52: 6000 | P52: 46 | Q52: =Q51+30 -> 47441 | R52: =TEXT($Q52,"MMMM")&TEXT($Q52," YYYY") -> November 2029 | S52: =($V$1/12+1)*S51+T51 -> 12318825 | T52: =$V$4 -> 2000000 | U52: =($V$2/12+1)*U51+$V$3 -> 2059931.3 | V52: =V51+$I$65 -> 726922.39 | W52: =W51+X51 -> 7480000 | X52: =T52 -> 2000000 | Y52: =SUM(S52:V52)-W52 -> 9625678.4
B53: Investment 5 - value | D53: =E53-I53 -> 0 | E53: =M67 -> 0 | G53: Investment 5 - Mortgage | I53: =M81 -> 0 | L53: Savings (account 2) | P53: 47 | Q53: =Q52+30 -> 47471 | R53: =TEXT($Q53,"MMMM")&TEXT($Q53," YYYY") -> December 2029 | S53: =($V$1/12+1)*S52+T52 -> 14390685 | U53: =($V$2/12+1)*U52+$V$3 -> 2087097.4 | V53: =V52+$I$65 -> 742942.89 | W53: =W52+X52 -> 9480000 | X53: =T53 -> 0 | Y53: =SUM(S53:V53)-W53 -> 7740724.8
P54: 48 | Q54: =Q53+30 -> 47501 | R54: =TEXT($Q54,"MMMM")&TEXT($Q54," YYYY") -> January 2030 | S54: =($V$1/12+1)*S53+T53 -> 14474630 | U54: =($V$2/12+1)*U53+$V$3 -> 2114489.8 | V54: =V53+$I$65 -> 758963.38 | W54: =W53+X53 -> 9480000 | X54: =T54 -> 0 | Y54: =SUM(S54:V54)-W54 -> 7868083.5
L55: Stocks / Shares (ASX) | M55: 208000 | P55: 49 | Q55: =Q54+30 -> 47531 | R55: =TEXT($Q55,"MMMM")&TEXT($Q55," YYYY") -> February 2030 | S55: =($V$1/12+1)*S54+T54 -> 14559066 | U55: =($V$2/12+1)*U54+$V$3 -> 2142110.6 | V55: =V54+$I$65 -> 774983.88 | W55: =W54+X54 -> 9480000 | X55: =T55 -> 0 | Y55: =SUM(S55:V55)-W55 -> 7996160.1
B56: TOTAL ASSETS (including Super) | E56: =SUM(E38:E55) -> 5675000 | L56: Stocks / Shares (NASDAQ Other) | M56: 242000 | P56: 50 | Q56: =Q55+30 -> 47561 | R56: =TEXT($Q56,"MMMM")&TEXT($Q56," YYYY") -> March 2030 | S56: =($V$1/12+1)*S55+T55 -> 14643993 | U56: =($V$2/12+1)*U55+$V$3 -> 2169961.5 | V56: =V55+$I$65 -> 791004.38 | W56: =W55+X55 -> 9480000 | X56: =T56 -> 0 | Y56: =SUM(S56:V56)-W56 -> 8124959.4
B57: TOTAL ASSETS | E57: =SUM(E56-E46-E45) -> 5255000 | G57: TOTAL LIABILITY | I57: =SUM(I38:I56) -> 1480000 | L57: Other stocks (Crypto etc) | M57: 594000 | P57: 51 | Q57: =Q56+30 -> 47591 | R57: =TEXT($Q57,"MMMM")&TEXT($Q57," YYYY") -> April 2030 | S57: =($V$1/12+1)*S56+T56 -> 14729417 | U57: =($V$2/12+1)*U56+$V$3 -> 2198044.5 | V57: =V56+$I$65 -> 807024.88 | W57: =W56+X56 -> 9480000 | X57: =T57 -> 0 | Y57: =SUM(S57:V57)-W57 -> 8254486.2
P58: 52 | Q58: =Q57+30 -> 47621 | R58: =TEXT($Q58,"MMMM")&TEXT($Q58," YYYY") -> May 2030 | S58: =($V$1/12+1)*S57+T57 -> 14815338 | U58: =($V$2/12+1)*U57+$V$3 -> 2226361.6 | V58: =V57+$I$65 -> 823045.37 | W58: =W57+X57 -> 9480000 | X58: =T58 -> 0 | Y58: =SUM(S58:V58)-W58 -> 8384745.3
L59: Super 1 | M59: 220000 | P59: 53 | Q59: =Q58+30 -> 47651 | R59: =TEXT($Q59,"MMMM")&TEXT($Q59," YYYY") -> June 2030 | S59: =($V$1/12+1)*S58+T58 -> 14901761 | U59: =($V$2/12+1)*U58+$V$3 -> 2254914.6 | V59: =V58+$I$65 -> 839065.87 | W59: =W58+X58 -> 9480000 | X59: =T59 -> 0 | Y59: =SUM(S59:V59)-W59 -> 8515741.6
L60: Super 2 | M60: 200000 | P60: 54 | Q60: =Q59+30 -> 47681 | R60: =TEXT($Q60,"MMMM")&TEXT($Q60," YYYY") -> July 2030 | S60: =($V$1/12+1)*S59+T59 -> 14988688 | U60: =($V$2/12+1)*U59+$V$3 -> 2283705.5 | V60: =V59+$I$65 -> 855086.37 | W60: =W59+X59 -> 9480000 | X60: =T60 -> 0 | Y60: =SUM(S60:V60)-W60 -> 8647480
B61: SUMMARY METRICS | P61: 55 | Q61: =Q60+30 -> 47711 | R61: =TEXT($Q61,"MMMM")&TEXT($Q61," YYYY") -> August 2030 | S61: =($V$1/12+1)*S60+T60 -> 15076122 | U61: =($V$2/12+1)*U60+$V$3 -> 2312736.4 | V61: =V60+$I$65 -> 871106.87 | W61: =W60+X60 -> 9480000 | X61: =T61 -> 0 | Y61: =SUM(S61:V61)-W61 -> 8779965.4
L62: Home Value (estimate) | M62: 1900000 | P62: 56 | Q62: =Q61+30 -> 47741 | R62: =TEXT($Q62,"MMMM")&TEXT($Q62," YYYY") -> September 2030 | S62: =($V$1/12+1)*S61+T61 -> 15164066 | U62: =($V$2/12+1)*U61+$V$3 -> 2342009.2 | V62: =V61+$I$65 -> 887127.36 | W62: =W61+X61 -> 9480000 | X62: =T62 -> 0 | Y62: =SUM(S62:V62)-W62 -> 8913202.7
B63: Overall Net worth | G63: Cashflow | L63: Investment 1 - Forest Lake value | M63: 1000000 | P63: 57 | Q63: =Q62+30 -> 47771 | R63: =TEXT($Q63,"MMMM")&TEXT($Q63," YYYY") -> October 2030 | S63: =($V$1/12+1)*S62+T62 -> 15252523 | U63: =($V$2/12+1)*U62+$V$3 -> 2371526 | V63: =V62+$I$65 -> 903147.86 | W63: =W62+X62 -> 9480000 | X63: =T63 -> 0 | Y63: =SUM(S63:V63)-W63 -> 9047197
L64: Investment 2 - Strathpine value | M64: 580000 | P64: 58 | Q64: =Q63+30 -> 47801 | R64: =TEXT($Q64,"MMMM")&TEXT($Q64," YYYY") -> November 2030 | S64: =($V$1/12+1)*S63+T63 -> 15341496 | T64: =$V$4 -> 2000000 | U64: =($V$2/12+1)*U63+$V$3 -> 2401288.7 | V64: =V63+$I$65 -> 919168.36 | W64: =W63+X63 -> 9480000 | X64: =T64 -> 2000000 | Y64: =SUM(S64:V64)-W64 -> 11181953
B65: Total Net Worth (ex Super) | D65: =E57-I57 -> 3775000 | G65: CASHFLOW | H65: monthly | I65: =I19-I32 -> 16020.498 | L65: Investment 3 - Mt Sheridan value | M65: 725000 | P65: 59 | Q65: =Q64+30 -> 47831 | R65: =TEXT($Q65,"MMMM")&TEXT($Q65," YYYY") -> December 2030 | S65: =($V$1/12+1)*S64+T64 -> 17430988 | U65: =($V$2/12+1)*U64+$V$3 -> 2431299.4 | V65: =V64+$I$65 -> 935188.86 | W65: =W64+X64 -> 11480000 | X65: =T65 -> 0 | Y65: =SUM(S65:V65)-W65 -> 9317476.6
B66: Total N | L66: Investment 4 - Eimeo value | P66: 60 | Q66: =Q65+30 -> 47861 | R66: =TEXT($Q66,"MMMM")&TEXT($Q66," YYYY") -> January 2031 | S66: =($V$1/12+1)*S65+T65 -> 17532669 | U66: =($V$2/12+1)*U65+$V$3 -> 2461560.2 | V66: =V65+$I$65 -> 951209.35 | W66: =W65+X65 -> 11480000 | X66: =T66 -> 0 | Y66: =SUM(S66:V66)-W66 -> 9465438.7
B67: Total Net Worth (incl Super) | D67: =E56-I57 -> 4195000 | G67: Savings Potential | H67: yearly | I67: =I65*12 -> 192245.97 | L67: Investmen 5 - value
B68: Total Net Asset Worth (excl PPOR) | D68: =D65-D48 -> 1875000
I69: =I67*0.07 -> 13457.218 | L69: LIABILITIES
B70: Property Stats | G70: Passive Income | L70: Credit Card 1 (total limit) | M70: 2000
L71: Credit Card 2 (total limit) | M71: 3000
B72: Total Property Debt | D72: =SUM(I48:I54) -> 1468000 | G72: Passive Income | H72: monthly | I72: =H5 -> 9953 | L72: Personal Loans
L73: Other Loans
B74: Total Property Assets | D74: =SUM(E48:E54) -> 4205000 | G74: Amount for 100% Passive (break even) | H74: monthly | I74: =I32-H5 -> 6979.5025
H75: yearly | I75: =I74*12 -> 83754.03 | L75: Home - Mortgage
B76: Total Equity Available | D76: =SUM(D48:D53) -> 2737000 | G76: Capital Required to Invest | I76: =I74*12/0.065 -> 1288523.5
G77: Estimated Capital required (at 6.5% income) to be financially independent | L77: Investment 1 Forest Lake - Mortgage | M77: 512000
B78: Current LVR | D78: =D72/D74 -> 0.3491082 | L78: Investment 2 Strathpine - Mortgage | M78: 200000
L79: Investment 3 Mt Sheridan - Mortgage | M79: 756000
B80: Equity available 80% | D80: =(80%-D78)*D74 -> 1896000 | G80: Liquidity | L80: Investment 4 Eimeo - Mortgage
L81: Investment 5 - Mortgage
B82: Potential Property Purchase (with equity as leverage) | D82: =D80/0.2 -> 9480000 | G82: Available Cash (including Line of Credit) | I82: =SUM(E38:E39) -> 6000
G83: Stocks currently invested | I83: =SUM(E41:E43) -> 1044000
B84: Borrowing Power | G84: Total Liquidity | I84: =SUM(I82:I83) -> 1050000
B86: Bank will lend you | D86: =D89-D72 -> 715329.38 | G86: Emergency Fund
B87: Assumed 3% above loan rate for Assessment Rate
G88: Without Salary - you'll last this many MONTHS | I88: =SUM(E38:E43)/(I32-H5) -> 150.44052
B89: Total Borrowing Capacity | D89: =PV(8%/12,30*12,H24,0)*-1 -> 2183329.4 | G89: Without Salary - you'll last this many YEARS | I89: =SUM(E38:E43)/(I32-H5)/12 -> 12.53671
B90: Assuming no additional income to offset | G90: Every WORKING month buys you this many MONTHS | I90: =H24/(I32-H5) -> 2.2953638
B96: Dream 1 - Financial Security (Cover the Basics) | G96: Emergency Fund needed - 12 Months
B97: 1. Mortgage | D97: 0 | G97: =D124 -> 88055.23
B98: 2. Utilities / Essentials | D98: =M42 -> 875.7325
B99: 3. Food | D99: =M43 -> 2120 | G99: Current Capital
B100: 4. Transportation | D100: 500 | G100: Savings | H100: =SUM(M52:M53) -> 6000
B101: 5. Insurance Costs | D101: 500 | G101: Stocks | H101: =SUM(M55:M57) -> 1044000
B102: 6. Health | D102: =M45 -> 1514.7033 | G102: Potential Equity | H102: =SUM(D49:D53) -> 837000 | I102: (excluding PPOR)
G104: Total Capital | H104: =SUM(H100:H103) -> 1887000 | I104: =H104*0.075 -> 141525
B105: Monthly | D105: =SUM(D97:D104) -> 5510.4358 | G105: (not including home)
B106: Yearly | D106: =D105*12 -> 66125.23
B107: Capital for Dream 1 @ 6% | D107: =D106/0.06 -> 1102087.2
...

Sheet FV_August25
U1: Property Growth Rate (PY) | V1: 0.07
B2: INCOME STATEMENT | L2: INPUTS!!! Fill out the ORANGE cells ONLY | U2: Stock Growth Rate (PY) | V2: 0.1
U3: Stock contribution per month | V3: 10000 | AI3: NET GROWTH FORECAST
B4: INCOME | C4: PER YEAR | D4: PER MONTH | E4: CASHFLOW PM | G4: PASSIVE | H4: PER MONTH | I4: PER YEAR | L4: INCOME | U4: Yearly Prop Purchase Value | V4: 2000000
G5: PASSIVE INCOME | H5: =SUM(D8:D19) -> 15345.464 | I5: =H5*12 -> 184145.57
B6: Salary 1 | C6: =D6*12 -> 276000 | D6: =M6 -> 23000 | L6: Salary 1 (ex tax per month) | M6: 23000 | P6: Date | Q6: Date | R6: Month | S6: Properties | T6: Add Prop | U6: Stocks | V6: Savings | W6: Liabilities | X6: Add Liab | Y6: Total Net Worth
B7: Salary 2 | C7: =D7*12 -> 0 | D7: =M7 -> 0 | L7: Salary 2 (ex tax per month) | P7: 1 | Q7: =TODAY() -> 46091 | R7: =TEXT($Q7,"MMMM")&TEXT($Q7," YYYY") -> March 2026 | S7: =SUM(E48:E54) -> 5010000 | U7: =SUM(E41:E43) -> 975000 | V7: =$E$38 -> 7000 | W7: =$I$57 -> 2331000 | X7: =T7 -> 0 | Y7: =SUM(S7:V7)-W7 -> 3661000
B8: Interest Earned (from savings) | D8: =M8 -> 10 | E8: =D8 -> 10 | L8: Interest from Savings (per month) | M8: 10 | P8: 2 | Q8: =Q7+30 -> 46121 | R8: =TEXT($Q8,"MMMM")&TEXT($Q8," YYYY") -> April 2026 | S8: =($V$1/12+1)*S7+T7 -> 5039225 | U8: =($V$2/12+1)*U7+$V$3 -> 993125 | V8: =V7+$I$65 -> 21594.916 | W8: =W7+X7 -> 2331000 | X8: =T8 -> 0 | Y8: =SUM(S8:V8)-W8 -> 3722944.9
B9: Dividends | C9: =D9*12 -> 9960 | D9: =M9 -> 830 | E9: =D9 -> 830 | L9: Income from Dividends (per month) | M9: 830 | P9: 3 | Q9: =Q8+30 -> 46151 | R9: =TEXT($Q9,"MMMM")&TEXT($Q9," YYYY") -> May 2026 | S9: =($V$1/12+1)*S8+T8 -> 5068620.5 | U9: =($V$2/12+1)*U8+$V$3 -> 1011401 | V9: =V8+$I$65 -> 36189.832 | W9: =W8+X8 -> 2331000 | X9: =T9 -> 0 | Y9: =SUM(S9:V9)-W9 -> 3785211.4
B10: Other income | D10: =M10 -> 0 | L10: Any other income (per month) | M10: 0 | P10: 4 | Q10: =Q9+30 -> 46181 | R10: =TEXT($Q10,"MMMM")&TEXT($Q10," YYYY") -> June 2026 | S10: =($V$1/12+1)*S9+T9 -> 5098187.4 | U10: =($V$2/12+1)*U9+$V$3 -> 1029829.4 | V10: =V9+$I$65 -> 50784.748 | W10: =W9+X9 -> 2331000 | X10: =T10 -> 0 | Y10: =SUM(S10:V10)-W10 -> 3847801.6
P11: 5 | Q11: =Q10+30 -> 46211 | R11: =TEXT($Q11,"MMMM")&TEXT($Q11," YYYY") -> July 2026 | S11: =($V$1/12+1)*S10+T10 -> 5127926.9 | U11: =($V$2/12+1)*U10+$V$3 -> 1048411.3 | V11: =V10+$I$65 -> 65379.663 | W11: =W10+X10 -> 2331000 | X11: =T11 -> 0 | Y11: =SUM(S11:V11)-W11 -> 3910717.8
B12: Real Estate / Other income (gross): | G12: Property Yield | H12: % Gross | I12: % Net | P12: 6 | Q12: =Q11+30 -> 46241 | R12: =TEXT($Q12,"MMMM")&TEXT($Q12," YYYY") -> August 2026 | S12: =($V$1/12+1)*S11+T11 -> 5157839.8 | U12: =($V$2/12+1)*U11+$V$3 -> 1067148.1 | V12: =V11+$I$65 -> 79974.579 | W12: =W11+X11 -> 2331000 | X12: =T12 -> 0 | Y12: =SUM(S12:V12)-W12 -> 3973962.4
P13: 7 | Q13: =Q12+30 -> 46271 | R13: =TEXT($Q13,"MMMM")&TEXT($Q13," YYYY") -> September 2026 | S13: =($V$1/12+1)*S12+T12 -> 5187927.2 | U13: =($V$2/12+1)*U12+$V$3 -> 1086041 | V13: =V12+$I$65 -> 94569.495 | W13: =W12+X12 -> 2331000 | X13: =T13 -> 0 | Y13: =SUM(S13:V13)-W13 -> 4037537.6
B14: =L14 -> Rental income Forest Lake (per week) | C14: =D14*12 -> 32240 | D14: =M14*52/12 -> 2686.6667 | E14: =SUM(D14-D23) -> -476.32667 | G14: Investment 1 (rental income) | H14: =C14/E49 -> 0.032565657 | I14: =(D14-M29)/E49*12 -> 0.025204929 | L14: Rental income Forest Lake (per week) | M14: 620 | P14: 8 | Q14: =Q13+30 -> 46301 | R14: =TEXT($Q14,"MMMM")&TEXT($Q14," YYYY") -> October 2026 | S14: =($V$1/12+1)*S13+T13 -> 5218190.1 | U14: =($V$2/12+1)*U13+$V$3 -> 1105091.3 | V14: =V13+$I$65 -> 109164.41 | W14: =W13+X13 -> 2331000 | X14: =T14 -> 0 | Y14: =SUM(S14:V14)-W14 -> 4101445.8
B15: =L15 -> Rental income Strathpine (per week) | C15: =D15*12 -> 39156 | D15: =M15*52/12 -> 3263 | E15: =SUM(D15-D24) -> 1413.025 | G15: Investment 2 (rental income) | H15: =C15/E50 -> 0.067510345 | I15: =(D15-M30)/E50*12 -> 0.0502 | L15: Rental income Strathpine (per week) | M15: 753 | P15: 9 | Q15: =Q14+30 -> 46331 | R15: =TEXT($Q15,"MMMM")&TEXT($Q15," YYYY") -> November 2026 | S15: =($V$1/12+1)*S14+T14 -> 5248629.5 | U15: =($V$2/12+1)*U14+$V$3 -> 1124300.4 | V15: =V14+$I$65 -> 123759.33 | W15: =W14+X14 -> 2331000 | X15: =T15 -> 0 | Y15: =SUM(S15:V15)-W15 -> 4165689.2
B16: =L16 -> Rental income Mt Sheridan (per week) | C16: =D16*12 -> 37960 | D16: =M16*52/12 -> 3163.3333 | E16: =SUM(D16-D25) -> -1553.04 | G16: Investment 3 (rental income) | H16: =C16/E51 -> 0.051297297 | I16: =(D16-M31)/E51*12 -> 0.037953405 | L16: Rental income Mt Sheridan (per week) | M16: 730 | P16: 10 | Q16: =Q15+30 -> 46361 | R16: =TEXT($Q16,"MMMM")&TEXT($Q16," YYYY") -> December 2026 | S16: =($V$1/12+1)*S15+T15 -> 5279246.5 | U16: =($V$2/12+1)*U15+$V$3 -> 1143669.6 | V16: =V15+$I$65 -> 138354.24 | W16: =W15+X15 -> 2331000 | X16: =T16 -> 0 | Y16: =SUM(S16:V16)-W16 -> 4230270.3
B17: =L17 -> Rental income - Eimeo (per week) | C17: =D17*12 -> 44200 | D17: =M17*52/12 -> 3683.3333 | E17: =SUM(D17-D26) -> -1290.8067 | G17: Investment 4 (rental income) | H17: =C17/E52 -> 0.05525 | I17: =(D17-M32)/E52*12 -> 0.0423349 | L17: Rental income - Eimeo (per week) | M17: 850 | P17: 11 | Q17: =Q16+30 -> 46391 | R17: =TEXT($Q17,"MMMM")&TEXT($Q17," YYYY") -> January 2027 | S17: =($V$1/12+1)*S16+T16 -> 5310042.1 | T17: =$V$4 -> 2000000 | U17: =($V$2/12+1)*U16+$V$3 -> 1163200.1 | V17: =V16+$I$65 -> 152949.16 | W17: =W16+X16 -> 2331000 | X17: =T17 -> 2000000 | Y17: =SUM(S17:V17)-W17 -> 6295191.4
B18: =L18 -> Rental income - (per week) | C18: =D18*12 -> 0 | D18: =M18*52/12 -> 0 | E18: =IF(SUM(D18-D27)>=0, SUM(D18-D27), "") -> 0 | G18: Investment 5 (rental income) | H18: - | I18: - | L18: Rental income - (per week) | P18: 12 | Q18: =Q17+30 -> 46421 | R18: =TEXT($Q18,"MMMM")&TEXT($Q18," YYYY") -> February 2027 | S18: =($V$1/12+1)*S17+T17 -> 7341017.4 | U18: =($V$2/12+1)*U17+$V$3 -> 1182893.5 | V18: =V17+$I$65 -> 167544.07 | W18: =W17+X17 -> 4331000 | X18: =T18 -> 0 | Y18: =SUM(S18:V18)-W18 -> 4360454.9
B19: Negative Gearing Potential | C19: {=SUM(E16:E18+E14)*0.4*-12} -> 20509.568 | D19: =C19/12 -> 1709.1307 | G19: TOTAL INCOME | H19: (per month) | I19: =SUM(D6:D18) -> 36636.333 | P19: 13 | Q19: =Q18+30 -> 46451 | R19: =TEXT($Q19,"MMMM")&TEXT($Q19," YYYY") -> March 2027 | S19: =($V$1/12+1)*S18+T18 -> 7383840 | U19: =($V$2/12+1)*U18+$V$3 -> 1202750.9 | V19: =V18+$I$65 -> 182138.99 | W19: =W18+X18 -> 4331000 | X19: =T19 -> 0 | Y19: =SUM(S19:V19)-W19 -> 4437729.9
B20: EXPENSES | C20: PER YEAR | D20: PER MONTH | L20: EXPENSES | P20: 14 | Q20: =Q19+30 -> 46481 | R20: =TEXT($Q20,"MMMM")&TEXT($Q20," YYYY") -> April 2027 | S20: =($V$1/12+1)*S19+T19 -> 7426912.4 | U20: =($V$2/12+1)*U19+$V$3 -> 1222773.8 | V20: =V19+$I$65 -> 196733.91 | W20: =W19+X19 -> 4331000 | X20: =T20 -> 0 | Y20: =SUM(S20:V20)-W20 -> 4515420.1
P21: 15 | Q21: =Q20+30 -> 46511 | R21: =TEXT($Q21,"MMMM")&TEXT($Q21," YYYY") -> May 2027 | S21: =($V$1/12+1)*S20+T20 -> 7470236 | U21: =($V$2/12+1)*U20+$V$3 -> 1242963.6 | V21: =V20+$I$65 -> 211328.82 | W21: =W20+X20 -> 4331000 | X21: =T21 -> 0 | Y21: =SUM(S21:V21)-W21 -> 4593528.5
B22: Mortgage - Home per month | C22: =D22*12 -> 0 | D22: =PMT(M22/12, 25*12, -M75) -> 0 | L22: HOME Mortgage (P+I) - per month | M22: 0.0599 | P22: 16 | Q22: =Q21+30 -> 46541 | R22: =TEXT($Q22,"MMMM")&TEXT($Q22," YYYY") -> June 2027 | S22: =($V$1/12+1)*S21+T21 -> 7513812.4 | U22: =($V$2/12+1)*U21+$V$3 -> 1263321.7 | V22: =V21+$I$65 -> 225923.74 | W22: =W21+X21 -> 4331000 | X22: =T22 -> 0 | Y22: =SUM(S22:V22)-W22 -> 4672057.8
B23: Interest / Expenses Forest Lake | C23: =D23*12 -> 37955.92 | D23: =M23*I49/12+(M29) -> 3162.9933 | L23: Interest Forest Lake | M23: 0.0599 | P23: 17 | Q23: =Q22+30 -> 46571 | R23: =TEXT($Q23,"MMMM")&TEXT($Q23," YYYY") -> July 2027 | S23: =($V$1/12+1)*S22+T22 -> 7557643 | U23: =($V$2/12+1)*U22+$V$3 -> 1283849.3 | V23: =V22+$I$65 -> 240518.65 | W23: =W22+X22 -> 4331000 | X23: =T23 -> 0 | Y23: =SUM(S23:V23)-W23 -> 4751011
B24: Interest / Expenses Strathpine | C24: =D24*12 -> 22199.7 | D24: =M24*I50/12+(M30) -> 1849.975 | G24: CASH FLOW (monthly) | H24: =I19-I32 -> 14594.916 | L24: Interest Strathpine | M24: =M23 -> 0.0599 | P24: 18 | Q24: =Q23+30 -> 46601 | R24: =TEXT($Q24,"MMMM")&TEXT($Q24," YYYY") -> August 2027 | S24: =($V$1/12+1)*S23+T23 -> 7601729.2 | U24: =($V$2/12+1)*U23+$V$3 -> 1304548.1 | V24: =V23+$I$65 -> 255113.57 | W24: =W23+X23 -> 4331000 | X24: =T24 -> 0 | Y24: =SUM(S24:V24)-W24 -> 4830390.9
B25: Interest / Expenses Mt Sheridan | C25: =D25*12 -> 56596.48 | D25: =M25*I51/12+(M31) -> 4716.3733 | G25: Total Income - Total Expenses | L25: Interest Mt Sheridan | M25: =M24 -> 0.0599 | P25: 19 | Q25: =Q24+30 -> 46631 | R25: =TEXT($Q25,"MMMM")&TEXT($Q25," YYYY") -> September 2027 | S25: =($V$1/12+1)*S24+T24 -> 7646072.6 | U25: =($V$2/12+1)*U24+$V$3 -> 1325419.3 | V25: =V24+$I$65 -> 269708.49 | W25: =W24+X24 -> 4331000 | X25: =T25 -> 0 | Y25: =SUM(S25:V25)-W25 -> 4910200.4
B26: Interest / Expenses Eimeo | C26: =D26*12 -> 59689.68 | D26: =M26*I52/12+(M32) -> 4974.14 | L26: Interest Eimeo | M26: =M25 -> 0.0599 | P26: 20 | Q26: =Q25+30 -> 46661 | R26: =TEXT($Q26,"MMMM")&TEXT($Q26," YYYY") -> October 2027 | S26: =($V$1/12+1)*S25+T25 -> 7690674.7 | U26: =($V$2/12+1)*U25+$V$3 -> 1346464.5 | V26: =V25+$I$65 -> 284303.4 | W26: =W25+X25 -> 4331000 | X26: =T26 -> 0 | Y26: =SUM(S26:V26)-W26 -> 4990442.6
B27: Interest / Expenses Investment 5 | C27: =D27*12 -> 0 | D27: =M27*I53/12 -> 0 | L27: Interest Investment 5 | M27: =M26 -> 0.0599 | P27: 21 | Q27: =Q26+30 -> 46691 | R27: =TEXT($Q27,"MMMM")&TEXT($Q27," YYYY") -> October 2027 | S27: =($V$1/12+1)*S26+T26 -> 7735537 | U27: =($V$2/12+1)*U26+$V$3 -> 1367685 | V27: =V26+$I$65 -> 298898.32 | W27: =W26+X26 -> 4331000 | X27: =T27 -> 0 | Y27: =SUM(S27:V27)-W27 -> 5071120.3
P28: 22 | Q28: =Q27+30 -> 46721 | R28: =TEXT($Q28,"MMMM")&TEXT($Q28," YYYY") -> November 2027 | S28: =($V$1/12+1)*S27+T27 -> 7780661 | T28: =$V$4 -> 2000000 | U28: =($V$2/12+1)*U27+$V$3 -> 1389082.4 | V28: =V27+$I$65 -> 313493.23 | W28: =W27+X27 -> 4331000 | X28: =T28 -> 2000000 | Y28: =SUM(S28:V28)-W28 -> 7152236.6
B29: Monthly Personal Expenses / Spending | C29: =D29*12 -> 88055.23 | D29: =SUM(M42:M48) -> 7337.9358 | L29: Other expenses Forest Lake | M29: ='Property Expenses'!C10 -> 607.26 | P29: 23 | Q29: =Q28+30 -> 46751 | R29: =TEXT($Q29,"MMMM")&TEXT($Q29," YYYY") -> December 2027 | S29: =($V$1/12+1)*S28+T28 -> 9826048.2 | U29: =($V$2/12+1)*U28+$V$3 -> 1410658.1 | V29: =V28+$I$65 -> 328088.15 | W29: =W28+X28 -> 6331000 | X29: =T29 -> 0 | Y29: =SUM(S29:V29)-W29 -> 5233794.4
B30: Rental Payment | C30: =D30*12 -> 0 | D30: ='Monthly Expenses Budget'!C10 -> 0 | L30: Other expenses Strathpine | M30: ='Property Expenses'!C18 -> 836.66667 | P30: 24 | Q30: =Q29+30 -> 46781 | R30: =TEXT($Q30,"MMMM")&TEXT($Q30," YYYY") -> January 2028 | S30: =($V$1/12+1)*S29+T29 -> 9883366.8 | U30: =($V$2/12+1)*U29+$V$3 -> 1432413.6 | V30: =V29+$I$65 -> 342683.06 | W30: =W29+X29 -> 6331000 | X30: =T30 -> 0 | Y30: =SUM(S30:V30)-W30 -> 5327463.4
B31: Other | D31: =M38 -> 0 | L31: Other expenses Mt Sheridan | M31: ='Property Expenses'!C26 -> 822.87333 | P31: 25 | Q31: =Q30+30 -> 46811 | R31: =TEXT($Q31,"MMMM")&TEXT($Q31," YYYY") -> February 2028 | S31: =($V$1/12+1)*S30+T30 -> 9941019.7 | U31: =($V$2/12+1)*U30+$V$3 -> 1454350.3 | V31: =V30+$I$65 -> 357277.98 | W31: =W30+X30 -> 6331000 | X31: =T31 -> 0 | Y31: =SUM(S31:V31)-W31 -> 5421648.1
G32: TOTAL EXPENSES | H32: (per month) | I32: =SUM(D22:D31) -> 22041.417 | L32: Other expenses Eimeo | M32: ='Property Expenses'!C34 -> 861.00667 | P32: 26 | Q32: =Q31+30 -> 46841 | R32: =TEXT($Q32,"MMMM")&TEXT($Q32," YYYY") -> March 2028 | S32: =($V$1/12+1)*S31+T31 -> 9999009 | U32: =($V$2/12+1)*U31+$V$3 -> 1476469.9 | V32: =V31+$I$65 -> 371872.9 | W32: =W31+X31 -> 6331000 | X32: =T32 -> 0 | Y32: =SUM(S32:V32)-W32 -> 5516351.9
L33: Other expenses Investment 5 | P33: 27 | Q33: =Q32+30 -> 46871 | R33: =TEXT($Q33,"MMMM")&TEXT($Q33," YYYY") -> April 2028 | S33: =($V$1/12+1)*S32+T32 -> 10057337 | U33: =($V$2/12+1)*U32+$V$3 -> 1498773.8 | V33: =V32+$I$65 -> 386467.81 | W33: =W32+X32 -> 6331000 | X33: =T33 -> 0 | Y33: =SUM(S33:V33)-W33 -> 5611578.2
B34: BALANCE SHEET | P34: 28 | Q34: =Q33+30 -> 46901 | R34: =TEXT($Q34,"MMMM")&TEXT($Q34," YYYY") -> May 2028 | S34: =($V$1/12+1)*S33+T33 -> 10116004 | U34: =($V$2/12+1)*U33+$V$3 -> 1521263.6 | V34: =V33+$I$65 -> 401062.73 | W34: =W33+X33 -> 6331000 | X34: =T34 -> 0 | Y34: =SUM(S34:V34)-W34 -> 5707330.7
P35: 29 | Q35: =Q34+30 -> 46931 | R35: =TEXT($Q35,"MMMM")&TEXT($Q35," YYYY") -> June 2028 | S35: =($V$1/12+1)*S34+T34 -> 10175014 | U35: =($V$2/12+1)*U34+$V$3 -> 1543940.8 | V35: =V34+$I$65 -> 415657.64 | W35: =W34+X34 -> 6331000 | X35: =T35 -> 0 | Y35: =SUM(S35:V35)-W35 -> 5803612.9
B36: ASSETS | E36: ASSET VALUE | G36: LIABILITIES (DEBT) | P36: 30 | Q36: =Q35+30 -> 46961 | R36: =TEXT($Q36,"MMMM")&TEXT($Q36," YYYY") -> July 2028 | S36: =($V$1/12+1)*S35+T35 -> 10234369 | U36: =($V$2/12+1)*U35+$V$3 -> 1566807 | V36: =V35+$I$65 -> 430252.56 | W36: =W35+X35 -> 6331000 | X36: =T36 -> 0 | Y36: =SUM(S36:V36)-W36 -> 5900428.2
P37: 31 | Q37: =Q36+30 -> 46991 | R37: =TEXT($Q37,"MMMM")&TEXT($Q37," YYYY") -> August 2028 | S37: =($V$1/12+1)*S36+T36 -> 10294069 | U37: =($V$2/12+1)*U36+$V$3 -> 1589863.7 | V37: =V36+$I$65 -> 444847.48 | W37: =W36+X36 -> 6331000 | X37: =T37 -> 0 | Y37: =SUM(S37:V37)-W37 -> 5997780.3
B38: Savings Account 1 | E38: =M52 -> 7000 | G38: Credit Card 1 (total limit) | I38: 10000 | L38: Other (Insert any other not covered) | P38: 32 | Q38: =Q37+30 -> 47021 | R38: =TEXT($Q38,"MMMM")&TEXT($Q38," YYYY") -> September 2028 | S38: =($V$1/12+1)*S37+T37 -> 10354118 | U38: =($V$2/12+1)*U37+$V$3 -> 1613112.6 | V38: =V37+$I$65 -> 459442.39 | W38: =W37+X37 -> 6331000 | X38: =T38 -> 0 | Y38: =SUM(S38:V38)-W38 -> 6095672.9
B39: Savings Account 2 | E39: =M53 -> 75000 | G39: Credit Card 2 (total limit) | I39: 2000 | P39: 33 | Q39: =Q38+30 -> 47051 | R39: =TEXT($Q39,"MMMM")&TEXT($Q39," YYYY") -> October 2028 | S39: =($V$1/12+1)*S38+T38 -> 10414517 | U39: =($V$2/12+1)*U38+$V$3 -> 1636555.2 | V39: =V38+$I$65 -> 474037.31 | W39: =W38+X38 -> 6331000 | X39: =T39 -> 0 | Y39: =SUM(S39:V39)-W39 -> 6194109.4
G40: Personal Loans | L40: From Budget Spreadsheet - DO NOT UPDATE THIS | M40: =SUM(M41:M48) -> 7337.9358 | P40: 34 | Q40: =Q39+30 -> 47081 | R40: =TEXT($Q40,"MMMM")&TEXT($Q40," YYYY") -> November 2028 | S40: =($V$1/12+1)*S39+T39 -> 10475268 | T40: =$V$4 -> 2000000 | U40: =($V$2/12+1)*U39+$V$3 -> 1660193.1 | V40: =V39+$I$65 -> 488632.22 | W40: =W39+X39 -> 6331000 | X40: =T40 -> 2000000 | Y40: =SUM(S40:V40)-W40 -> 8293093.6
B41: Stocks (local) | E41: =M55 -> 210000 | G41: Other Loans | L41: ='Monthly Expenses Budget'!B5 -> Home and other Fixed Expenses | M41: ='Monthly Expenses Budget'!C5 -> 0 | P41: 35 | Q41: =Q40+30 -> 47111 | R41: =TEXT($Q41,"MMMM")&TEXT($Q41," YYYY") -> December 2028 | S41: =($V$1/12+1)*S40+T40 -> 12536374 | U41: =($V$2/12+1)*U40+$V$3 -> 1684028.1 | V41: =V40+$I$65 -> 503227.14 | W41: =W40+X40 -> 8331000 | X41: =T41 -> 0 | Y41: =SUM(S41:V41)-W41 -> 6392629.2
B42: Stocks (offshore) | E42: =M56 -> 142000 | L42: ='Monthly Expenses Budget'!B12 -> Essentials | M42: ='Monthly Expenses Budget'!C12 -> 875.7325 | P42: 36 | Q42: =Q41+30 -> 47141 | R42: =TEXT($Q42,"MMMM")&TEXT($Q42," YYYY") -> January 2029 | S42: =($V$1/12+1)*S41+T41 -> 12609503 | U42: =($V$2/12+1)*U41+$V$3 -> 1708061.7 | V42: =V41+$I$65 -> 517822.05 | W42: =W41+X41 -> 8331000 | X42: =T42 -> 0 | Y42: =SUM(S42:V42)-W42 -> 6504386.5
B43: Other stocks | E43: =M57 -> 623000 | L43: ='Monthly Expenses Budget'!B22 -> Groceries | M43: ='Monthly Expenses Budget'!C22 -> 2120 | P43: 37 | Q43: =Q42+30 -> 47171 | R43: =TEXT($Q43,"MMMM")&TEXT($Q43," YYYY") -> February 2029 | S43: =($V$1/12+1)*S42+T42 -> 12683058 | U43: =($V$2/12+1)*U42+$V$3 -> 1732295.5 | V43: =V42+$I$65 -> 532416.97 | W43: =W42+X42 -> 8331000 | X43: =T43 -> 0 | Y43: =SUM(S43:V43)-W43 -> 6616770.7
L44: ='Monthly Expenses Budget'!B31 -> House Maintenance | M44: ='Monthly Expenses Budget'!C31 -> 230 | P44: 38 | Q44: =Q43+30 -> 47201 | R44: =TEXT($Q44,"MMMM")&TEXT($Q44," YYYY") -> March 2029 | S44: =($V$1/12+1)*S43+T43 -> 12757043 | U44: =($V$2/12+1)*U43+$V$3 -> 1756731.3 | V44: =V43+$I$65 -> 547011.89 | W44: =W43+X43 -> 8331000 | X44: =T44 -> 0 | Y44: =SUM(S44:V44)-W44 -> 6729786
B45: Super 1 | E45: =M59 -> 220000 | L45: ='Monthly Expenses Budget'!B39 -> Health | M45: ='Monthly Expenses Budget'!C39 -> 1514.7033 | P45: 39 | Q45: =Q44+30 -> 47231 | R45: =TEXT($Q45,"MMMM")&TEXT($Q45," YYYY") -> April 2029 | S45: =($V$1/12+1)*S44+T44 -> 12831459 | U45: =($V$2/12+1)*U44+$V$3 -> 1781370.7 | V45: =V44+$I$65 -> 561606.8 | W45: =W44+X44 -> 8331000 | X45: =T45 -> 0 | Y45: =SUM(S45:V45)-W45 -> 6843436.4
B46: Super 2 | E46: =M60 -> 200000 | L46: ='Monthly Expenses Budget'!B49 -> Discretionary | M46: ='Monthly Expenses Budget'!C49 -> 1100 | P46: 40 | Q46: =Q45+30 -> 47261 | R46: =TEXT($Q46,"MMMM")&TEXT($Q46," YYYY") -> May 2029 | S46: =($V$1/12+1)*S45+T45 -> 12906309 | U46: =($V$2/12+1)*U45+$V$3 -> 1806215.5 | V46: =V45+$I$65 -> 576201.72 | W46: =W45+X45 -> 8331000 | X46: =T46 -> 0 | Y46: =SUM(S46:V46)-W46 -> 6957726.2
D47: EQUITY | L47: ='Monthly Expenses Budget'!B58 -> Sports / Activities | M47: ='Monthly Expenses Budget'!C58 -> 397.5 | P47: 41 | Q47: =Q46+30 -> 47291 | R47: =TEXT($Q47,"MMMM")&TEXT($Q47," YYYY") -> June 2029 | S47: =($V$1/12+1)*S46+T46 -> 12981596 | U47: =($V$2/12+1)*U46+$V$3 -> 1831267.3 | V47: =V46+$I$65 -> 590796.63 | W47: =W46+X46 -> 8331000 | X47: =T47 -> 0 | Y47: =SUM(S47:V47)-W47 -> 7072659.7
B48: Home | D48: =E48-I48 -> 1900000 | E48: =M62 -> 1900000 | G48: Mortgage - Home | I48: =M75 -> 0 | L48: ='Monthly Expenses Budget'!B64 -> Other | M48: ='Monthly Expenses Budget'!C64 -> 1100 | P48: 42 | Q48: =Q47+30 -> 47321 | R48: =TEXT($Q48,"MMMM")&TEXT($Q48," YYYY") -> July 2029 | S48: =($V$1/12+1)*S47+T47 -> 13057322 | U48: =($V$2/12+1)*U47+$V$3 -> 1856527.8 | V48: =V47+$I$65 -> 605391.55 | W48: =W47+X47 -> 8331000 | X48: =T48 -> 0 | Y48: =SUM(S48:V48)-W48 -> 7188241.2
B49: Investment 1 - Forest Lake value | D49: =E49-I49 -> 478000 | E49: =M63 -> 990000 | G49: Investment 1 Forest Lake - Mortgage | I49: =M77 -> 512000 | P49: 43 | Q49: =Q48+30 -> 47351 | R49: =TEXT($Q49,"MMMM")&TEXT($Q49," YYYY") -> August 2029 | S49: =($V$1/12+1)*S48+T48 -> 13133490 | U49: =($V$2/12+1)*U48+$V$3 -> 1881998.9 | V49: =V48+$I$65 -> 619986.47 | W49: =W48+X48 -> 8331000 | X49: =T49 -> 0 | Y49: =SUM(S49:V49)-W49 -> 7304474.9
B50: Investment 2 - Strathpine value | D50: =E50-I50 -> 377000 | E50: =M64 -> 580000 | G50: Investment 2 Strathpine - Mortgage | I50: =M78 -> 203000 | P50: 44 | Q50: =Q49+30 -> 47381 | R50: =TEXT($Q50,"MMMM")&TEXT($Q50," YYYY") -> September 2029 | S50: =($V$1/12+1)*S49+T49 -> 13210102 | U50: =($V$2/12+1)*U49+$V$3 -> 1907682.2 | V50: =V49+$I$65 -> 634581.38 | W50: =W49+X49 -> 8331000 | X50: =T50 -> 0 | Y50: =SUM(S50:V50)-W50 -> 7421365.2
B51: Investment 3 - Mt Sheridan value | D51: =E51-I51 -> -40000 | E51: =M65 -> 740000 | G51: Investment 3 Mt Sheridan - Mortgage | I51: =M79 -> 780000 | L51: ASSETS | P51: 45 | Q51: =Q50+30 -> 47411 | R51: =TEXT($Q51,"MMMM")&TEXT($Q51," YYYY") -> October 2029 | S51: =($V$1/12+1)*S50+T50 -> 13287160 | U51: =($V$2/12+1)*U50+$V$3 -> 1933579.6 | V51: =V50+$I$65 -> 649176.3 | W51: =W50+X50 -> 8331000 | X51: =T51 -> 0 | Y51: =SUM(S51:V51)-W51 -> 7538916.3
B52: Investment 4 - Eimeo value | D52: =E52-I52 -> -24000 | E52: =M66 -> 800000 | G52: Investment 4 Eimeo - Mortgage | I52: =M80 -> 824000 | L52: Savings (account 1) | M52: 7000 | P52: 46 | Q52: =Q51+30 -> 47441 | R52: =TEXT($Q52,"MMMM")&TEXT($Q52," YYYY") -> November 2029 | S52: =($V$1/12+1)*S51+T51 -> 13364669 | T52: =$V$4 -> 2000000 | U52: =($V$2/12+1)*U51+$V$3 -> 1959692.7 | V52: =V51+$I$65 -> 663771.21 | W52: =W51+X51 -> 8331000 | X52: =T52 -> 2000000 | Y52: =SUM(S52:V52)-W52 -> 9657132.9
B53: Investment 5 - value | D53: =E53-I53 -> 0 | E53: =M67 -> 0 | G53: Investment 5 - Mortgage | I53: =M81 -> 0 | L53: Savings (account 2) | M53: 75000 | P53: 47 | Q53: =Q52+30 -> 47471 | R53: =TEXT($Q53,"MMMM")&TEXT($Q53," YYYY") -> December 2029 | S53: =($V$1/12+1)*S52+T52 -> 15442629 | U53: =($V$2/12+1)*U52+$V$3 -> 1986023.5 | V53: =V52+$I$65 -> 678366.13 | W53: =W52+X52 -> 10331000 | X53: =T53 -> 0 | Y53: =SUM(S53:V53)-W53 -> 7776019.1
P54: 48 | Q54: =Q53+30 -> 47501 | R54: =TEXT($Q54,"MMMM")&TEXT($Q54," YYYY") -> January 2030 | S54: =($V$1/12+1)*S53+T53 -> 15532711 | U54: =($V$2/12+1)*U53+$V$3 -> 2012573.7 | V54: =V53+$I$65 -> 692961.04 | W54: =W53+X53 -> 10331000 | X54: =T54 -> 0 | Y54: =SUM(S54:V54)-W54 -> 7907246.2
L55: Stocks / Shares (ASX) | M55: 210000 | P55: 49 | Q55: =Q54+30 -> 47531 | R55: =TEXT($Q55,"MMMM")&TEXT($Q55," YYYY") -> February 2030 | S55: =($V$1/12+1)*S54+T54 -> 15623319 | U55: =($V$2/12+1)*U54+$V$3 -> 2039345.2 | V55: =V54+$I$65 -> 707555.96 | W55: =W54+X54 -> 10331000 | X55: =T55 -> 0 | Y55: =SUM(S55:V55)-W55 -> 8039220.1
B56: TOTAL ASSETS (including Super) | E56: =SUM(E38:E55) -> 6487000 | L56: Stocks / Shares (NASDAQ Other) | M56: 142000 | P56: 50 | Q56: =Q55+30 -> 47561 | R56: =TEXT($Q56,"MMMM")&TEXT($Q56," YYYY") -> March 2030 | S56: =($V$1/12+1)*S55+T55 -> 15714455 | U56: =($V$2/12+1)*U55+$V$3 -> 2066339.7 | V56: =V55+$I$65 -> 722150.88 | W56: =W55+X55 -> 10331000 | X56: =T56 -> 0 | Y56: =SUM(S56:V56)-W56 -> 8171945.6
B57: TOTAL ASSETS | E57: =SUM(E56-E46-E45) -> 6067000 | G57: TOTAL LIABILITY | I57: =SUM(I38:I56) -> 2331000 | L57: Other stocks (Crypto etc) | M57: 623000 | P57: 51 | Q57: =Q56+30 -> 47591 | R57: =TEXT($Q57,"MMMM")&TEXT($Q57," YYYY") -> April 2030 | S57: =($V$1/12+1)*S56+T56 -> 15806123 | U57: =($V$2/12+1)*U56+$V$3 -> 2093559.2 | V57: =V56+$I$65 -> 736745.79 | W57: =W56+X56 -> 10331000 | X57: =T57 -> 0 | Y57: =SUM(S57:V57)-W57 -> 8305427.6
P58: 52 | Q58: =Q57+30 -> 47621 | R58: =TEXT($Q58,"MMMM")&TEXT($Q58," YYYY") -> May 2030 | S58: =($V$1/12+1)*S57+T57 -> 15898325 | U58: =($V$2/12+1)*U57+$V$3 -> 2121005.5 | V58: =V57+$I$65 -> 751340.71 | W58: =W57+X57 -> 10331000 | X58: =T58 -> 0 | Y58: =SUM(S58:V58)-W58 -> 8439671.3
L59: Super 1 | M59: 220000 | P59: 53 | Q59: =Q58+30 -> 47651 | R59: =TEXT($Q59,"MMMM")&TEXT($Q59," YYYY") -> June 2030 | S59: =($V$1/12+1)*S58+T58 -> 15991065 | U59: =($V$2/12+1)*U58+$V$3 -> 2148680.6 | V59: =V58+$I$65 -> 765935.62 | W59: =W58+X58 -> 10331000 | X59: =T59 -> 0 | Y59: =SUM(S59:V59)-W59 -> 8574681.4
L60: Super 2 | M60: 200000 | P60: 54 | Q60: =Q59+30 -> 47681 | R60: =TEXT($Q60,"MMMM")&TEXT($Q60," YYYY") -> July 2030 | S60: =($V$1/12+1)*S59+T59 -> 16084346 | U60: =($V$2/12+1)*U59+$V$3 -> 2176586.2 | V60: =V59+$I$65 -> 780530.54 | W60: =W59+X59 -> 10331000 | X60: =T60 -> 0 | Y60: =SUM(S60:V60)-W60 -> 8710463.3
B61: SUMMARY METRICS | P61: 55 | Q61: =Q60+30 -> 47711 | R61: =TEXT($Q61,"MMMM")&TEXT($Q61," YYYY") -> August 2030 | S61: =($V$1/12+1)*S60+T60 -> 16178172 | U61: =($V$2/12+1)*U60+$V$3 -> 2204724.5 | V61: =V60+$I$65 -> 795125.46 | W61: =W60+X60 -> 10331000 | X61: =T61 -> 0 | Y61: =SUM(S61:V61)-W61 -> 8847021.7
L62: Home Value (estimate) | M62: 1900000 | P62: 56 | Q62: =Q61+30 -> 47741 | R62: =TEXT($Q62,"MMMM")&TEXT($Q62," YYYY") -> September 2030 | S62: =($V$1/12+1)*S61+T61 -> 16272544 | U62: =($V$2/12+1)*U61+$V$3 -> 2233097.2 | V62: =V61+$I$65 -> 809720.37 | W62: =W61+X61 -> 10331000 | X62: =T62 -> 0 | Y62: =SUM(S62:V62)-W62 -> 8984362
B63: Overall Net worth | G63: Cashflow | L63: Investment 1 - Forest Lake value | M63: 990000 | P63: 57 | Q63: =Q62+30 -> 47771 | R63: =TEXT($Q63,"MMMM")&TEXT($Q63," YYYY") -> October 2030 | S63: =($V$1/12+1)*S62+T62 -> 16367468 | U63: =($V$2/12+1)*U62+$V$3 -> 2261706.3 | V63: =V62+$I$65 -> 824315.29 | W63: =W62+X62 -> 10331000 | X63: =T63 -> 0 | Y63: =SUM(S63:V63)-W63 -> 9122489.3
L64: Investment 2 - Strathpine value | M64: 580000 | P64: 58 | Q64: =Q63+30 -> 47801 | R64: =TEXT($Q64,"MMMM")&TEXT($Q64," YYYY") -> November 2030 | S64: =($V$1/12+1)*S63+T63 -> 16462945 | T64: =$V$4 -> 2000000 | U64: =($V$2/12+1)*U63+$V$3 -> 2290553.9 | V64: =V63+$I$65 -> 838910.2 | W64: =W63+X63 -> 10331000 | X64: =T64 -> 2000000 | Y64: =SUM(S64:V64)-W64 -> 11261409
B65: Total Net Worth (ex Super) | D65: =E57-I57 -> 3736000 | G65: CASHFLOW | H65: monthly | I65: =I19-I32 -> 14594.916 | L65: Investment 3 - Mt Sheridan value | M65: 740000 | P65: 59 | Q65: =Q64+30 -> 47831 | R65: =TEXT($Q65,"MMMM")&TEXT($Q65," YYYY") -> December 2030 | S65: =($V$1/12+1)*S64+T64 -> 18558978 | U65: =($V$2/12+1)*U64+$V$3 -> 2319641.8 | V65: =V64+$I$65 -> 853505.12 | W65: =W64+X64 -> 12331000 | X65: =T65 -> 0 | Y65: =SUM(S65:V65)-W65 -> 9401125.3
B66: Total N | L66: Investment 4 - Eimeo value | M66: 800000 | P66: 60 | Q66: =Q65+30 -> 47861 | R66: =TEXT($Q66,"MMMM")&TEXT($Q66," YYYY") -> January 2031 | S66: =($V$1/12+1)*S65+T65 -> 18667239 | U66: =($V$2/12+1)*U65+$V$3 -> 2348972.2 | V66: =V65+$I$65 -> 868100.03 | W66: =W65+X65 -> 12331000 | X66: =T66 -> 0 | Y66: =SUM(S66:V66)-W66 -> 9553311.3
B67: Total Net Worth (incl Super) | D67: =E56-I57 -> 4156000 | G67: Savings Potential | H67: yearly | I67: =I65*12 -> 175138.99 | L67: Investmen 5 - value
B68: Total Net Asset Worth (excl PPOR) | D68: =D65-D48 -> 1836000
I69: =I67*0.07 -> 12259.729 | L69: LIABILITIES
B70: Property Stats | G70: Passive Income | L70: Credit Card 1 (total limit) | M70: 2000
L71: Credit Card 2 (total limit) | M71: 3000
B72: Total Property Debt | D72: =SUM(I48:I54) -> 2319000 | G72: Passive Income | H72: monthly | I72: =H5 -> 15345.464 | L72: Personal Loans
L73: Other Loans
B74: Total Property Assets | D74: =SUM(E48:E54) -> 5010000 | G74: Amount for 100% Passive (break even) | H74: monthly | I74: =I32-H5 -> 6695.9535
B75: Potential Asset Growth per year | D75: =SUM(E41:E54)*0.07 -> 448350 | H75: yearly | I75: =I74*12 -> 80351.442 | L75: Home - Mortgage
G76: Capital Required to Invest | I76: =I74*12/0.065 -> 1236176
B77: Total Equity Available | D77: =SUM(D48:D53) -> 2691000 | G77: Estimated Capital required (at 6.5% income) to be financially independent | L77: Investment 1 Forest Lake - Mortgage | M77: 512000
L78: Investment 2 Strathpine - Mortgage | M78: 203000
B79: Current LVR | D79: =D72/D74 -> 0.46287425 | L79: Investment 3 Mt Sheridan - Mortgage | M79: 780000
G80: Liquidity | L80: Investment 4 Eimeo - Mortgage | M80: 824000
B81: Equity available 80% | D81: =(80%-D79)*D74 -> 1689000 | L81: Investment 5 - Mortgage
G82: Available Cash (including Line of Credit) | I82: =SUM(E38:E39) -> 82000
B83: Potential Property Purchase (with equity as leverage) | D83: =D81/0.2 -> 8445000 | G83: Stocks currently invested | I83: =SUM(E41:E43) -> 975000
G84: Total Liquidity | I84: =SUM(I82:I83) -> 1057000
B85: Borrowing Power
G86: Emergency Fund
B87: Bank will lend you | D87: =D90-D72 -> -329953.87
B88: Assumed 3% above loan rate for Assessment Rate | G88: Without Salary - you'll last this many MONTHS | I88: =SUM(E38:E43)/(I32-H5) -> 157.85653 | L88: Sale from Home | M88: 2100000
G89: Without Salary - you'll last this many YEARS | I89: =SUM(E38:E43)/(I32-H5)/12 -> 13.154711 | L89: Sell non crypto stocks | M89: 451000
B90: Total Borrowing Capacity | D90: =PV(8%/12,30*12,H24,0)*-1 -> 1989046.1 | G90: Every WORKING month buys you this many MONTHS | I90: =H24/(I32-H5) -> 2.1796621 | L90: Sell Forest Lake | M90: ???
L91: New Mortgage | M91: 1500000
L92: 200k of Crypto stocks | M92: 200000
L93: 400k of crypto stocks | M93: 400000
M94: =SUM(M88:M93) -> 4651000
B96: Dream 1 - Financial Security (Cover the Basics) | G96: Emergency Fund needed - 12 Months
B97: 1. Mortgage | D97: 0 | G97: =D124 -> 88055.23
B98: 2. Utilities / Essentials | D98: =M42 -> 875.7325
B99: 3. Food | D99: =M43 -> 2120 | G99: Current Capital
B100: 4. Transportation | D100: 500 | G100: Savings | H100: =SUM(M52:M53) -> 82000
B101: 5. Insurance Costs | D101: 500 | G101: Stocks | H101: =SUM(M55:M57) -> 975000
...

Sheet FV_September25
U1: Property Growth Rate (PY) | V1: 0.07
B2: INCOME STATEMENT | L2: INPUTS!!! Fill out the ORANGE cells ONLY | U2: Stock Growth Rate (PY) | V2: 0.1
U3: Stock contribution per month | V3: 10000 | AI3: NET GROWTH FORECAST
B4: INCOME | C4: PER YEAR | D4: PER MONTH | E4: CASHFLOW PM | G4: PASSIVE | H4: PER MONTH | I4: PER YEAR | L4: INCOME | U4: Yearly Prop Purchase Value | V4: 2000000
G5: PASSIVE INCOME | H5: =SUM(D8:D18) -> 13636.333 | I5: =H5*12 -> 163636
B6: Salary 1 | C6: =D6*12 -> 276000 | D6: =M6 -> 23000 | L6: Salary 1 (ex tax per month) | M6: 23000 | P6: Date | Q6: Date | R6: Month | S6: Properties | T6: Add Prop | U6: Stocks | V6: Savings | W6: Liabilities | X6: Add Liab | Y6: Total Net Worth
B7: Salary 2 | C7: =D7*12 -> 0 | D7: =M7 -> 0 | L7: Salary 2 (ex tax per month) | P7: 1 | Q7: =TODAY() -> 46091 | R7: =TEXT($Q7,"MMMM")&TEXT($Q7," YYYY") -> March 2026 | S7: =SUM(E48:E54) -> 5060000 | U7: =SUM(E41:E43) -> 956000 | V7: =$E$38 -> 10000 | W7: =$I$57 -> 2331000 | X7: =T7 -> 0 | Y7: =SUM(S7:V7)-W7 -> 3695000
B8: Interest Earned (from savings) | D8: =M8 -> 10 | E8: =D8 -> 10 | L8: Interest from Savings (per month) | M8: 10 | P8: 2 | Q8: =Q7+30 -> 46121 | R8: =TEXT($Q8,"MMMM")&TEXT($Q8," YYYY") -> April 2026 | S8: =($V$1/12+1)*S7+T7 -> 5089516.7 | U8: =($V$2/12+1)*U7+$V$3 -> 973966.67 | V8: =V7+$I$65 -> 25078.041 | W8: =W7+X7 -> 2331000 | X8: =T8 -> 0 | Y8: =SUM(S8:V8)-W8 -> 3757561.4
B9: Dividends | C9: =D9*12 -> 9960 | D9: =M9 -> 830 | E9: =D9 -> 830 | L9: Income from Dividends (per month) | M9: 830 | P9: 3 | Q9: =Q8+30 -> 46151 | R9: =TEXT($Q9,"MMMM")&TEXT($Q9," YYYY") -> May 2026 | S9: =($V$1/12+1)*S8+T8 -> 5119205.5 | U9: =($V$2/12+1)*U8+$V$3 -> 992083.06 | V9: =V8+$I$65 -> 40156.082 | W9: =W8+X8 -> 2331000 | X9: =T9 -> 0 | Y9: =SUM(S9:V9)-W9 -> 3820444.7
B10: Other income | D10: =M10 -> 0 | L10: Any other income (per month) | M10: 0 | P10: 4 | Q10: =Q9+30 -> 46181 | R10: =TEXT($Q10,"MMMM")&TEXT($Q10," YYYY") -> June 2026 | S10: =($V$1/12+1)*S9+T9 -> 5149067.5 | U10: =($V$2/12+1)*U9+$V$3 -> 1010350.4 | V10: =V9+$I$65 -> 55234.123 | W10: =W9+X9 -> 2331000 | X10: =T10 -> 0 | Y10: =SUM(S10:V10)-W10 -> 3883652.1
P11: 5 | Q11: =Q10+30 -> 46211 | R11: =TEXT($Q11,"MMMM")&TEXT($Q11," YYYY") -> July 2026 | S11: =($V$1/12+1)*S10+T10 -> 5179103.8 | U11: =($V$2/12+1)*U10+$V$3 -> 1028770 | V11: =V10+$I$65 -> 70312.163 | W11: =W10+X10 -> 2331000 | X11: =T11 -> 0 | Y11: =SUM(S11:V11)-W11 -> 3947185.9
B12: Real Estate / Other income (gross): | G12: Property Yield | H12: % Gross | I12: % Net | P12: 6 | Q12: =Q11+30 -> 46241 | R12: =TEXT($Q12,"MMMM")&TEXT($Q12," YYYY") -> August 2026 | S12: =($V$1/12+1)*S11+T11 -> 5209315.2 | U12: =($V$2/12+1)*U11+$V$3 -> 1047343.1 | V12: =V11+$I$65 -> 85390.204 | W12: =W11+X11 -> 2331000 | X12: =T12 -> 0 | Y12: =SUM(S12:V12)-W12 -> 4011048.5
P13: 7 | Q13: =Q12+30 -> 46271 | R13: =TEXT($Q13,"MMMM")&TEXT($Q13," YYYY") -> September 2026 | S13: =($V$1/12+1)*S12+T12 -> 5239702.9 | U13: =($V$2/12+1)*U12+$V$3 -> 1066070.9 | V13: =V12+$I$65 -> 100468.25 | W13: =W12+X12 -> 2331000 | X13: =T13 -> 0 | Y13: =SUM(S13:V13)-W13 -> 4075242.1
B14: =L14 -> Rental income Forest Lake (per week) | C14: =D14*12 -> 32240 | D14: =M14*52/12 -> 2686.6667 | E14: =SUM(D14-D23) -> -369.66 | G14: Investment 1 (rental income) | H14: =C14/E49 -> 0.032565657 | I14: =(D14-M29)/E49*12 -> 0.025204929 | L14: Rental income Forest Lake (per week) | M14: 620 | P14: 8 | Q14: =Q13+30 -> 46301 | R14: =TEXT($Q14,"MMMM")&TEXT($Q14," YYYY") -> October 2026 | S14: =($V$1/12+1)*S13+T13 -> 5270267.8 | U14: =($V$2/12+1)*U13+$V$3 -> 1084954.9 | V14: =V13+$I$65 -> 115546.29 | W14: =W13+X13 -> 2331000 | X14: =T14 -> 0 | Y14: =SUM(S14:V14)-W14 -> 4139769
B15: =L15 -> Rental income Strathpine (per week) | C15: =D15*12 -> 39156 | D15: =M15*52/12 -> 3263 | E15: =SUM(D15-D24) -> 1455.3167 | G15: Investment 2 (rental income) | H15: =C15/E50 -> 0.067510345 | I15: =(D15-M30)/E50*12 -> 0.0502 | L15: Rental income Strathpine (per week) | M15: 753 | P15: 9 | Q15: =Q14+30 -> 46331 | R15: =TEXT($Q15,"MMMM")&TEXT($Q15," YYYY") -> November 2026 | S15: =($V$1/12+1)*S14+T14 -> 5301011 | U15: =($V$2/12+1)*U14+$V$3 -> 1103996.2 | V15: =V14+$I$65 -> 130624.33 | W15: =W14+X14 -> 2331000 | X15: =T15 -> 0 | Y15: =SUM(S15:V15)-W15 -> 4204631.5
B16: =L16 -> Rental income Mt Sheridan (per week) | C16: =D16*12 -> 37960 | D16: =M16*52/12 -> 3163.3333 | E16: =SUM(D16-D25) -> -1390.54 | G16: Investment 3 (rental income) | H16: =C16/E51 -> 0.050613333 | I16: =(D16-M31)/E51*12 -> 0.03744736 | L16: Rental income Mt Sheridan (per week) | M16: 730 | P16: 10 | Q16: =Q15+30 -> 46361 | R16: =TEXT($Q16,"MMMM")&TEXT($Q16," YYYY") -> December 2026 | S16: =($V$1/12+1)*S15+T15 -> 5331933.6 | U16: =($V$2/12+1)*U15+$V$3 -> 1123196.1 | V16: =V15+$I$65 -> 145702.37 | W16: =W15+X15 -> 2331000 | X16: =T16 -> 0 | Y16: =SUM(S16:V16)-W16 -> 4269832.1
B17: =L17 -> Rental income - Eimeo (per week) | C17: =D17*12 -> 44200 | D17: =M17*52/12 -> 3683.3333 | E17: =SUM(D17-D26) -> -1119.14 | G17: Investment 4 (rental income) | H17: =C17/E52 -> 0.053902439 | I17: =(D17-M32)/E52*12 -> 0.041302341 | L17: Rental income - Eimeo (per week) | M17: 850 | P17: 11 | Q17: =Q16+30 -> 46391 | R17: =TEXT($Q17,"MMMM")&TEXT($Q17," YYYY") -> January 2027 | S17: =($V$1/12+1)*S16+T16 -> 5363036.6 | T17: =$V$4 -> 2000000 | U17: =($V$2/12+1)*U16+$V$3 -> 1142556.1 | V17: =V16+$I$65 -> 160780.41 | W17: =W16+X16 -> 2331000 | X17: =T17 -> 2000000 | Y17: =SUM(S17:V17)-W17 -> 6335373.1
B18: =L18 -> Rental income - (per week) | C18: =D18*12 -> 0 | D18: =M18*52/12 -> 0 | E18: =IF(SUM(D18-D27)>=0, SUM(D18-D27), "") -> 0 | G18: Investment 5 (rental income) | H18: - | I18: - | L18: Rental income - (per week) | P18: 12 | Q18: =Q17+30 -> 46421 | R18: =TEXT($Q18,"MMMM")&TEXT($Q18," YYYY") -> February 2027 | S18: =($V$1/12+1)*S17+T17 -> 7394320.9 | U18: =($V$2/12+1)*U17+$V$3 -> 1162077.4 | V18: =V17+$I$65 -> 175858.45 | W18: =W17+X17 -> 4331000 | X18: =T18 -> 0 | Y18: =SUM(S18:V18)-W18 -> 4401256.8
B19: Negative Gearing Potential | C19: {=SUM(E16:E17+E14)*0.4*-12} -> 15595.2 | D19: =C19/12 -> 1299.6 | G19: TOTAL INCOME | H19: (per month) | I19: =SUM(D6:D18) -> 36636.333 | P19: 13 | Q19: =Q18+30 -> 46451 | R19: =TEXT($Q19,"MMMM")&TEXT($Q19," YYYY") -> March 2027 | S19: =($V$1/12+1)*S18+T18 -> 7437454.5 | U19: =($V$2/12+1)*U18+$V$3 -> 1181761.4 | V19: =V18+$I$65 -> 190936.49 | W19: =W18+X18 -> 4331000 | X19: =T19 -> 0 | Y19: =SUM(S19:V19)-W19 -> 4479152.3
B20: EXPENSES | C20: PER YEAR | D20: PER MONTH | L20: EXPENSES | P20: 14 | Q20: =Q19+30 -> 46481 | R20: =TEXT($Q20,"MMMM")&TEXT($Q20," YYYY") -> April 2027 | S20: =($V$1/12+1)*S19+T19 -> 7480839.6 | U20: =($V$2/12+1)*U19+$V$3 -> 1201609.4 | V20: =V19+$I$65 -> 206014.53 | W20: =W19+X19 -> 4331000 | X20: =T20 -> 0 | Y20: =SUM(S20:V20)-W20 -> 4557463.5
P21: 15 | Q21: =Q20+30 -> 46511 | R21: =TEXT($Q21,"MMMM")&TEXT($Q21," YYYY") -> May 2027 | S21: =($V$1/12+1)*S20+T20 -> 7524477.9 | U21: =($V$2/12+1)*U20+$V$3 -> 1221622.8 | V21: =V20+$I$65 -> 221092.57 | W21: =W20+X20 -> 4331000 | X21: =T21 -> 0 | Y21: =SUM(S21:V21)-W21 -> 4636193.2
B22: Mortgage - Home per month | C22: =D22*12 -> 0 | D22: =PMT(M22/12, 25*12, -M75) -> 0 | L22: HOME Mortgage (P+I) - per month | M22: 0.0542 | P22: 16 | Q22: =Q21+30 -> 46541 | R22: =TEXT($Q22,"MMMM")&TEXT($Q22," YYYY") -> June 2027 | S22: =($V$1/12+1)*S21+T21 -> 7568370.6 | U22: =($V$2/12+1)*U21+$V$3 -> 1241803 | V22: =V21+$I$65 -> 236170.61 | W22: =W21+X21 -> 4331000 | X22: =T22 -> 0 | Y22: =SUM(S22:V22)-W22 -> 4715344.2
B23: Interest / Expenses Forest Lake | C23: =D23*12 -> 36675.92 | D23: =M23*I49/12+(M29) -> 3056.3267 | L23: Interest Forest Lake | M23: 0.0574 | P23: 17 | Q23: =Q22+30 -> 46571 | R23: =TEXT($Q23,"MMMM")&TEXT($Q23," YYYY") -> July 2027 | S23: =($V$1/12+1)*S22+T22 -> 7612519.5 | U23: =($V$2/12+1)*U22+$V$3 -> 1262151.3 | V23: =V22+$I$65 -> 251248.65 | W23: =W22+X22 -> 4331000 | X23: =T23 -> 0 | Y23: =SUM(S23:V23)-W23 -> 4794919.5
B24: Interest / Expenses Strathpine | C24: =D24*12 -> 21692.2 | D24: =M24*I50/12+(M30) -> 1807.6833 | G24: CASH FLOW (monthly) | H24: =I19-I32 -> 15078.041 | L24: Interest Strathpine | M24: =M23 -> 0.0574 | P24: 18 | Q24: =Q23+30 -> 46601 | R24: =TEXT($Q24,"MMMM")&TEXT($Q24," YYYY") -> August 2027 | S24: =($V$1/12+1)*S23+T23 -> 7656925.8 | U24: =($V$2/12+1)*U23+$V$3 -> 1282669.3 | V24: =V23+$I$65 -> 266326.69 | W24: =W23+X23 -> 4331000 | X24: =T24 -> 0 | Y24: =SUM(S24:V24)-W24 -> 4874921.8
B25: Interest / Expenses Mt Sheridan | C25: =D25*12 -> 54646.48 | D25: =M25*I51/12+(M31) -> 4553.8733 | G25: Total Income - Total Expenses | L25: Interest Mt Sheridan | M25: =M24 -> 0.0574 | P25: 19 | Q25: =Q24+30 -> 46631 | R25: =TEXT($Q25,"MMMM")&TEXT($Q25," YYYY") -> September 2027 | S25: =($V$1/12+1)*S24+T24 -> 7701591.2 | U25: =($V$2/12+1)*U24+$V$3 -> 1303358.2 | V25: =V24+$I$65 -> 281404.74 | W25: =W24+X24 -> 4331000 | X25: =T25 -> 0 | Y25: =SUM(S25:V25)-W25 -> 4955354.2
B26: Interest / Expenses Eimeo | C26: =D26*12 -> 57629.68 | D26: =M26*I52/12+(M32) -> 4802.4733 | L26: Interest Eimeo | M26: =M25 -> 0.0574 | P26: 20 | Q26: =Q25+30 -> 46661 | R26: =TEXT($Q26,"MMMM")&TEXT($Q26," YYYY") -> October 2027 | S26: =($V$1/12+1)*S25+T25 -> 7746517.2 | U26: =($V$2/12+1)*U25+$V$3 -> 1324219.5 | V26: =V25+$I$65 -> 296482.78 | W26: =W25+X25 -> 4331000 | X26: =T26 -> 0 | Y26: =SUM(S26:V26)-W26 -> 5036219.5
B27: Interest / Expenses Investment 5 | C27: =D27*12 -> 0 | D27: =M27*I53/12 -> 0 | L27: Interest Investment 5 | M27: =M26 -> 0.0574 | P27: 21 | Q27: =Q26+30 -> 46691 | R27: =TEXT($Q27,"MMMM")&TEXT($Q27," YYYY") -> October 2027 | S27: =($V$1/12+1)*S26+T26 -> 7791705.2 | U27: =($V$2/12+1)*U26+$V$3 -> 1345254.7 | V27: =V26+$I$65 -> 311560.82 | W27: =W26+X26 -> 4331000 | X27: =T27 -> 0 | Y27: =SUM(S27:V27)-W27 -> 5117520.7
P28: 22 | Q28: =Q27+30 -> 46721 | R28: =TEXT($Q28,"MMMM")&TEXT($Q28," YYYY") -> November 2027 | S28: =($V$1/12+1)*S27+T27 -> 7837156.8 | T28: =$V$4 -> 2000000 | U28: =($V$2/12+1)*U27+$V$3 -> 1366465.1 | V28: =V27+$I$65 -> 326638.86 | W28: =W27+X27 -> 4331000 | X28: =T28 -> 2000000 | Y28: =SUM(S28:V28)-W28 -> 7199260.8
B29: Monthly Personal Expenses / Spending | C29: =D29*12 -> 88055.23 | D29: =SUM(M42:M48) -> 7337.9358 | L29: Other expenses Forest Lake | M29: ='Property Expenses'!C10 -> 607.26 | P29: 23 | Q29: =Q28+30 -> 46751 | R29: =TEXT($Q29,"MMMM")&TEXT($Q29," YYYY") -> December 2027 | S29: =($V$1/12+1)*S28+T28 -> 9882873.6 | U29: =($V$2/12+1)*U28+$V$3 -> 1387852.3 | V29: =V28+$I$65 -> 341716.9 | W29: =W28+X28 -> 6331000 | X29: =T29 -> 0 | Y29: =SUM(S29:V29)-W29 -> 5281442.8
B30: Rental Payment | C30: =D30*12 -> 0 | D30: ='Monthly Expenses Budget'!C10 -> 0 | L30: Other expenses Strathpine | M30: ='Property Expenses'!C18 -> 836.66667 | P30: 24 | Q30: =Q29+30 -> 46781 | R30: =TEXT($Q30,"MMMM")&TEXT($Q30," YYYY") -> January 2028 | S30: =($V$1/12+1)*S29+T29 -> 9940523.7 | U30: =($V$2/12+1)*U29+$V$3 -> 1409417.8 | V30: =V29+$I$65 -> 356794.94 | W30: =W29+X29 -> 6331000 | X30: =T30 -> 0 | Y30: =SUM(S30:V30)-W30 -> 5375736.4
B31: Other | D31: =M38 -> 0 | L31: Other expenses Mt Sheridan | M31: ='Property Expenses'!C26 -> 822.87333 | P31: 25 | Q31: =Q30+30 -> 46811 | R31: =TEXT($Q31,"MMMM")&TEXT($Q31," YYYY") -> February 2028 | S31: =($V$1/12+1)*S30+T30 -> 9998510.1 | U31: =($V$2/12+1)*U30+$V$3 -> 1431162.9 | V31: =V30+$I$65 -> 371872.98 | W31: =W30+X30 -> 6331000 | X31: =T31 -> 0 | Y31: =SUM(S31:V31)-W31 -> 5470545.9
G32: TOTAL EXPENSES | H32: (per month) | I32: =SUM(D22:D31) -> 21558.292 | L32: Other expenses Eimeo | M32: ='Property Expenses'!C34 -> 861.00667 | P32: 26 | Q32: =Q31+30 -> 46841 | R32: =TEXT($Q32,"MMMM")&TEXT($Q32," YYYY") -> March 2028 | S32: =($V$1/12+1)*S31+T31 -> 10056835 | U32: =($V$2/12+1)*U31+$V$3 -> 1453089.3 | V32: =V31+$I$65 -> 386951.02 | W32: =W31+X31 -> 6331000 | X32: =T32 -> 0 | Y32: =SUM(S32:V32)-W32 -> 5565875
L33: Other expenses Investment 5 | P33: 27 | Q33: =Q32+30 -> 46871 | R33: =TEXT($Q33,"MMMM")&TEXT($Q33," YYYY") -> April 2028 | S33: =($V$1/12+1)*S32+T32 -> 10115500 | U33: =($V$2/12+1)*U32+$V$3 -> 1475198.3 | V33: =V32+$I$65 -> 402029.06 | W33: =W32+X32 -> 6331000 | X33: =T33 -> 0 | Y33: =SUM(S33:V33)-W33 -> 5661727
B34: BALANCE SHEET | P34: 28 | Q34: =Q33+30 -> 46901 | R34: =TEXT($Q34,"MMMM")&TEXT($Q34," YYYY") -> May 2028 | S34: =($V$1/12+1)*S33+T33 -> 10174507 | U34: =($V$2/12+1)*U33+$V$3 -> 1497491.7 | V34: =V33+$I$65 -> 417107.1 | W34: =W33+X33 -> 6331000 | X34: =T34 -> 0 | Y34: =SUM(S34:V34)-W34 -> 5758105.4
P35: 29 | Q35: =Q34+30 -> 46931 | R35: =TEXT($Q35,"MMMM")&TEXT($Q35," YYYY") -> June 2028 | S35: =($V$1/12+1)*S34+T34 -> 10233858 | U35: =($V$2/12+1)*U34+$V$3 -> 1519970.8 | V35: =V34+$I$65 -> 432185.14 | W35: =W34+X34 -> 6331000 | X35: =T35 -> 0 | Y35: =SUM(S35:V35)-W35 -> 5855013.8
B36: ASSETS | E36: ASSET VALUE | G36: LIABILITIES (DEBT) | P36: 30 | Q36: =Q35+30 -> 46961 | R36: =TEXT($Q36,"MMMM")&TEXT($Q36," YYYY") -> July 2028 | S36: =($V$1/12+1)*S35+T35 -> 10293555 | U36: =($V$2/12+1)*U35+$V$3 -> 1542637.2 | V36: =V35+$I$65 -> 447263.18 | W36: =W35+X35 -> 6331000 | X36: =T36 -> 0 | Y36: =SUM(S36:V36)-W36 -> 5952455.8
P37: 31 | Q37: =Q36+30 -> 46991 | R37: =TEXT($Q37,"MMMM")&TEXT($Q37," YYYY") -> August 2028 | S37: =($V$1/12+1)*S36+T36 -> 10353601 | U37: =($V$2/12+1)*U36+$V$3 -> 1565492.5 | V37: =V36+$I$65 -> 462341.23 | W37: =W36+X36 -> 6331000 | X37: =T37 -> 0 | Y37: =SUM(S37:V37)-W37 -> 6050434.9
B38: Savings Account 1 | E38: =M52 -> 10000 | G38: Credit Card 1 (total limit) | I38: 10000 | L38: Other (Insert any other not covered) | P38: 32 | Q38: =Q37+30 -> 47021 | R38: =TEXT($Q38,"MMMM")&TEXT($Q38," YYYY") -> September 2028 | S38: =($V$1/12+1)*S37+T37 -> 10413997 | U38: =($V$2/12+1)*U37+$V$3 -> 1588538.3 | V38: =V37+$I$65 -> 477419.27 | W38: =W37+X37 -> 6331000 | X38: =T38 -> 0 | Y38: =SUM(S38:V38)-W38 -> 6148954.7
B39: Savings Account 2 | E39: =M53 -> 0 | G39: Credit Card 2 (total limit) | I39: 2000 | P39: 33 | Q39: =Q38+30 -> 47051 | R39: =TEXT($Q39,"MMMM")&TEXT($Q39," YYYY") -> October 2028 | S39: =($V$1/12+1)*S38+T38 -> 10474745 | U39: =($V$2/12+1)*U38+$V$3 -> 1611776.1 | V39: =V38+$I$65 -> 492497.31 | W39: =W38+X38 -> 6331000 | X39: =T39 -> 0 | Y39: =SUM(S39:V39)-W39 -> 6248018.9
G40: Personal Loans | L40: From Budget Spreadsheet - DO NOT UPDATE THIS | M40: =SUM(M41:M48) -> 7337.9358 | P40: 34 | Q40: =Q39+30 -> 47081 | R40: =TEXT($Q40,"MMMM")&TEXT($Q40," YYYY") -> November 2028 | S40: =($V$1/12+1)*S39+T39 -> 10535848 | T40: =$V$4 -> 2000000 | U40: =($V$2/12+1)*U39+$V$3 -> 1635207.6 | V40: =V39+$I$65 -> 507575.35 | W40: =W39+X39 -> 6331000 | X40: =T40 -> 2000000 | Y40: =SUM(S40:V40)-W40 -> 8347631.1
B41: Stocks (local) | E41: =M55 -> 190000 | G41: Other Loans | L41: ='Monthly Expenses Budget'!B5 -> Home and other Fixed Expenses | M41: ='Monthly Expenses Budget'!C5 -> 0 | P41: 35 | Q41: =Q40+30 -> 47111 | R41: =TEXT($Q41,"MMMM")&TEXT($Q41," YYYY") -> December 2028 | S41: =($V$1/12+1)*S40+T40 -> 12597307 | U41: =($V$2/12+1)*U40+$V$3 -> 1658834.3 | V41: =V40+$I$65 -> 522653.39 | W41: =W40+X40 -> 8331000 | X41: =T41 -> 0 | Y41: =SUM(S41:V41)-W41 -> 6447795
B42: Stocks (offshore) | E42: =M56 -> 144000 | L42: ='Monthly Expenses Budget'!B12 -> Essentials | M42: ='Monthly Expenses Budget'!C12 -> 875.7325 | P42: 36 | Q42: =Q41+30 -> 47141 | R42: =TEXT($Q42,"MMMM")&TEXT($Q42," YYYY") -> January 2029 | S42: =($V$1/12+1)*S41+T41 -> 12670792 | U42: =($V$2/12+1)*U41+$V$3 -> 1682657.9 | V42: =V41+$I$65 -> 537731.43 | W42: =W41+X41 -> 8331000 | X42: =T42 -> 0 | Y42: =SUM(S42:V42)-W42 -> 6560180.9
B43: Other stocks | E43: =M57 -> 622000 | L43: ='Monthly Expenses Budget'!B22 -> Groceries | M43: ='Monthly Expenses Budget'!C22 -> 2120 | P43: 37 | Q43: =Q42+30 -> 47171 | R43: =TEXT($Q43,"MMMM")&TEXT($Q43," YYYY") -> February 2029 | S43: =($V$1/12+1)*S42+T42 -> 12744705 | U43: =($V$2/12+1)*U42+$V$3 -> 1706680.1 | V43: =V42+$I$65 -> 552809.47 | W43: =W42+X42 -> 8331000 | X43: =T43 -> 0 | Y43: =SUM(S43:V43)-W43 -> 6673194.1
L44: ='Monthly Expenses Budget'!B31 -> House Maintenance | M44: ='Monthly Expenses Budget'!C31 -> 230 | P44: 38 | Q44: =Q43+30 -> 47201 | R44: =TEXT($Q44,"MMMM")&TEXT($Q44," YYYY") -> March 2029 | S44: =($V$1/12+1)*S43+T43 -> 12819049 | U44: =($V$2/12+1)*U43+$V$3 -> 1730902.4 | V44: =V43+$I$65 -> 567887.51 | W44: =W43+X43 -> 8331000 | X44: =T44 -> 0 | Y44: =SUM(S44:V44)-W44 -> 6786838.5
B45: Super 1 | E45: =M59 -> 220000 | L45: ='Monthly Expenses Budget'!B39 -> Health | M45: ='Monthly Expenses Budget'!C39 -> 1514.7033 | P45: 39 | Q45: =Q44+30 -> 47231 | R45: =TEXT($Q45,"MMMM")&TEXT($Q45," YYYY") -> April 2029 | S45: =($V$1/12+1)*S44+T44 -> 12893826 | U45: =($V$2/12+1)*U44+$V$3 -> 1755326.6 | V45: =V44+$I$65 -> 582965.55 | W45: =W44+X44 -> 8331000 | X45: =T45 -> 0 | Y45: =SUM(S45:V45)-W45 -> 6901118.6
B46: Super 2 | E46: =M60 -> 200000 | L46: ='Monthly Expenses Budget'!B49 -> Discretionary | M46: ='Monthly Expenses Budget'!C49 -> 1100 | P46: 40 | Q46: =Q45+30 -> 47261 | R46: =TEXT($Q46,"MMMM")&TEXT($Q46," YYYY") -> May 2029 | S46: =($V$1/12+1)*S45+T45 -> 12969040 | U46: =($V$2/12+1)*U45+$V$3 -> 1779954.3 | V46: =V45+$I$65 -> 598043.59 | W46: =W45+X45 -> 8331000 | X46: =T46 -> 0 | Y46: =SUM(S46:V46)-W46 -> 7016038.3
D47: EQUITY | L47: ='Monthly Expenses Budget'!B58 -> Sports / Activities | M47: ='Monthly Expenses Budget'!C58 -> 397.5 | P47: 41 | Q47: =Q46+30 -> 47291 | R47: =TEXT($Q47,"MMMM")&TEXT($Q47," YYYY") -> June 2029 | S47: =($V$1/12+1)*S46+T46 -> 13044693 | U47: =($V$2/12+1)*U46+$V$3 -> 1804787.2 | V47: =V46+$I$65 -> 613121.63 | W47: =W46+X46 -> 8331000 | X47: =T47 -> 0 | Y47: =SUM(S47:V47)-W47 -> 7131602
B48: Home | D48: =E48-I48 -> 1920000 | E48: =M62 -> 1920000 | G48: Mortgage - Home | I48: =M75 -> 0 | L48: ='Monthly Expenses Budget'!B64 -> Other | M48: ='Monthly Expenses Budget'!C64 -> 1100 | P48: 42 | Q48: =Q47+30 -> 47321 | R48: =TEXT($Q48,"MMMM")&TEXT($Q48," YYYY") -> July 2029 | S48: =($V$1/12+1)*S47+T47 -> 13120787 | U48: =($V$2/12+1)*U47+$V$3 -> 1829827.1 | V48: =V47+$I$65 -> 628199.67 | W48: =W47+X47 -> 8331000 | X48: =T48 -> 0 | Y48: =SUM(S48:V48)-W48 -> 7247814
B49: Investment 1 - Forest Lake value | D49: =E49-I49 -> 478000 | E49: =M63 -> 990000 | G49: Investment 1 Forest Lake - Mortgage | I49: =M77 -> 512000 | P49: 43 | Q49: =Q48+30 -> 47351 | R49: =TEXT($Q49,"MMMM")&TEXT($Q49," YYYY") -> August 2029 | S49: =($V$1/12+1)*S48+T48 -> 13197325 | U49: =($V$2/12+1)*U48+$V$3 -> 1855075.7 | V49: =V48+$I$65 -> 643277.72 | W49: =W48+X48 -> 8331000 | X49: =T49 -> 0 | Y49: =SUM(S49:V49)-W49 -> 7364678.5
B50: Investment 2 - Strathpine value | D50: =E50-I50 -> 377000 | E50: =M64 -> 580000 | G50: Investment 2 Strathpine - Mortgage | I50: =M78 -> 203000 | P50: 44 | Q50: =Q49+30 -> 47381 | R50: =TEXT($Q50,"MMMM")&TEXT($Q50," YYYY") -> September 2029 | S50: =($V$1/12+1)*S49+T49 -> 13274310 | U50: =($V$2/12+1)*U49+$V$3 -> 1880534.7 | V50: =V49+$I$65 -> 658355.76 | W50: =W49+X49 -> 8331000 | X50: =T50 -> 0 | Y50: =SUM(S50:V50)-W50 -> 7482199.9
B51: Investment 3 - Mt Sheridan value | D51: =E51-I51 -> -30000 | E51: =M65 -> 750000 | G51: Investment 3 Mt Sheridan - Mortgage | I51: =M79 -> 780000 | L51: ASSETS | P51: 45 | Q51: =Q50+30 -> 47411 | R51: =TEXT($Q51,"MMMM")&TEXT($Q51," YYYY") -> October 2029 | S51: =($V$1/12+1)*S50+T50 -> 13351743 | U51: =($V$2/12+1)*U50+$V$3 -> 1906205.8 | V51: =V50+$I$65 -> 673433.8 | W51: =W50+X50 -> 8331000 | X51: =T51 -> 0 | Y51: =SUM(S51:V51)-W51 -> 7600382.6
B52: Investment 4 - Eimeo value | D52: =E52-I52 -> -4000 | E52: =M66 -> 820000 | G52: Investment 4 Eimeo - Mortgage | I52: =M80 -> 824000 | L52: Savings (account 1) | M52: 10000 | P52: 46 | Q52: =Q51+30 -> 47441 | R52: =TEXT($Q52,"MMMM")&TEXT($Q52," YYYY") -> November 2029 | S52: =($V$1/12+1)*S51+T51 -> 13429628 | T52: =$V$4 -> 2000000 | U52: =($V$2/12+1)*U51+$V$3 -> 1932090.8 | V52: =V51+$I$65 -> 688511.84 | W52: =W51+X51 -> 8331000 | X52: =T52 -> 2000000 | Y52: =SUM(S52:V52)-W52 -> 9719230.8
B53: Investment 5 - value | D53: =E53-I53 -> 0 | E53: =M67 -> 0 | G53: Investment 5 - Mortgage | I53: =M81 -> 0 | L53: Savings (account 2) | P53: 47 | Q53: =Q52+30 -> 47471 | R53: =TEXT($Q53,"MMMM")&TEXT($Q53," YYYY") -> December 2029 | S53: =($V$1/12+1)*S52+T52 -> 15507968 | U53: =($V$2/12+1)*U52+$V$3 -> 1958191.6 | V53: =V52+$I$65 -> 703589.88 | W53: =W52+X52 -> 10331000 | X53: =T53 -> 0 | Y53: =SUM(S53:V53)-W53 -> 7838749.1
P54: 48 | Q54: =Q53+30 -> 47501 | R54: =TEXT($Q54,"MMMM")&TEXT($Q54," YYYY") -> January 2030 | S54: =($V$1/12+1)*S53+T53 -> 15598431 | U54: =($V$2/12+1)*U53+$V$3 -> 1984509.9 | V54: =V53+$I$65 -> 718667.92 | W54: =W53+X53 -> 10331000 | X54: =T54 -> 0 | Y54: =SUM(S54:V54)-W54 -> 7970608.6
L55: Stocks / Shares (ASX) | M55: 190000 | P55: 49 | Q55: =Q54+30 -> 47531 | R55: =TEXT($Q55,"MMMM")&TEXT($Q55," YYYY") -> February 2030 | S55: =($V$1/12+1)*S54+T54 -> 15689422 | U55: =($V$2/12+1)*U54+$V$3 -> 2011047.4 | V55: =V54+$I$65 -> 733745.96 | W55: =W54+X54 -> 10331000 | X55: =T55 -> 0 | Y55: =SUM(S55:V55)-W55 -> 8103215
B56: TOTAL ASSETS (including Super) | E56: =SUM(E38:E55) -> 6446000 | L56: Stocks / Shares (NASDAQ Other) | M56: 144000 | P56: 50 | Q56: =Q55+30 -> 47561 | R56: =TEXT($Q56,"MMMM")&TEXT($Q56," YYYY") -> March 2030 | S56: =($V$1/12+1)*S55+T55 -> 15780943 | U56: =($V$2/12+1)*U55+$V$3 -> 2037806.2 | V56: =V55+$I$65 -> 748824 | W56: =W55+X55 -> 10331000 | X56: =T56 -> 0 | Y56: =SUM(S56:V56)-W56 -> 8236573.4
B57: TOTAL ASSETS | E57: =SUM(E56-E46-E45) -> 6026000 | G57: TOTAL LIABILITY | I57: =SUM(I38:I56) -> 2331000 | L57: Other stocks (Crypto etc) | M57: 622000 | P57: 51 | Q57: =Q56+30 -> 47591 | R57: =TEXT($Q57,"MMMM")&TEXT($Q57," YYYY") -> April 2030 | S57: =($V$1/12+1)*S56+T56 -> 15872999 | U57: =($V$2/12+1)*U56+$V$3 -> 2064787.9 | V57: =V56+$I$65 -> 763902.04 | W57: =W56+X56 -> 10331000 | X57: =T57 -> 0 | Y57: =SUM(S57:V57)-W57 -> 8370688.7
P58: 52 | Q58: =Q57+30 -> 47621 | R58: =TEXT($Q58,"MMMM")&TEXT($Q58," YYYY") -> May 2030 | S58: =($V$1/12+1)*S57+T57 -> 15965591 | U58: =($V$2/12+1)*U57+$V$3 -> 2091994.4 | V58: =V57+$I$65 -> 778980.08 | W58: =W57+X57 -> 10331000 | X58: =T58 -> 0 | Y58: =SUM(S58:V58)-W58 -> 8505565.8
L59: Super 1 | M59: 220000 | P59: 53 | Q59: =Q58+30 -> 47651 | R59: =TEXT($Q59,"MMMM")&TEXT($Q59," YYYY") -> June 2030 | S59: =($V$1/12+1)*S58+T58 -> 16058724 | U59: =($V$2/12+1)*U58+$V$3 -> 2119427.7 | V59: =V58+$I$65 -> 794058.12 | W59: =W58+X58 -> 10331000 | X59: =T59 -> 0 | Y59: =SUM(S59:V59)-W59 -> 8641209.7
L60: Super 2 | M60: 200000 | P60: 54 | Q60: =Q59+30 -> 47681 | R60: =TEXT($Q60,"MMMM")&TEXT($Q60," YYYY") -> July 2030 | S60: =($V$1/12+1)*S59+T59 -> 16152400 | U60: =($V$2/12+1)*U59+$V$3 -> 2147089.6 | V60: =V59+$I$65 -> 809136.16 | W60: =W59+X59 -> 10331000 | X60: =T60 -> 0 | Y60: =SUM(S60:V60)-W60 -> 8777625.6
B61: SUMMARY METRICS | P61: 55 | Q61: =Q60+30 -> 47711 | R61: =TEXT($Q61,"MMMM")&TEXT($Q61," YYYY") -> August 2030 | S61: =($V$1/12+1)*S60+T60 -> 16246622 | U61: =($V$2/12+1)*U60+$V$3 -> 2174982 | V61: =V60+$I$65 -> 824214.21 | W61: =W60+X60 -> 10331000 | X61: =T61 -> 0 | Y61: =SUM(S61:V61)-W61 -> 8914818.4
L62: Home Value (estimate) | M62: 1920000 | P62: 56 | Q62: =Q61+30 -> 47741 | R62: =TEXT($Q62,"MMMM")&TEXT($Q62," YYYY") -> September 2030 | S62: =($V$1/12+1)*S61+T61 -> 16341394 | U62: =($V$2/12+1)*U61+$V$3 -> 2203106.9 | V62: =V61+$I$65 -> 839292.25 | W62: =W61+X61 -> 10331000 | X62: =T62 -> 0 | Y62: =SUM(S62:V62)-W62 -> 9052793.2
B63: Overall Net worth | G63: Cashflow | L63: Investment 1 - Forest Lake value | M63: 990000 | P63: 57 | Q63: =Q62+30 -> 47771 | R63: =TEXT($Q63,"MMMM")&TEXT($Q63," YYYY") -> October 2030 | S63: =($V$1/12+1)*S62+T62 -> 16436719 | U63: =($V$2/12+1)*U62+$V$3 -> 2231466.1 | V63: =V62+$I$65 -> 854370.29 | W63: =W62+X62 -> 10331000 | X63: =T63 -> 0 | Y63: =SUM(S63:V63)-W63 -> 9191555.3
L64: Investment 2 - Strathpine value | M64: 580000 | P64: 58 | Q64: =Q63+30 -> 47801 | R64: =TEXT($Q64,"MMMM")&TEXT($Q64," YYYY") -> November 2030 | S64: =($V$1/12+1)*S63+T63 -> 16532600 | T64: =$V$4 -> 2000000 | U64: =($V$2/12+1)*U63+$V$3 -> 2260061.7 | V64: =V63+$I$65 -> 869448.33 | W64: =W63+X63 -> 10331000 | X64: =T64 -> 2000000 | Y64: =SUM(S64:V64)-W64 -> 11331110
B65: Total Net Worth (ex Super) | D65: =E57-I57 -> 3695000 | G65: CASHFLOW | H65: monthly | I65: =I19-I32 -> 15078.041 | L65: Investment 3 - Mt Sheridan value | M65: 750000 | P65: 59 | Q65: =Q64+30 -> 47831 | R65: =TEXT($Q65,"MMMM")&TEXT($Q65," YYYY") -> December 2030 | S65: =($V$1/12+1)*S64+T64 -> 18629040 | U65: =($V$2/12+1)*U64+$V$3 -> 2288895.5 | V65: =V64+$I$65 -> 884526.37 | W65: =W64+X64 -> 12331000 | X65: =T65 -> 0 | Y65: =SUM(S65:V65)-W65 -> 9471461.8
B66: Total N | L66: Investment 4 - Eimeo value | M66: 820000 | P66: 60 | Q66: =Q65+30 -> 47861 | R66: =TEXT($Q66,"MMMM")&TEXT($Q66," YYYY") -> January 2031 | S66: =($V$1/12+1)*S65+T65 -> 18737709 | U66: =($V$2/12+1)*U65+$V$3 -> 2317969.6 | V66: =V65+$I$65 -> 899604.41 | W66: =W65+X65 -> 12331000 | X66: =T66 -> 0 | Y66: =SUM(S66:V66)-W66 -> 9624283.4
B67: Total Net Worth (incl Super) | D67: =E56-I57 -> 4115000 | G67: Savings Potential | H67: yearly | I67: =I65*12 -> 180936.49 | L67: Investmen 5 - value
B68: Total Net Asset Worth (excl PPOR) | D68: =D65-D48 -> 1775000
I69: =I67*0.07 -> 12665.554 | L69: LIABILITIES
B70: Property Stats | G70: Passive Income | L70: Credit Card 1 (total limit) | M70: 2000
L71: Credit Card 2 (total limit) | M71: 3000
B72: Total Property Debt | D72: =SUM(I48:I54) -> 2319000 | G72: Passive Income | H72: monthly | I72: =H5 -> 13636.333 | L72: Personal Loans
L73: Other Loans
B74: Total Property Assets | D74: =SUM(E48:E54) -> 5060000 | G74: Amount for 100% Passive (break even) | H74: monthly | I74: =I32-H5 -> 7921.9592
B75: Potential Asset Growth per year | D75: =SUM(E41:E54)*0.07 -> 450520 | H75: yearly | I75: =I74*12 -> 95063.51 | L75: Home - Mortgage
G76: Capital Required to Invest | I76: =I74*12/0.065 -> 1462515.5
B77: Total Equity Available | D77: =SUM(D48:D53) -> 2741000 | G77: Estimated Capital required (at 6.5% income) to be financially independent | L77: Investment 1 Forest Lake - Mortgage | M77: 512000
L78: Investment 2 Strathpine - Mortgage | M78: 203000
B79: Current LVR | D79: =D72/D74 -> 0.4583004 | L79: Investment 3 Mt Sheridan - Mortgage | M79: 780000
G80: Liquidity | L80: Investment 4 Eimeo - Mortgage | M80: 824000
B81: Equity available 80% | D81: =(80%-D79)*D74 -> 1729000 | L81: Investment 5 - Mortgage
G82: Available Cash (including Line of Credit) | I82: =SUM(E38:E39) -> 10000
B83: Potential Property Purchase (with equity as leverage) | D83: =D81/0.2 -> 8645000 | G83: Stocks currently invested | I83: =SUM(E41:E43) -> 956000
G84: Total Liquidity | I84: =SUM(I82:I83) -> 966000
B85: Borrowing Power
G86: Emergency Fund
B87: Bank will lend you | D87: =D90-D72 -> -264111.91
B88: Assumed 3% above loan rate for Assessment Rate | G88: Without Salary - you'll last this many MONTHS | I88: =SUM(E38:E43)/(I32-H5) -> 121.93953 | L88: Sale from Home | M88: 2100000
G89: Without Salary - you'll last this many YEARS | I89: =SUM(E38:E43)/(I32-H5)/12 -> 10.161628 | L89: Sell non crypto stocks | M89: 451000
B90: Total Borrowing Capacity | D90: =PV(8%/12,30*12,H24,0)*-1 -> 2054888.1 | G90: Every WORKING month buys you this many MONTHS | I90: =H24/(I32-H5) -> 1.9033222 | L90: Sell Forest Lake | M90: ???
L91: New Mortgage | M91: 1500000
L92: 200k of Crypto stocks | M92: 200000
L93: 400k of crypto stocks | M93: 400000
M94: =SUM(M88:M93) -> 4651000
B96: Dream 1 - Financial Security (Cover the Basics) | G96: Emergency Fund needed - 12 Months
B97: 1. Mortgage | D97: 0 | G97: =D124 -> 88055.23
B98: 2. Utilities / Essentials | D98: =M42 -> 875.7325
B99: 3. Food | D99: =M43 -> 2120 | G99: Current Capital
B100: 4. Transportation | D100: 500 | G100: Savings | H100: =SUM(M52:M53) -> 10000
B101: 5. Insurance Costs | D101: 500 | G101: Stocks | H101: =SUM(M55:M57) -> 956000
...

Sheet FV_October25
U1: Property Growth Rate (PY) | V1: 0.07
B2: INCOME STATEMENT | L2: INPUTS!!! Fill out the ORANGE cells ONLY | U2: Stock Growth Rate (PY) | V2: 0.1
U3: Stock contribution per month | V3: 10000 | AI3: NET GROWTH FORECAST
B4: INCOME | C4: PER YEAR | D4: PER MONTH | E4: CASHFLOW PM | G4: PASSIVE | H4: PER MONTH | I4: PER YEAR | L4: INCOME | U4: Yearly Prop Purchase Value | V4: 2000000
G5: PASSIVE INCOME | H5: =SUM(D8:D18) -> 13636.333 | I5: =H5*12 -> 163636
B6: Salary 1 | C6: =D6*12 -> 276000 | D6: =M6 -> 23000 | L6: Salary 1 (ex tax per month) | M6: 23000 | P6: Date | Q6: Date | R6: Month | S6: Properties | T6: Add Prop | U6: Stocks | V6: Savings | W6: Liabilities | X6: Add Liab | Y6: Total Net Worth
B7: Salary 2 | C7: =D7*12 -> 0 | D7: =M7 -> 0 | L7: Salary 2 (ex tax per month) | P7: 1 | Q7: =TODAY() -> 46091 | R7: =TEXT($Q7,"MMMM")&TEXT($Q7," YYYY") -> March 2026 | S7: =SUM(E48:E54) -> 6700000 | U7: =SUM(E41:E43) -> 260000 | V7: =$E$38 -> 13900 | W7: =$I$57 -> 3530000 | X7: =T7 -> 0 | Y7: =SUM(S7:V7)-W7 -> 3443900
B8: Interest Earned (from savings) | D8: =M8 -> 10 | E8: =D8 -> 10 | L8: Interest from Savings (per month) | M8: 10 | P8: 2 | Q8: =Q7+30 -> 46121 | R8: =TEXT($Q8,"MMMM")&TEXT($Q8," YYYY") -> April 2026 | S8: =($V$1/12+1)*S7+T7 -> 6739083.3 | U8: =($V$2/12+1)*U7+$V$3 -> 272166.67 | V8: =V7+$I$65 -> 21707.671 | W8: =W7+X7 -> 3530000 | X8: =T8 -> 0 | Y8: =SUM(S8:V8)-W8 -> 3502957.7
B9: Dividends | C9: =D9*12 -> 9960 | D9: =M9 -> 830 | E9: =D9 -> 830 | L9: Income from Dividends (per month) | M9: 830 | P9: 3 | Q9: =Q8+30 -> 46151 | R9: =TEXT($Q9,"MMMM")&TEXT($Q9," YYYY") -> May 2026 | S9: =($V$1/12+1)*S8+T8 -> 6778394.7 | U9: =($V$2/12+1)*U8+$V$3 -> 284434.72 | V9: =V8+$I$65 -> 29515.341 | W9: =W8+X8 -> 3530000 | X9: =T9 -> 0 | Y9: =SUM(S9:V9)-W9 -> 3562344.7
B10: Other income | D10: =M10 -> 0 | L10: Any other income (per month) | M10: 0 | P10: 4 | Q10: =Q9+30 -> 46181 | R10: =TEXT($Q10,"MMMM")&TEXT($Q10," YYYY") -> June 2026 | S10: =($V$1/12+1)*S9+T9 -> 6817935.3 | U10: =($V$2/12+1)*U9+$V$3 -> 296805.01 | V10: =V9+$I$65 -> 37323.012 | W10: =W9+X9 -> 3530000 | X10: =T10 -> 0 | Y10: =SUM(S10:V10)-W10 -> 3622063.3
P11: 5 | Q11: =Q10+30 -> 46211 | R11: =TEXT($Q11,"MMMM")&TEXT($Q11," YYYY") -> July 2026 | S11: =($V$1/12+1)*S10+T10 -> 6857706.6 | U11: =($V$2/12+1)*U10+$V$3 -> 309278.39 | V11: =V10+$I$65 -> 45130.683 | W11: =W10+X10 -> 3530000 | X11: =T11 -> 0 | Y11: =SUM(S11:V11)-W11 -> 3682115.6
B12: Real Estate / Other income (gross): | G12: Property Yield | H12: % Gross | I12: % Net | P12: 6 | Q12: =Q11+30 -> 46241 | R12: =TEXT($Q12,"MMMM")&TEXT($Q12," YYYY") -> August 2026 | S12: =($V$1/12+1)*S11+T11 -> 6897709.9 | U12: =($V$2/12+1)*U11+$V$3 -> 321855.71 | V12: =V11+$I$65 -> 52938.353 | W12: =W11+X11 -> 3530000 | X12: =T12 -> 0 | Y12: =SUM(S12:V12)-W12 -> 3742503.9
P13: 7 | Q13: =Q12+30 -> 46271 | R13: =TEXT($Q13,"MMMM")&TEXT($Q13," YYYY") -> September 2026 | S13: =($V$1/12+1)*S12+T12 -> 6937946.5 | U13: =($V$2/12+1)*U12+$V$3 -> 334537.84 | V13: =V12+$I$65 -> 60746.024 | W13: =W12+X12 -> 3530000 | X13: =T13 -> 0 | Y13: =SUM(S13:V13)-W13 -> 3803230.4
B14: =L14 -> Rental income Forest Lake (per week) | C14: =D14*12 -> 32240 | D14: =M14*52/12 -> 2686.6667 | E14: =SUM(D14-D23) -> -369.66 | G14: Investment 1 (rental income) | H14: =C14/E49 -> 0.031 | I14: =(D14-M29)/E49*12 -> 0.023993154 | L14: Rental income Forest Lake (per week) | M14: 620 | P14: 8 | Q14: =Q13+30 -> 46301 | R14: =TEXT($Q14,"MMMM")&TEXT($Q14," YYYY") -> October 2026 | S14: =($V$1/12+1)*S13+T13 -> 6978417.9 | U14: =($V$2/12+1)*U13+$V$3 -> 347325.65 | V14: =V13+$I$65 -> 68553.694 | W14: =W13+X13 -> 3530000 | X14: =T14 -> 0 | Y14: =SUM(S14:V14)-W14 -> 3864297.2
B15: =L15 -> Rental income Strathpine (per week) | C15: =D15*12 -> 39156 | D15: =M15*52/12 -> 3263 | E15: =SUM(D15-D24) -> 1326.1667 | G15: Investment 2 (rental income) | H15: =C15/E50 -> 0.067510345 | I15: =(D15-M30)/E50*12 -> 0.0502 | L15: Rental income Strathpine (per week) | M15: 753 | P15: 9 | Q15: =Q14+30 -> 46331 | R15: =TEXT($Q15,"MMMM")&TEXT($Q15," YYYY") -> November 2026 | S15: =($V$1/12+1)*S14+T14 -> 7019125.3 | U15: =($V$2/12+1)*U14+$V$3 -> 360220.03 | V15: =V14+$I$65 -> 76361.365 | W15: =W14+X14 -> 3530000 | X15: =T15 -> 0 | Y15: =SUM(S15:V15)-W15 -> 3925706.7
B16: =L16 -> Rental income Mt Sheridan (per week) | C16: =D16*12 -> 37960 | D16: =M16*52/12 -> 3163.3333 | E16: =SUM(D16-D25) -> -1390.54 | G16: Investment 3 (rental income) | H16: =C16/E51 -> 0.049947368 | I16: =(D16-M31)/E51*12 -> 0.036954632 | L16: Rental income Mt Sheridan (per week) | M16: 730 | P16: 10 | Q16: =Q15+30 -> 46361 | R16: =TEXT($Q16,"MMMM")&TEXT($Q16," YYYY") -> December 2026 | S16: =($V$1/12+1)*S15+T15 -> 7060070.2 | U16: =($V$2/12+1)*U15+$V$3 -> 373221.87 | V16: =V15+$I$65 -> 84169.036 | W16: =W15+X15 -> 3530000 | X16: =T16 -> 0 | Y16: =SUM(S16:V16)-W16 -> 3987461.1
B17: =L17 -> Rental income - Eimeo (per week) | C17: =D17*12 -> 44200 | D17: =M17*52/12 -> 3683.3333 | E17: =SUM(D17-D26) -> -1119.14 | G17: Investment 4 (rental income) | H17: =C17/E52 -> 0.053902439 | I17: =(D17-M32)/E52*12 -> 0.041302341 | L17: Rental income - Eimeo (per week) | M17: 850 | P17: 11 | Q17: =Q16+30 -> 46391 | R17: =TEXT($Q17,"MMMM")&TEXT($Q17," YYYY") -> January 2027 | S17: =($V$1/12+1)*S16+T16 -> 7101253.9 | T17: =$V$4 -> 2000000 | U17: =($V$2/12+1)*U16+$V$3 -> 386332.05 | V17: =V16+$I$65 -> 91976.706 | W17: =W16+X16 -> 3530000 | X17: =T17 -> 2000000 | Y17: =SUM(S17:V17)-W17 -> 6049562.7
B18: =L18 -> Rental income - (per week) | C18: =D18*12 -> 0 | D18: =M18*52/12 -> 0 | E18: =IF(SUM(D18-D27)>=0, SUM(D18-D27), "") -> 0 | G18: Investment 5 (rental income) | H18: - | I18: - | L18: Rental income - (per week) | P18: 12 | Q18: =Q17+30 -> 46421 | R18: =TEXT($Q18,"MMMM")&TEXT($Q18," YYYY") -> February 2027 | S18: =($V$1/12+1)*S17+T17 -> 9142677.9 | U18: =($V$2/12+1)*U17+$V$3 -> 399551.48 | V18: =V17+$I$65 -> 99784.377 | W18: =W17+X17 -> 5530000 | X18: =T18 -> 0 | Y18: =SUM(S18:V18)-W18 -> 4112013.8
B19: Negative Gearing Potential | C19: {=SUM(E16:E17+E14)*0.4*-12} -> 15595.2 | D19: =C19/12 -> 1299.6 | E19: =SUM(E14:E18) -> -1553.1733 | G19: TOTAL INCOME | H19: (per month) | I19: =SUM(D6:D18) -> 36636.333 | P19: 13 | Q19: =Q18+30 -> 46451 | R19: =TEXT($Q19,"MMMM")&TEXT($Q19," YYYY") -> March 2027 | S19: =($V$1/12+1)*S18+T18 -> 9196010.2 | U19: =($V$2/12+1)*U18+$V$3 -> 412881.08 | V19: =V18+$I$65 -> 107592.05 | W19: =W18+X18 -> 5530000 | X19: =T19 -> 0 | Y19: =SUM(S19:V19)-W19 -> 4186483.3
B20: EXPENSES | C20: PER YEAR | D20: PER MONTH | L20: EXPENSES | P20: 14 | Q20: =Q19+30 -> 46481 | R20: =TEXT($Q20,"MMMM")&TEXT($Q20," YYYY") -> April 2027 | S20: =($V$1/12+1)*S19+T19 -> 9249653.6 | U20: =($V$2/12+1)*U19+$V$3 -> 426321.75 | V20: =V19+$I$65 -> 115399.72 | W20: =W19+X19 -> 5530000 | X20: =T20 -> 0 | Y20: =SUM(S20:V20)-W20 -> 4261375.1
P21: 15 | Q21: =Q20+30 -> 46511 | R21: =TEXT($Q21,"MMMM")&TEXT($Q21," YYYY") -> May 2027 | S21: =($V$1/12+1)*S20+T20 -> 9303609.9 | U21: =($V$2/12+1)*U20+$V$3 -> 439874.44 | V21: =V20+$I$65 -> 123207.39 | W21: =W20+X20 -> 5530000 | X21: =T21 -> 0 | Y21: =SUM(S21:V21)-W21 -> 4336691.7
B22: Mortgage - Home per month | C22: =D22*12 -> 85694.642 | D22: =PMT(M22/12, 25*12, -M75) -> 7141.2202 | L22: HOME Mortgage (P+I) - per month | M22: 0.0542 | P22: 16 | Q22: =Q21+30 -> 46541 | R22: =TEXT($Q22,"MMMM")&TEXT($Q22," YYYY") -> June 2027 | S22: =($V$1/12+1)*S21+T21 -> 9357881 | U22: =($V$2/12+1)*U21+$V$3 -> 453540.06 | V22: =V21+$I$65 -> 131015.06 | W22: =W21+X21 -> 5530000 | X22: =T22 -> 0 | Y22: =SUM(S22:V22)-W22 -> 4412436.1
B23: Interest / Expenses Forest Lake | C23: =D23*12 -> 36675.92 | D23: =M23*I49/12+(M29) -> 3056.3267 | L23: Interest Forest Lake | M23: 0.0574 | P23: 17 | Q23: =Q22+30 -> 46571 | R23: =TEXT($Q23,"MMMM")&TEXT($Q23," YYYY") -> July 2027 | S23: =($V$1/12+1)*S22+T22 -> 9412468.6 | U23: =($V$2/12+1)*U22+$V$3 -> 467319.56 | V23: =V22+$I$65 -> 138822.73 | W23: =W22+X22 -> 5530000 | X23: =T23 -> 0 | Y23: =SUM(S23:V23)-W23 -> 4488610.9
B24: Interest / Expenses Strathpine | C24: =D24*12 -> 23242 | D24: =M24*I50/12+(M30) -> 1936.8333 | G24: CASH FLOW (monthly) | H24: =I19-I32 -> 7807.6706 | L24: Interest Strathpine | M24: =M23 -> 0.0574 | P24: 18 | Q24: =Q23+30 -> 46601 | R24: =TEXT($Q24,"MMMM")&TEXT($Q24," YYYY") -> August 2027 | S24: =($V$1/12+1)*S23+T23 -> 9467374.7 | U24: =($V$2/12+1)*U23+$V$3 -> 481213.89 | V24: =V23+$I$65 -> 146630.4 | W24: =W23+X23 -> 5530000 | X24: =T24 -> 0 | Y24: =SUM(S24:V24)-W24 -> 4565219
B25: Interest / Expenses Mt Sheridan | C25: =D25*12 -> 54646.48 | D25: =M25*I51/12+(M31) -> 4553.8733 | G25: Total Income - Total Expenses | L25: Interest Mt Sheridan | M25: =M24 -> 0.0574 | P25: 19 | Q25: =Q24+30 -> 46631 | R25: =TEXT($Q25,"MMMM")&TEXT($Q25," YYYY") -> September 2027 | S25: =($V$1/12+1)*S24+T24 -> 9522601 | U25: =($V$2/12+1)*U24+$V$3 -> 495224 | V25: =V24+$I$65 -> 154438.07 | W25: =W24+X24 -> 5530000 | X25: =T25 -> 0 | Y25: =SUM(S25:V25)-W25 -> 4642263.1
B26: Interest / Expenses Eimeo | C26: =D26*12 -> 57629.68 | D26: =M26*I52/12+(M32) -> 4802.4733 | L26: Interest Eimeo | M26: =M25 -> 0.0574 | P26: 20 | Q26: =Q25+30 -> 46661 | R26: =TEXT($Q26,"MMMM")&TEXT($Q26," YYYY") -> October 2027 | S26: =($V$1/12+1)*S25+T25 -> 9578149.5 | U26: =($V$2/12+1)*U25+$V$3 -> 509350.87 | V26: =V25+$I$65 -> 162245.74 | W26: =W25+X25 -> 5530000 | X26: =T26 -> 0 | Y26: =SUM(S26:V26)-W26 -> 4719746.1
B27: Interest / Expenses Investment 5 | C27: =D27*12 -> 0 | D27: =M27*I53/12 -> 0 | L27: Interest Investment 5 | M27: =M26 -> 0.0574 | P27: 21 | Q27: =Q26+30 -> 46691 | R27: =TEXT($Q27,"MMMM")&TEXT($Q27," YYYY") -> October 2027 | S27: =($V$1/12+1)*S26+T26 -> 9634022.1 | U27: =($V$2/12+1)*U26+$V$3 -> 523595.46 | V27: =V26+$I$65 -> 170053.41 | W27: =W26+X26 -> 5530000 | X27: =T27 -> 0 | Y27: =SUM(S27:V27)-W27 -> 4797670.9
P28: 22 | Q28: =Q27+30 -> 46721 | R28: =TEXT($Q28,"MMMM")&TEXT($Q28," YYYY") -> November 2027 | S28: =($V$1/12+1)*S27+T27 -> 9690220.5 | T28: =$V$4 -> 2000000 | U28: =($V$2/12+1)*U27+$V$3 -> 537958.75 | V28: =V27+$I$65 -> 177861.08 | W28: =W27+X27 -> 5530000 | X28: =T28 -> 2000000 | Y28: =SUM(S28:V28)-W28 -> 6876040.4
B29: Monthly Personal Expenses / Spending | C29: =D29*12 -> 88055.23 | D29: =SUM(M42:M48) -> 7337.9358 | L29: Other expenses Forest Lake | M29: ='Property Expenses'!C10 -> 607.26 | P29: 23 | Q29: =Q28+30 -> 46751 | R29: =TEXT($Q29,"MMMM")&TEXT($Q29," YYYY") -> December 2027 | S29: =($V$1/12+1)*S28+T28 -> 11746747 | U29: =($V$2/12+1)*U28+$V$3 -> 552441.74 | V29: =V28+$I$65 -> 185668.75 | W29: =W28+X28 -> 7530000 | X29: =T29 -> 0 | Y29: =SUM(S29:V29)-W29 -> 4954857.3
B30: Rental Payment | C30: =D30*12 -> 0 | D30: ='Monthly Expenses Budget'!C10 -> 0 | L30: Other expenses Strathpine | M30: ='Property Expenses'!C18 -> 836.66667 | P30: 24 | Q30: =Q29+30 -> 46781 | R30: =TEXT($Q30,"MMMM")&TEXT($Q30," YYYY") -> January 2028 | S30: =($V$1/12+1)*S29+T29 -> 11815270 | U30: =($V$2/12+1)*U29+$V$3 -> 567045.43 | V30: =V29+$I$65 -> 193476.42 | W30: =W29+X29 -> 7530000 | X30: =T30 -> 0 | Y30: =SUM(S30:V30)-W30 -> 5045791.4
B31: Other | D31: =M38 -> 0 | L31: Other expenses Mt Sheridan | M31: ='Property Expenses'!C26 -> 822.87333 | P31: 25 | Q31: =Q30+30 -> 46811 | R31: =TEXT($Q31,"MMMM")&TEXT($Q31," YYYY") -> February 2028 | S31: =($V$1/12+1)*S30+T30 -> 11884192 | U31: =($V$2/12+1)*U30+$V$3 -> 581770.8 | V31: =V30+$I$65 -> 201284.1 | W31: =W30+X30 -> 7530000 | X31: =T31 -> 0 | Y31: =SUM(S31:V31)-W31 -> 5137246.8
G32: TOTAL EXPENSES | H32: (per month) | I32: =SUM(D22:D31) -> 28828.663 | L32: Other expenses Eimeo | M32: ='Property Expenses'!C34 -> 861.00667 | P32: 26 | Q32: =Q31+30 -> 46841 | R32: =TEXT($Q32,"MMMM")&TEXT($Q32," YYYY") -> March 2028 | S32: =($V$1/12+1)*S31+T31 -> 11953516 | U32: =($V$2/12+1)*U31+$V$3 -> 596618.89 | V32: =V31+$I$65 -> 209091.77 | W32: =W31+X31 -> 7530000 | X32: =T32 -> 0 | Y32: =SUM(S32:V32)-W32 -> 5229227
L33: Other expenses Investment 5 | P33: 27 | Q33: =Q32+30 -> 46871 | R33: =TEXT($Q33,"MMMM")&TEXT($Q33," YYYY") -> April 2028 | S33: =($V$1/12+1)*S32+T32 -> 12023245 | U33: =($V$2/12+1)*U32+$V$3 -> 611590.72 | V33: =V32+$I$65 -> 216899.44 | W33: =W32+X32 -> 7530000 | X33: =T33 -> 0 | Y33: =SUM(S33:V33)-W33 -> 5321735.4
B34: BALANCE SHEET | P34: 28 | Q34: =Q33+30 -> 46901 | R34: =TEXT($Q34,"MMMM")&TEXT($Q34," YYYY") -> May 2028 | S34: =($V$1/12+1)*S33+T33 -> 12093381 | U34: =($V$2/12+1)*U33+$V$3 -> 626687.31 | V34: =V33+$I$65 -> 224707.11 | W34: =W33+X33 -> 7530000 | X34: =T34 -> 0 | Y34: =SUM(S34:V34)-W34 -> 5414775.2
P35: 29 | Q35: =Q34+30 -> 46931 | R35: =TEXT($Q35,"MMMM")&TEXT($Q35," YYYY") -> June 2028 | S35: =($V$1/12+1)*S34+T34 -> 12163926 | U35: =($V$2/12+1)*U34+$V$3 -> 641909.7 | V35: =V34+$I$65 -> 232514.78 | W35: =W34+X34 -> 7530000 | X35: =T35 -> 0 | Y35: =SUM(S35:V35)-W35 -> 5508350
B36: ASSETS | E36: ASSET VALUE | G36: LIABILITIES (DEBT) | P36: 30 | Q36: =Q35+30 -> 46961 | R36: =TEXT($Q36,"MMMM")&TEXT($Q36," YYYY") -> July 2028 | S36: =($V$1/12+1)*S35+T35 -> 12234882 | U36: =($V$2/12+1)*U35+$V$3 -> 657258.95 | V36: =V35+$I$65 -> 240322.45 | W36: =W35+X35 -> 7530000 | X36: =T36 -> 0 | Y36: =SUM(S36:V36)-W36 -> 5602463.2
P37: 31 | Q37: =Q36+30 -> 46991 | R37: =TEXT($Q37,"MMMM")&TEXT($Q37," YYYY") -> August 2028 | S37: =($V$1/12+1)*S36+T36 -> 12306252 | U37: =($V$2/12+1)*U36+$V$3 -> 672736.11 | V37: =V36+$I$65 -> 248130.12 | W37: =W36+X36 -> 7530000 | X37: =T37 -> 0 | Y37: =SUM(S37:V37)-W37 -> 5697118.1
B38: Savings Account 1 | E38: =M52 -> 13900 | G38: Credit Card 1 (total limit) | I38: 10000 | L38: Other (Insert any other not covered) | P38: 32 | Q38: =Q37+30 -> 47021 | R38: =TEXT($Q38,"MMMM")&TEXT($Q38," YYYY") -> September 2028 | S38: =($V$1/12+1)*S37+T37 -> 12378038 | U38: =($V$2/12+1)*U37+$V$3 -> 688342.24 | V38: =V37+$I$65 -> 255937.79 | W38: =W37+X37 -> 7530000 | X38: =T38 -> 0 | Y38: =SUM(S38:V38)-W38 -> 5792318.4
B39: Savings Account 2 | E39: =M53 -> 8400 | G39: Credit Card 2 (total limit) | I39: 2000 | P39: 33 | Q39: =Q38+30 -> 47051 | R39: =TEXT($Q39,"MMMM")&TEXT($Q39," YYYY") -> October 2028 | S39: =($V$1/12+1)*S38+T38 -> 12450244 | U39: =($V$2/12+1)*U38+$V$3 -> 704078.43 | V39: =V38+$I$65 -> 263745.46 | W39: =W38+X38 -> 7530000 | X39: =T39 -> 0 | Y39: =SUM(S39:V39)-W39 -> 5888067.5
G40: Personal Loans | L40: From Budget Spreadsheet - DO NOT UPDATE THIS | M40: =SUM(M41:M48) -> 7337.9358 | P40: 34 | Q40: =Q39+30 -> 47081 | R40: =TEXT($Q40,"MMMM")&TEXT($Q40," YYYY") -> November 2028 | S40: =($V$1/12+1)*S39+T39 -> 12522870 | T40: =$V$4 -> 2000000 | U40: =($V$2/12+1)*U39+$V$3 -> 719945.75 | V40: =V39+$I$65 -> 271553.13 | W40: =W39+X39 -> 7530000 | X40: =T40 -> 2000000 | Y40: =SUM(S40:V40)-W40 -> 7984368.9
B41: Stocks (local) | E41: =M55 -> 0 | G41: Other Loans | L41: ='Monthly Expenses Budget'!B5 -> Home and other Fixed Expenses | M41: ='Monthly Expenses Budget'!C5 -> 0 | P41: 35 | Q41: =Q40+30 -> 47111 | R41: =TEXT($Q41,"MMMM")&TEXT($Q41," YYYY") -> December 2028 | S41: =($V$1/12+1)*S40+T40 -> 14595920 | U41: =($V$2/12+1)*U40+$V$3 -> 735945.29 | V41: =V40+$I$65 -> 279360.8 | W41: =W40+X40 -> 9530000 | X41: =T41 -> 0 | Y41: =SUM(S41:V41)-W41 -> 6081226.2
B42: Stocks (offshore) | E42: =M56 -> 0 | L42: ='Monthly Expenses Budget'!B12 -> Essentials | M42: ='Monthly Expenses Budget'!C12 -> 875.7325 | P42: 36 | Q42: =Q41+30 -> 47141 | R42: =TEXT($Q42,"MMMM")&TEXT($Q42," YYYY") -> January 2029 | S42: =($V$1/12+1)*S41+T41 -> 14681063 | U42: =($V$2/12+1)*U41+$V$3 -> 752078.17 | V42: =V41+$I$65 -> 287168.47 | W42: =W41+X41 -> 9530000 | X42: =T42 -> 0 | Y42: =SUM(S42:V42)-W42 -> 6190309.6
B43: Other stocks | E43: =M57 -> 260000 | L43: ='Monthly Expenses Budget'!B22 -> Groceries | M43: ='Monthly Expenses Budget'!C22 -> 2120 | P43: 37 | Q43: =Q42+30 -> 47171 | R43: =TEXT($Q43,"MMMM")&TEXT($Q43," YYYY") -> February 2029 | S43: =($V$1/12+1)*S42+T42 -> 14766703 | U43: =($V$2/12+1)*U42+$V$3 -> 768345.49 | V43: =V42+$I$65 -> 294976.14 | W43: =W42+X42 -> 9530000 | X43: =T43 -> 0 | Y43: =SUM(S43:V43)-W43 -> 6300024.1
L44: ='Monthly Expenses Budget'!B31 -> House Maintenance | M44: ='Monthly Expenses Budget'!C31 -> 230 | P44: 38 | Q44: =Q43+30 -> 47201 | R44: =TEXT($Q44,"MMMM")&TEXT($Q44," YYYY") -> March 2029 | S44: =($V$1/12+1)*S43+T43 -> 14852842 | U44: =($V$2/12+1)*U43+$V$3 -> 784748.37 | V44: =V43+$I$65 -> 302783.81 | W44: =W43+X43 -> 9530000 | X44: =T44 -> 0 | Y44: =SUM(S44:V44)-W44 -> 6410373.8
B45: Super 1 | E45: =M59 -> 220000 | L45: ='Monthly Expenses Budget'!B39 -> Health | M45: ='Monthly Expenses Budget'!C39 -> 1514.7033 | P45: 39 | Q45: =Q44+30 -> 47231 | R45: =TEXT($Q45,"MMMM")&TEXT($Q45," YYYY") -> April 2029 | S45: =($V$1/12+1)*S44+T44 -> 14939483 | U45: =($V$2/12+1)*U44+$V$3 -> 801287.94 | V45: =V44+$I$65 -> 310591.48 | W45: =W44+X44 -> 9530000 | X45: =T45 -> 0 | Y45: =SUM(S45:V45)-W45 -> 6521362.6
B46: Super 2 | E46: =M60 -> 200000 | L46: ='Monthly Expenses Budget'!B49 -> Discretionary | M46: ='Monthly Expenses Budget'!C49 -> 1100 | P46: 40 | Q46: =Q45+30 -> 47261 | R46: =TEXT($Q46,"MMMM")&TEXT($Q46," YYYY") -> May 2029 | S46: =($V$1/12+1)*S45+T45 -> 15026630 | U46: =($V$2/12+1)*U45+$V$3 -> 817965.34 | V46: =V45+$I$65 -> 318399.15 | W46: =W45+X45 -> 9530000 | X46: =T46 -> 0 | Y46: =SUM(S46:V46)-W46 -> 6632994.7
D47: EQUITY | L47: ='Monthly Expenses Budget'!B58 -> Sports / Activities | M47: ='Monthly Expenses Budget'!C58 -> 397.5 | P47: 41 | Q47: =Q46+30 -> 47291 | R47: =TEXT($Q47,"MMMM")&TEXT($Q47," YYYY") -> June 2029 | S47: =($V$1/12+1)*S46+T46 -> 15114286 | U47: =($V$2/12+1)*U46+$V$3 -> 834781.72 | V47: =V46+$I$65 -> 326206.83 | W47: =W46+X46 -> 9530000 | X47: =T47 -> 0 | Y47: =SUM(S47:V47)-W47 -> 6745274
B48: Home | D48: =E48-I48 -> 2328000 | E48: =M62 -> 3500000 | G48: Mortgage - Home | I48: =M75 -> 1172000 | L48: ='Monthly Expenses Budget'!B64 -> Other | M48: ='Monthly Expenses Budget'!C64 -> 1100 | P48: 42 | Q48: =Q47+30 -> 47321 | R48: =TEXT($Q48,"MMMM")&TEXT($Q48," YYYY") -> July 2029 | S48: =($V$1/12+1)*S47+T47 -> 15202452 | U48: =($V$2/12+1)*U47+$V$3 -> 851738.23 | V48: =V47+$I$65 -> 334014.5 | W48: =W47+X47 -> 9530000 | X48: =T48 -> 0 | Y48: =SUM(S48:V48)-W48 -> 6858204.9
B49: Investment 1 - Forest Lake value | D49: =E49-I49 -> 528000 | E49: =M63 -> 1040000 | G49: Investment 1 Forest Lake - Mortgage | I49: =M77 -> 512000 | P49: 43 | Q49: =Q48+30 -> 47351 | R49: =TEXT($Q49,"MMMM")&TEXT($Q49," YYYY") -> August 2029 | S49: =($V$1/12+1)*S48+T48 -> 15291133 | U49: =($V$2/12+1)*U48+$V$3 -> 868836.05 | V49: =V48+$I$65 -> 341822.17 | W49: =W48+X48 -> 9530000 | X49: =T49 -> 0 | Y49: =SUM(S49:V49)-W49 -> 6971791.4
B50: Investment 2 - Strathpine value | D50: =E50-I50 -> 350000 | E50: =M64 -> 580000 | G50: Investment 2 Strathpine - Mortgage | I50: =M78 -> 230000 | P50: 44 | Q50: =Q49+30 -> 47381 | R50: =TEXT($Q50,"MMMM")&TEXT($Q50," YYYY") -> September 2029 | S50: =($V$1/12+1)*S49+T49 -> 15380331 | U50: =($V$2/12+1)*U49+$V$3 -> 886076.35 | V50: =V49+$I$65 -> 349629.84 | W50: =W49+X49 -> 9530000 | X50: =T50 -> 0 | Y50: =SUM(S50:V50)-W50 -> 7086037.6
B51: Investment 3 - Mt Sheridan value | D51: =E51-I51 -> -20000 | E51: =M65 -> 760000 | G51: Investment 3 Mt Sheridan - Mortgage | I51: =M79 -> 780000 | L51: ASSETS | P51: 45 | Q51: =Q50+30 -> 47411 | R51: =TEXT($Q51,"MMMM")&TEXT($Q51," YYYY") -> October 2029 | S51: =($V$1/12+1)*S50+T50 -> 15470050 | U51: =($V$2/12+1)*U50+$V$3 -> 903460.32 | V51: =V50+$I$65 -> 357437.51 | W51: =W50+X50 -> 9530000 | X51: =T51 -> 0 | Y51: =SUM(S51:V51)-W51 -> 7200947.8
B52: Investment 4 - Eimeo value | D52: =E52-I52 -> -4000 | E52: =M66 -> 820000 | G52: Investment 4 Eimeo - Mortgage | I52: =M80 -> 824000 | L52: Savings (account 1) | M52: 13900 | P52: 46 | Q52: =Q51+30 -> 47441 | R52: =TEXT($Q52,"MMMM")&TEXT($Q52," YYYY") -> November 2029 | S52: =($V$1/12+1)*S51+T51 -> 15560292 | T52: =$V$4 -> 2000000 | U52: =($V$2/12+1)*U51+$V$3 -> 920989.15 | V52: =V51+$I$65 -> 365245.18 | W52: =W51+X51 -> 9530000 | X52: =T52 -> 2000000 | Y52: =SUM(S52:V52)-W52 -> 9316526.3
B53: Investment 5 - value | D53: =E53-I53 -> 0 | E53: =M67 -> 0 | G53: Investment 5 - Mortgage | I53: =M81 -> 0 | L53: Savings (account 2) | M53: 8400 | P53: 47 | Q53: =Q52+30 -> 47471 | R53: =TEXT($Q53,"MMMM")&TEXT($Q53," YYYY") -> December 2029 | S53: =($V$1/12+1)*S52+T52 -> 17651060 | U53: =($V$2/12+1)*U52+$V$3 -> 938664.06 | V53: =V52+$I$65 -> 373052.85 | W53: =W52+X52 -> 11530000 | X53: =T53 -> 0 | Y53: =SUM(S53:V53)-W53 -> 7432777.3
P54: 48 | Q54: =Q53+30 -> 47501 | R54: =TEXT($Q54,"MMMM")&TEXT($Q54," YYYY") -> January 2030 | S54: =($V$1/12+1)*S53+T53 -> 17754025 | U54: =($V$2/12+1)*U53+$V$3 -> 956486.27 | V54: =V53+$I$65 -> 380860.52 | W54: =W53+X53 -> 11530000 | X54: =T54 -> 0 | Y54: =SUM(S54:V54)-W54 -> 7561371.6
L55: Stocks / Shares (ASX) | M55: 0 | P55: 49 | Q55: =Q54+30 -> 47531 | R55: =TEXT($Q55,"MMMM")&TEXT($Q55," YYYY") -> February 2030 | S55: =($V$1/12+1)*S54+T54 -> 17857590 | U55: =($V$2/12+1)*U54+$V$3 -> 974456.98 | V55: =V54+$I$65 -> 388668.19 | W55: =W54+X54 -> 11530000 | X55: =T55 -> 0 | Y55: =SUM(S55:V55)-W55 -> 7690715.2
B56: TOTAL ASSETS (including Super) | E56: =SUM(E38:E55) -> 7402300 | L56: Stocks / Shares (NASDAQ Other) | M56: 0 | P56: 50 | Q56: =Q55+30 -> 47561 | R56: =TEXT($Q56,"MMMM")&TEXT($Q56," YYYY") -> March 2030 | S56: =($V$1/12+1)*S55+T55 -> 17961759 | U56: =($V$2/12+1)*U55+$V$3 -> 992577.46 | V56: =V55+$I$65 -> 396475.86 | W56: =W55+X55 -> 11530000 | X56: =T56 -> 0 | Y56: =SUM(S56:V56)-W56 -> 7820812.6
B57: TOTAL ASSETS | E57: =SUM(E56-E46-E45) -> 6982300 | G57: TOTAL LIABILITY | I57: =SUM(I38:I56) -> 3530000 | L57: Pending Settlement amount | M57: 260000 | P57: 51 | Q57: =Q56+30 -> 47591 | R57: =TEXT($Q57,"MMMM")&TEXT($Q57," YYYY") -> April 2030 | S57: =($V$1/12+1)*S56+T56 -> 18066536 | U57: =($V$2/12+1)*U56+$V$3 -> 1010848.9 | V57: =V56+$I$65 -> 404283.53 | W57: =W56+X56 -> 11530000 | X57: =T57 -> 0 | Y57: =SUM(S57:V57)-W57 -> 7951668.7
P58: 52 | Q58: =Q57+30 -> 47621 | R58: =TEXT($Q58,"MMMM")&TEXT($Q58," YYYY") -> May 2030 | S58: =($V$1/12+1)*S57+T57 -> 18171924 | U58: =($V$2/12+1)*U57+$V$3 -> 1029272.7 | V58: =V57+$I$65 -> 412091.2 | W58: =W57+X57 -> 11530000 | X58: =T58 -> 0 | Y58: =SUM(S58:V58)-W58 -> 8083288.2
L59: Super 1 | M59: 220000 | P59: 53 | Q59: =Q58+30 -> 47651 | R59: =TEXT($Q59,"MMMM")&TEXT($Q59," YYYY") -> June 2030 | S59: =($V$1/12+1)*S58+T58 -> 18277927 | U59: =($V$2/12+1)*U58+$V$3 -> 1047850 | V59: =V58+$I$65 -> 419898.87 | W59: =W58+X58 -> 11530000 | X59: =T59 -> 0 | Y59: =SUM(S59:V59)-W59 -> 8215676.1
